Workbook

Sheet DNI
A1: DELGADO SECLEN ALVARO ELISEO | B1: 80640163
A2: ALVAREZ ALVINES JUAN MANUEL | B2: 46108491
A3: AMAYA CAPUÑAY JOSE ENRIQUE | B3: 45686225
A4: AQUINO SILVA DANTE JESUS ALEXIS | B4: 74863779
A5: AQUINO TEJEDA JUAN JOSE | B5: 80483542
A6: AYALA RAMIREZ RUBEN ISAI | B6: 75557820
A7: BALLENA ADANAQUE MIGUEL ANGEL | B7: 48446313
A8: LABAN SEVERINO EDWIN DENIS | B8: 47466045
A9: MEDINA GUEVARA TIRSO | B9: 16792081
A10: BONILLA RADAELLI CARLOS EDUARDO | B10: 73130745
A11: BUSTAMANTE GONZALES CARLOS | B11: 27291529
A12: CAMIZAN CUNIAS LENDER NEYDEN | B12: 47711616
... A94: CASTILLO LOYOLA ANTONIO | B94: 42435768
A95: SALAZAR AQUINO IRVIN
A96: PLATA ESCALANTE SERGIO | B96: 3548110
A97: SANCHEZ MEOÑO FRANK | B97: 72684512
A98: SOLANO SUELDO CARLOS | B98: 44676684
A99: VIDAURRE YOVERA JOSE | B99: 43705902

Sheet RUBRO
A1: N° | B1: COD. | C1: ESTACION DE TRABAJO | D1: PUESTO DE TRABAJO: PRODUCCION | F1: DNI | G1: CODIGO | H1: PERFIL | I1: ESTACION DE TRABAJO | J1: DETALLE DE PERFIL | K1: OPERARIO | L1: RENTA | M1: DIARIO | N1: EMPRESA | O1: ITEM | Q1: N° | R1: LUGAR | S1: HORAS | T1: ALMUERZO | W1: FECHA | X1: DOMINICAL | Y1: DIA | Z1: DETALLE | AA1: CÓDIGO
A2: 1 | B2: MAE-06 | C2: CORTE Y PLEGADO | D2: MAESTRO DE CORTE Y PLEGADO | F2: =VLOOKUP(K2,DNI!$A$1:$B$10000,2,FALSE) -> 80640163 | G2: =H2&-O2 -> MAE-02-1 | H2: MAE-02 | I2: MONTAJE MN | J2: MAESTRO MECANICO MONTAJISTA DE MAQUINARIA | K2: DELGADO SECLEN ALVARO ELISEO | L2: 5ta | M2: 83.333333 | N2: DELCOR | O2: 001 | Q2: 1 | R2: PLANTA | S2: 0.375 | T2: 0.54166667 | U2: 0.58333333 | W2: 43831 | Y2: =TEXT(W2,"ddddd") -> miércoles | Z2: año nuevo | AA2: 1 | AC2: 0.041666667 | AD2: 0.54166667
A3: 2 | B3: OPE-06 | C3: CORTE Y PLEGADO | D3: OPERARIO DE CORTE Y PLEGADO | F3: =VLOOKUP(K3,DNI!$A$1:$B$10000,2,FALSE) -> 46108491 | G3: =H3&-O3 -> TEC-02-2 | H3: TEC-02 | I3: MONTAJE MN | J3: TECNICO MECANICO MONTAJISTA DE MAQUINARIA | K3: ALVAREZ ALVINES JUAN MANUEL | L3: 5ta | M3: 50 | N3: MECANOS | O3: 002 | Q3: 2 | R3: OBRA | S3: 0.33333333 | T3: 0.54166667 | U3: 0.58333333 | W3: 43832 | Y3: =TEXT(W3,"ddddd") -> jueves | AC3: 0.083333333
A4: 3 | B4: MAEME-03 | C4: ELECTRICIDAD | D4: MAESTRO ELECTRICO MONTAJISTA DE MAQUINARIA EXTRANJERA | F4: =VLOOKUP(K4,DNI!$A$1:$B$10000,2,FALSE) -> 45686225 | G4: =H4&-O4 -> TEC-02-3 | H4: TEC-02 | I4: MONTAJE MN | J4: TECNICO MECANICO MONTAJISTA DE MAQUINARIA | K4: AMAYA CAPUÑAY JOSE ENRIQUE | L4: 4ta | M4: 60 | N4: MECANOS | O4: 003 | Q4: 3 | R4: DESCANSO | W4: 43833 | Y4: =TEXT(W4,"ddddd") -> viernes | AC4: 0.125
A5: 4 | B5: OPE-03 | C5: ELECTRICIDAD | D5: OPERARIO ELECTRICO | F5: =VLOOKUP(K5,DNI!$A$1:$B$10000,2,FALSE) -> 74863779 | G5: =H5&-O5 -> AYU-VA-4 | H5: AYU-VA | I5: VARIAS | J5: AYUDANTE DE PRODUCCION | K5: AQUINO SILVA DANTE JESUS ALEXIS | L5: 4ta | M5: 40 | N5: MECANOS | O5: 004 | Q5: 4 | R5: FALTA | W5: 43834 | Y5: =TEXT(W5,"ddddd") -> sábado | AC5: 0.16666667
A6: 5 | B6: TECME-03 | C6: ELECTRICIDAD | D6: TECNICO ELECTRICO MONTAJISTA DE MAQUINARIA EXTRANJERA | F6: =VLOOKUP(K6,DNI!$A$1:$B$10000,2,FALSE) -> 80483542 | G6: =H6&-O6 -> AYU-VA-5 | H6: AYU-VA | I6: VARIAS | J6: AYUDANTE DE PRODUCCION | K6: AQUINO TEJEDA JUAN JOSE | L6: 4ta | M6: 45 | N6: MECANOS | O6: 005 | Q6: 5 | R6: | | W6: 43835 | X6: 1 | Y6: =TEXT(W6,"ddddd") -> domingo | AC6: 0.20833333
A7: 6 | B7: TECMN-03 | C7: ELECTRICIDAD | D7: TECNICO ELECTRICO MONTAJISTA DE MAQUINARIA | F7: =VLOOKUP(K7,DNI!$A$1:$B$10000,2,FALSE) -> 75557820 | G7: =H7&-O7 -> OPE-03-6 | H7: OPE-03 | I7: ELECTRICIDAD | J7: OPERARIO ELECTRICO | K7: AYALA RAMIREZ RUBEN ISAI | L7: 4ta | M7: 50 | N7: MECANOS | O7: 006 | Q7: 6 | R7: LICENCIA SIN GOCE | W7: 43836 | Y7: =TEXT(W7,"ddddd") -> lunes | AC7: 0.25
A8: 7 | B8: MAE-07 | C8: FACTORIA | D8: MAESTRO MECANICO DE FACTORIA | F8: =VLOOKUP(K8,DNI!$A$1:$B$10000,2,FALSE) -> 48446313 | G8: =H8&-O8 -> TEC-02-7 | H8: TEC-02 | I8: MONTAJE MN | J8: TECNICO MECANICO MONTAJISTA DE MAQUINARIA | K8: BALLENA ADANAQUE MIGUEL ANGEL | L8: 4ta | M8: 50 | N8: MECANOS | O8: 007 | Q8: 7 | R8: DESCANSO MEDICO | W8: 43837 | Y8: =TEXT(W8,"ddddd") -> martes | AC8: 0.29166667
A9: 8 | B9: TEC-07 | C9: FACTORIA | D9: TECNICO MECANICO DE FACTORIA | F9: =VLOOKUP(K9,DNI!$A$1:$B$10000,2,FALSE) -> 10664396 | G9: =H9&-O9 -> OPE-01-8 | H9: OPE-01 | I9: SOLDADURA | J9: OPERARIO SOLDADOR | K9: BENDEZU PISCO JORGE GUILLERMO | L9: 5ta | M9: 60 | N9: MECANOS | O9: 008 | Q9: 8 | R9: H.EXTRAS 5TA | S9: 0.33333333 | T9: 0.54166667 | U9: 0.58333333 | W9: 43838 | Y9: =TEXT(W9,"ddddd") -> miércoles | AC9: 0.33333333
A10: 9 | B10: MAE-04 | C10: MONTAJE ME | D10: MAESTRO MECANICO MONTAJISTA DE MAQUINARIA EXTRANJERA | F10: =VLOOKUP(K10,DNI!$A$1:$B$10000,2,FALSE) -> 71995358 | G10: =H10&-O10 -> OPE-01-9 | H10: OPE-01 | I10: SOLDADURA | J10: OPERARIO SOLDADOR | K10: BONILLA CHAVEZ LUIS DANIEL | L10: 4ta | M10: 45 | N10: MECANOS | O10: 009 | W10: 43839 | Y10: =TEXT(W10,"ddddd") -> jueves | AC10: 0.375
A11: 10 | B11: MEC-04 | C11: MONTAJE ME | D11: MECANICO MONTAJISTA DE MAQUINARIA EXTRANJERA | F11: =VLOOKUP(K11,DNI!$A$1:$B$10000,2,FALSE) -> 73130745 | G11: =H11&-O11 -> AYU-VA-10 | H11: AYU-VA | I11: VARIAS | J11: AYUDANTE DE PRODUCCION | K11: BONILLA RADAELLI CARLOS EDUARDO | L11: 4ta | M11: 40 | N11: MECANOS | O11: 010 | W11: 43840 | Y11: =TEXT(W11,"ddddd") -> viernes | AC11: 0.41666667
A12: 11 | B12: TEC-04 | C12: MONTAJE ME | D12: TECNICO MECANICO MONTAJISTA DE MAQUINARIA EXTRANJERA | F12: =VLOOKUP(K12,DNI!$A$1:$B$10000,2,FALSE) -> 27291529 | G12: =H12&-O12 -> MEC-04-11 | H12: MEC-04 | I12: MONTAJE ME | J12: MECANICO MONTAJISTA DE MAQUINARIA EXTRANJERA | K12: BUSTAMANTE GONZALES CARLOS | L12: 5ta | M12: 72.54 | N12: MECANOS | O12: 011 | W12: 43841 | Y12: =TEXT(W12,"ddddd") -> sábado | AC12: 0.45833333
A13: 12 | B13: MAE-02 | C13: MONTAJE MN | D13: MAESTRO MECANICO MONTAJISTA DE MAQUINARIA | F13: =VLOOKUP(K13,DNI!$A$1:$B$10000,2,FALSE) -> 47711616 | G13: =H13&-O13 -> TECMN-03-12 | H13: TECMN-03 | I13: ELECTRICIDAD | J13: TECNICO ELECTRICO MONTAJISTA DE MAQUINARIA | K13: CAMIZAN CUNIAS LENDER NEYDEN | L13: 5ta | M13: 47.73 | N13: MECANOS | O13: 012 | W13: 43842 | X13: 1 | Y13: =TEXT(W13,"ddddd") -> domingo | AC13: 0.5
A14: 13 | B14: MEC-02 | C14: MONTAJE MN | D14: MECANICO MONTAJISTA DE MAQUINARIA | F14: =VLOOKUP(K14,DNI!$A$1:$B$10000,2,FALSE) -> 48237026 | G14: =H14&-O14 -> TEC-05-13 | H14: TEC-05 | I14: MONTAJE NAVE | J14: TECNICO MECANICO MONTAJISTA DE NAVE INDUSTRIAL | K14: CAVERO ANCAJIMA JHONATAN | L14: 5ta | M14: 52.2 | N14: MECANOS | O14: 013 | W14: 43843 | Y14: =TEXT(W14,"ddddd") -> lunes | AC14: 0.54166667
A15: 14 | B15: TEC-02 | C15: MONTAJE MN | D15: TECNICO MECANICO MONTAJISTA DE MAQUINARIA | F15: =VLOOKUP(K15,DNI!$A$1:$B$10000,2,FALSE) -> 47055982 | G15: =H15&-O15 -> TECME-03-14 | H15: TECME-03 | I15: ELECTRICIDAD | J15: TECNICO ELECTRICO MONTAJISTA DE MAQUINARIA EXTRANJERA | K15: CHAQUILA JIMENEZ VICTOR JHEYNER | L15: 5ta | M15: 73.72 | N15: MECANOS | O15: 014 | W15: 43844 | Y15: =TEXT(W15,"ddddd") -> martes | AC15: 0.58333333
A16: 15 | B16: AYU-05 | C16: MONTAJE NAVE | D16: AYUDANTE MONTAJISTA DE NAVE INDUSTRIAL | F16: =VLOOKUP(K16,DNI!$A$1:$B$10000,2,FALSE) -> 44983080 | G16: =H16&-O16 -> OPE-01-15 | H16: OPE-01 | I16: SOLDADURA | J16: OPERARIO SOLDADOR | K16: CHAVESTA LLUEN WALTER OMAR | L16: 4ta | M16: 75 | N16: TALLERES | O16: 015 | W16: 43845 | Y16: =TEXT(W16,"ddddd") -> miércoles | AC16: 0.625
A17: 16 | B17: MAE-05 | C17: MONTAJE NAVE | D17: MAESTRO MECANICO MONTAJISTA DE NAVE INDUSTRIAL | F17: =VLOOKUP(K17,DNI!$A$1:$B$10000,2,FALSE) -> 75322465 | G17: =H17&-O17 -> AYU-VA-16 | H17: AYU-VA | I17: VARIAS | J17: AYUDANTE DE PRODUCCION | K17: CHERO AYALA JOSE ISMAEL | L17: 4ta | M17: 60 | N17: MECANOS | O17: 016 | W17: 43846 | Y17: =TEXT(W17,"ddddd") -> jueves | AC17: 0.66666667
A18: 17 | B18: TEC-05 | C18: MONTAJE NAVE | D18: TECNICO MECANICO MONTAJISTA DE NAVE INDUSTRIAL | F18: =VLOOKUP(K18,DNI!$A$1:$B$10000,2,FALSE) -> 74359947 | G18: =H18&-O18 -> OPE-01-17 | H18: OPE-01 | I18: SOLDADURA | J18: OPERARIO SOLDADOR | K18: CORDOVA OJEDA JHON GIAMPIERRE | L18: 5ta | M18: 57.62 | N18: MECANOS | O18: 017 | W18: 43847 | Y18: =TEXT(W18,"ddddd") -> viernes | AC18: 0.70833333
A19: 18 | B19: MAE-08 | C19: PINTURA | D19: MAESTRO PINTOR | F19: =VLOOKUP(K19,DNI!$A$1:$B$10000,2,FALSE) -> 75461003 | G19: =H19&-O19 -> OPE-03-18 | H19: OPE-03 | I19: ELECTRICIDAD | J19: OPERARIO ELECTRICO | K19: CORONADO MONJE JEAN CARLOS | L19: 4ta | M19: 40 | N19: MECANOS | O19: 018 | W19: 43848 | Y19: =TEXT(W19,"ddddd") -> sábado | AC19: 0.75
A20: 19 | B20: MAE3G-01 | C20: SOLDADURA | D20: MAESTRO SOLDADOR 3G | F20: =VLOOKUP(K20,DNI!$A$1:$B$10000,2,FALSE) -> 47321409 | G20: =H20&-O20 -> TEC-02-19 | H20: TEC-02 | I20: MONTAJE MN | J20: TECNICO MECANICO MONTAJISTA DE MAQUINARIA | K20: CORREA TORRES NOYLER | L20: 5ta | M20: 65 | N20: MECANOS | O20: 019 | W20: 43849 | X20: 1 | Y20: =TEXT(W20,"ddddd") -> domingo | AC20: 0.79166667
A21: 20 | B21: MAE6G-01 | C21: SOLDADURA | D21: MAESTRO SOLDADOR 6G MONTAJISTA DE MAQUINARIA | F21: =VLOOKUP(K21,DNI!$A$1:$B$10000,2,FALSE) -> 70133802 | G21: =H21&-O21 -> TEC-04-20 | H21: TEC-04 | I21: MONTAJE ME | J21: TECNICO MECANICO MONTAJISTA DE MAQUINARIA EXTRANJERA | K21: CUYA CAYCHO DANIEL LORENZO | L21: 5ta | M21: 66.92 | N21: MECANOS | O21: 020 | W21: 43850 | Y21: =TEXT(W21,"ddddd") -> lunes | AC21: 0.83333333
A22: 21 | B22: OPE-01 | C22: SOLDADURA | D22: OPERARIO SOLDADOR | F22: =VLOOKUP(K22,DNI!$A$1:$B$10000,2,FALSE) -> 42558469 | G22: =H22&-O22 -> OPE-01-21 | H22: OPE-01 | I22: SOLDADURA | J22: OPERARIO SOLDADOR | K22: ENRIQUEZ GONZALES MIGUEL ANGEL | L22: 4ta | M22: 60 | N22: MECANOS | O22: 021 | W22: 43851 | Y22: =TEXT(W22,"ddddd") -> martes | AC22: 0.875
A23: 22 | B23: TEC-01 | C23: SOLDADURA | D23: TECNICO SOLDADOR | F23: =VLOOKUP(K23,DNI!$A$1:$B$10000,2,FALSE) -> 73147673 | G23: =H23&-O23 -> OPE-01-22 | H23: OPE-01 | I23: SOLDADURA | J23: OPERARIO SOLDADOR | K23: ESPINOZA CHANAME DIEGO ARMANDO | L23: 5ta | M23: 55 | N23: MECANOS | O23: 022 | W23: 43852 | Y23: =TEXT(W23,"ddddd") -> miércoles | AC23: 0.91666667
A24: 23 | B24: AYU-VA | C24: VARIAS | D24: AYUDANTE DE PRODUCCION | F24: 47555533 | G24: =H24&-O24 -> TEC-02-23 | H24: TEC-02 | I24: MONTAJE MN | J24: TECNICO MECANICO MONTAJISTA DE MAQUINARIA | K24: FLORES TINEO JOSE ANGEL | L24: 4ta | M24: 60 | N24: MECANOS | O24: 023 | W24: 43853 | Y24: =TEXT(W24,"ddddd") -> jueves | AC24: 0.95833333
F25: =VLOOKUP(K25,DNI!$A$1:$B$10000,2,FALSE) -> 48046568 | G25: =H25&-O25 -> MAE-02-24 | H25: MAE-02 | I25: MONTAJE MN | J25: MAESTRO MECANICO MONTAJISTA DE MAQUINARIA | K25: GRAUS JUAREZ MIGUEL RICARDO | L25: 5ta | M25: 68.15 | N25: MECANOS | O25: 024 | W25: 43854 | Y25: =TEXT(W25,"ddddd") -> viernes | AC25: 1
F26: =VLOOKUP(K26,DNI!$A$1:$B$10000,2,FALSE) -> 45545014 | G26: =H26&-O26 -> TEC-01-25 | H26: TEC-01 | I26: SOLDADURA | J26: TECNICO SOLDADOR | K26: GUEVARA PACHERREZ ERICK DANIEL | L26: 4ta | M26: 60 | N26: MECANOS | O26: 025 | W26: 43855 | Y26: =TEXT(W26,"ddddd") -> sábado
F27: =VLOOKUP(K27,DNI!$A$1:$B$10000,2,FALSE) -> 70858509 | G27: =H27&-O27 -> TEC-01-26 | H27: TEC-01 | I27: SOLDADURA | J27: TECNICO SOLDADOR | K27: HUAMAN CAMPOS BRIAN ROY | L27: 4ta | M27: 60 | N27: MECANOS | O27: 026 | W27: 43856 | X27: 1 | Y27: =TEXT(W27,"ddddd") -> domingo
F28: =VLOOKUP(K28,DNI!$A$1:$B$10000,2,FALSE) -> 46228460 | G28: =H28&-O28 -> TEC-04-27 | H28: TEC-04 | I28: MONTAJE ME | J28: TECNICO MECANICO MONTAJISTA DE MAQUINARIA EXTRANJERA | K28: IDROGO CHAVEZ EMANUEL | L28: 5ta | M28: 67.66 | N28: MECANOS | O28: 027 | W28: 43857 | Y28: =TEXT(W28,"ddddd") -> lunes
F29: =VLOOKUP(K29,DNI!$A$1:$B$10000,2,FALSE) -> 47466045 | G29: =H29&-O29 -> MAE3G-01-28 | H29: MAE3G-01 | I29: SOLDADURA | J29: MAESTRO SOLDADOR 3G | K29: LABAN SEVERINO EDWIN DENIS | L29: 5ta | M29: 70.38 | N29: MECANOS | O29: 028 | W29: 43858 | Y29: =TEXT(W29,"ddddd") -> martes
F30: =VLOOKUP(K30,DNI!$A$1:$B$10000,2,FALSE) -> 62188868 | G30: =H30&-O30 -> AYU-VA-29 | H30: AYU-VA | I30: VARIAS | J30: AYUDANTE DE PRODUCCION | K30: LOPEZ TANTARICO ELY | L30: 5ta | M30: 39.15 | N30: MECANOS | O30: 029 | W30: 43859 | Y30: =TEXT(W30,"ddddd") -> miércoles
F31: =VLOOKUP(K31,DNI!$A$1:$B$10000,2,FALSE) -> 16792081 | G31: =H31&-O31 -> MAE3G-01-30 | H31: MAE3G-01 | I31: SOLDADURA | J31: MAESTRO SOLDADOR 3G | K31: MEDINA GUEVARA TIRSO | L31: 4ta | M31: 85 | N31: MECANOS | O31: 030 | W31: 43860 | Y31: =TEXT(W31,"ddddd") -> jueves
F32: =VLOOKUP(K32,DNI!$A$1:$B$10000,2,FALSE) -> 73541627 | G32: =H32&-O32 -> TEC-02-31 | H32: TEC-02 | I32: MONTAJE MN | J32: TECNICO MECANICO MONTAJISTA DE MAQUINARIA | K32: MEJIA AYALA LUIS MANUEL | L32: 5ta | M32: 55 | N32: MECANOS | O32: 031 | W32: 43861 | Y32: =TEXT(W32,"ddddd") -> viernes
F33: =VLOOKUP(K33,DNI!$A$1:$B$10000,2,FALSE) -> 76811302 | G33: =H33&-O33 -> TEC-04-32 | H33: TEC-04 | I33: MONTAJE ME | J33: TECNICO MECANICO MONTAJISTA DE MAQUINARIA EXTRANJERA | K33: MEREGILDO CABRERA RICARDO JOEL | L33: 5ta | M33: 60 | N33: MECANOS | O33: 032 | W33: 43862 | Y33: =TEXT(W33,"ddddd") -> sábado
F34: =VLOOKUP(K34,DNI!$A$1:$B$10000,2,FALSE) -> 76457697 | G34: =H34&-O34 -> AYU-VA-33 | H34: AYU-VA | I34: VARIAS | J34: AYUDANTE DE PRODUCCION | K34: MIO QUIÑONES ALEXIS | L34: 5ta | M34: 45 | N34: MECANOS | O34: 033 | W34: 43863 | X34: 1 | Y34: =TEXT(W34,"ddddd") -> domingo
F35: =VLOOKUP(K35,DNI!$A$1:$B$10000,2,FALSE) -> 47586740 | G35: =H35&-O35 -> TEC-02-34 | H35: TEC-02 | I35: MONTAJE MN | J35: TECNICO MECANICO MONTAJISTA DE MAQUINARIA | K35: MIO SOLUCO CESAR AUGUSTO | L35: 4ta | M35: 60 | N35: MECANOS | O35: 034 | W35: 43864 | Y35: =TEXT(W35,"ddddd") -> lunes
F36: =VLOOKUP(K36,DNI!$A$1:$B$10000,2,FALSE) -> 72241927 | G36: =H36&-O36 -> MAE-05-35 | H36: MAE-05 | I36: MONTAJE NAVE | J36: MAESTRO MECANICO MONTAJISTA DE NAVE INDUSTRIAL | K36: OJANAMA UTIA ENERLI HORACIO | L36: 5ta | M36: 70 | N36: MECANOS | O36: 035 | W36: 43865 | Y36: =TEXT(W36,"ddddd") -> martes
F37: =VLOOKUP(K37,DNI!$A$1:$B$10000,2,FALSE) -> 76785790 | G37: =H37&-O37 -> AYU-VA-36 | H37: AYU-VA | I37: VARIAS | J37: AYUDANTE DE PRODUCCION | K37: OJANAMA UTIA MARTIN SOLANO | L37: 4ta | M37: 45 | N37: MECANOS | O37: 036 | W37: 43866 | Y37: =TEXT(W37,"ddddd") -> miércoles
F38: =VLOOKUP(K38,DNI!$A$1:$B$10000,2,FALSE) -> 72241926 | G38: =H38&-O38 -> AYU-VA-37 | H38: AYU-VA | I38: VARIAS | J38: AYUDANTE DE PRODUCCION | K38: OJANAMA UTIA TEOFILO ALVINO | L38: 4ta | M38: 45 | N38: MECANOS | O38: 037 | W38: 43867 | Y38: =TEXT(W38,"ddddd") -> jueves
F39: =VLOOKUP(K39,DNI!$A$1:$B$10000,2,FALSE) -> 45821420 | G39: =H39&-O39 -> TEC-05-38 | H39: TEC-05 | I39: MONTAJE NAVE | J39: TECNICO MECANICO MONTAJISTA DE NAVE INDUSTRIAL | K39: ORTIZ PANTALEON POLH MANIX | L39: 5ta | M39: 56.55 | N39: MECANOS | O39: 038 | W39: 43868 | Y39: =TEXT(W39,"ddddd") -> viernes
F40: =VLOOKUP(K40,DNI!$A$1:$B$10000,2,FALSE) -> 47887505 | G40: =H40&-O40 -> TEC-01-39 | H40: TEC-01 | I40: SOLDADURA | J40: TECNICO SOLDADOR | K40: PANDO SALAZAR LUIS BRYAN | L40: 5ta | M40: 66.48 | N40: MECANOS | O40: 039 | W40: 43869 | Y40: =TEXT(W40,"ddddd") -> sábado
F41: =VLOOKUP(K41,DNI!$A$1:$B$10000,2,FALSE) -> 47942907 | G41: =H41&-O41 -> MEC-02-40 | H41: MEC-02 | I41: MONTAJE MN | J41: MECANICO MONTAJISTA DE MAQUINARIA | K41: PEREZ VASQUEZ RONAL | L41: 5ta | M41: 75 | N41: MECANOS | O41: 040 | W41: 43870 | X41: 1 | Y41: =TEXT(W41,"ddddd") -> domingo
F42: =VLOOKUP(K42,DNI!$A$1:$B$10000,2,FALSE) -> 48372384 | G42: =H42&-O42 -> TEC-02-41 | H42: TEC-02 | I42: MONTAJE MN | J42: TECNICO MECANICO MONTAJISTA DE MAQUINARIA | K42: PURIZACA CHUÑE JHON ANDERSON | L42: 5ta | M42: 57.62 | N42: MECANOS | O42: 041 | W42: 43871 | Y42: =TEXT(W42,"ddddd") -> lunes
F43: =VLOOKUP(K43,DNI!$A$1:$B$10000,2,FALSE) -> 42308744 | G43: =H43&-O43 -> MAE-02-42 | H43: MAE-02 | I43: MONTAJE MN | J43: MAESTRO MECANICO MONTAJISTA DE MAQUINARIA | K43: PURIZACA SEVERINO DANIEL FERNANDO | L43: 5ta | M43: 87.1 | N43: MECANOS | O43: 042 | W43: 43872 | Y43: =TEXT(W43,"ddddd") -> martes
F44: 45486657 | G44: =H44&-O44 -> MAE3G-01-43 | H44: MAE3G-01 | I44: SOLDADURA | J44: MAESTRO SOLDADOR 3G | K44: QUIROZ CORTEJANA DANTE GABRIEL | L44: 4ta | M44: 90 | N44: MECANOS | O44: 043 | W44: 43873 | Y44: =TEXT(W44,"ddddd") -> miércoles
F45: =VLOOKUP(K45,DNI!$A$1:$B$10000,2,FALSE) -> 45779525 | G45: =H45&-O45 -> MAEME-03-44 | H45: MAEME-03 | I45: ELECTRICIDAD | J45: MAESTRO ELECTRICO MONTAJISTA DE MAQUINARIA EXTRANJERA | K45: RAMIREZ PELAEZ ELIAS | L45: 5ta | M45: 116.06 | N45: MECANOS | O45: 044 | W45: 43874 | Y45: =TEXT(W45,"ddddd") -> jueves
F46: =VLOOKUP(K46,DNI!$A$1:$B$10000,2,FALSE) -> 77423720 | G46: =H46&-O46 -> MAE3G-01-45 | H46: MAE3G-01 | I46: SOLDADURA | J46: MAESTRO SOLDADOR 3G | K46: RIOJA RODRIGUEZ MARCO JEAIR | L46: 5ta | M46: 69.44 | N46: MECANOS | O46: 045 | W46: 43875 | Y46: =TEXT(W46,"ddddd") -> viernes
F47: =VLOOKUP(K47,DNI!$A$1:$B$10000,2,FALSE) -> 45035778 | G47: =H47&-O47 -> MAE6G-01-46 | H47: MAE6G-01 | I47: SOLDADURA | J47: MAESTRO SOLDADOR 6G MONTAJISTA DE MAQUINARIA | K47: RIVERA LEONARDO EVER JOSE | L47: 5ta | M47: 92.8 | N47: MECANOS | O47: 046 | W47: 43876 | Y47: =TEXT(W47,"ddddd") -> sábado
F48: =VLOOKUP(K48,DNI!$A$1:$B$10000,2,FALSE) -> 72926564 | G48: =H48&-O48 -> MAE-04-47 | H48: MAE-04 | I48: MONTAJE ME | J48: MAESTRO MECANICO MONTAJISTA DE MAQUINARIA EXTRANJERA | K48: ROMERO MARIN JAIRO JOEL | L48: 5ta | M48: 88.27 | N48: MECANOS | O48: 047 | W48: 43877 | X48: 1 | Y48: =TEXT(W48,"ddddd") -> domingo
F49: =VLOOKUP(K49,DNI!$A$1:$B$10000,2,FALSE) -> 76022523 | G49: =H49&-O49 -> AYU-VA-48 | H49: AYU-VA | I49: VARIAS | J49: AYUDANTE DE PRODUCCION | K49: SANCHEZ SALAS ISAAC | L49: 4ta | M49: 45 | N49: MECANOS | O49: 048 | W49: 43878 | Y49: =TEXT(W49,"ddddd") -> lunes
F50: =VLOOKUP(K50,DNI!$A$1:$B$10000,2,FALSE) -> 43543039 | G50: =H50&-O50 -> MAE3G-01-49 | H50: MAE3G-01 | I50: SOLDADURA | J50: MAESTRO SOLDADOR 3G | K50: SANCHEZ ZEÑA LUIS ALFREDO | L50: 5ta | M50: 69.64 | N50: MECANOS | O50: 049 | W50: 43879 | Y50: =TEXT(W50,"ddddd") -> martes
F51: =VLOOKUP(K51,DNI!$A$1:$B$10000,2,FALSE) -> 45360771 | G51: =H51&-O51 -> MEC-04-50 | H51: MEC-04 | I51: MONTAJE ME | J51: MECANICO MONTAJISTA DE MAQUINARIA EXTRANJERA | K51: SANDOVAL CHAPOÑAN ELVIS EDUARDO | L51: 5ta | M51: 94.35 | N51: MECANOS | O51: 050 | W51: 43880 | Y51: =TEXT(W51,"ddddd") -> miércoles
F52: =VLOOKUP(K52,DNI!$A$1:$B$10000,2,FALSE) -> 75952484 | G52: =H52&-O52 -> AYU-VA-51 | H52: AYU-VA | I52: VARIAS | J52: AYUDANTE DE PRODUCCION | K52: SIESQUEN BANCES ALEX HUMBERTO | L52: 4ta | M52: 45 | N52: TALLERES | O52: 051 | W52: 43881 | Y52: =TEXT(W52,"ddddd") -> jueves
F53: =VLOOKUP(K53,DNI!$A$1:$B$10000,2,FALSE) -> 45046642 | G53: =H53&-O53 -> MAE6G-01-52 | H53: MAE6G-01 | I53: SOLDADURA | J53: MAESTRO SOLDADOR 6G MONTAJISTA DE MAQUINARIA | K53: SILVA ADANAQUE RONAL ARMANDO | L53: 5ta | M53: 90.86 | N53: MECANOS | O53: 052 | W53: 43882 | Y53: =TEXT(W53,"ddddd") -> viernes
F54: =VLOOKUP(K54,DNI!$A$1:$B$10000,2,FALSE) -> 41004188 | G54: =H54&-O54 -> TEC-05-53 | H54: TEC-05 | I54: MONTAJE NAVE | J54: TECNICO MECANICO MONTAJISTA DE NAVE INDUSTRIAL | K54: SOTO VILLALOBOS DAVID | L54: 5ta | M54: 65 | N54: MECANOS | O54: 053 | W54: 43883 | Y54: =TEXT(W54,"ddddd") -> sábado
F55: =VLOOKUP(K55,DNI!$A$1:$B$10000,2,FALSE) -> 70549127 | G55: =H55&-O55 -> TEC-05-54 | H55: TEC-05 | I55: MONTAJE NAVE | J55: TECNICO MECANICO MONTAJISTA DE NAVE INDUSTRIAL | K55: TAFUR ALVA TONY | L55: 4ta | M55: 60 | N55: MECANOS | O55: 054 | W55: 43884 | X55: 1 | Y55: =TEXT(W55,"ddddd") -> domingo
F56: =VLOOKUP(K56,DNI!$A$1:$B$10000,2,FALSE) -> 47158079 | G56: =H56&-O56 -> TEC-02-55 | H56: TEC-02 | I56: MONTAJE MN | J56: TECNICO MECANICO MONTAJISTA DE MAQUINARIA | K56: TINOCO SANTISTEBAN JIMMY JOEL | L56: 5ta | M56: 56.55 | N56: MECANOS | O56: 055 | W56: 43885 | Y56: =TEXT(W56,"ddddd") -> lunes
F57: =VLOOKUP(K57,DNI!$A$1:$B$10000,2,FALSE) -> 76449683 | G57: =H57&-O57 -> TECME-03-56 | H57: TECME-03 | I57: ELECTRICIDAD | J57: TECNICO ELECTRICO MONTAJISTA DE MAQUINARIA EXTRANJERA | K57: TORRES RAMOS ANGY ANDREINA | L57: 5ta | M57: 73.87 | N57: MECANOS | O57: 056 | W57: 43886 | Y57: =TEXT(W57,"ddddd") -> martes
F58: =VLOOKUP(K58,DNI!$A$1:$B$10000,2,FALSE) -> 43878459 | G58: =H58&-O58 -> MEC-04-57 | H58: MEC-04 | I58: MONTAJE ME | J58: MECANICO MONTAJISTA DE MAQUINARIA EXTRANJERA | K58: VARGAS TARRILLO GLOBER | L58: 5ta | M58: 79.78 | N58: MECANOS | O58: 057 | W58: 43887 | Y58: =TEXT(W58,"ddddd") -> miércoles
F59: =VLOOKUP(K59,DNI!$A$1:$B$10000,2,FALSE) -> 46578402 | G59: =H59&-O59 -> MEC-04-58 | H59: MEC-04 | I59: MONTAJE ME | J59: MECANICO MONTAJISTA DE MAQUINARIA EXTRANJERA | K59: VARGAS TARRILLO OMAR ALEXANDER | L59: 5ta | M59: 103.42 | N59: MECANOS | O59: 058 | W59: 43888 | Y59: =TEXT(W59,"ddddd") -> jueves
F60: =VLOOKUP(K60,DNI!$A$1:$B$10000,2,FALSE) -> 45416906 | G60: =H60&-O60 -> MEC-04-59 | H60: MEC-04 | I60: MONTAJE ME | J60: MECANICO MONTAJISTA DE MAQUINARIA EXTRANJERA | K60: VASQUEZ GAMBOA JUAN JOSE | L60: 5ta | M60: 87 | N60: MECANOS | O60: 059 | W60: 43889 | Y60: =TEXT(W60,"ddddd") -> viernes
F61: =VLOOKUP(K61,DNI!$A$1:$B$10000,2,FALSE) -> 45074286 | G61: =H61&-O61 -> MAE-02-60 | H61: MAE-02 | I61: MONTAJE MN | J61: MAESTRO MECANICO MONTAJISTA DE MAQUINARIA | K61: VASQUEZ TARRILLO EVER | L61: 4ta | M61: 70 | N61: MECANOS | O61: 060 | W61: 43890 | Y61: =TEXT(W61,"ddddd") -> sábado
F62: =VLOOKUP(K62,DNI!$A$1:$B$10000,2,FALSE) -> 44044783 | G62: =H62&-O62 -> TEC-04-61 | H62: TEC-04 | I62: MONTAJE ME | J62: TECNICO MECANICO MONTAJISTA DE MAQUINARIA EXTRANJERA | K62: VASQUEZ TARRILLO LUIS | L62: 5ta | M62: 70.92 | N62: MECANOS | O62: 061 | W62: 43891 | X62: 1 | Y62: =TEXT(W62,"ddddd") -> domingo
F63: =VLOOKUP(K63,DNI!$A$1:$B$10000,2,FALSE) -> 44685832 | G63: =H63&-O63 -> MAEME-03-62 | H63: MAEME-03 | I63: ELECTRICIDAD | J63: MAESTRO ELECTRICO MONTAJISTA DE MAQUINARIA EXTRANJERA | K63: VELASQUEZ LIZA JOSE ROGELIO | L63: 5ta | M63: 88.47 | N63: MECANOS | O63: 062 | W63: 43892 | Y63: =TEXT(W63,"ddddd") -> lunes
F64: =VLOOKUP(K64,DNI!$A$1:$B$10000,2,FALSE) -> 47749907 | G64: =H64&-O64 -> TEC-05-63 | H64: TEC-05 | I64: MONTAJE NAVE | J64: TECNICO MECANICO MONTAJISTA DE NAVE INDUSTRIAL | K64: VENTURA CUBAS ALEXANDER JOHAN | L64: 5ta | M64: 80 | N64: MECANOS | O64: 063 | W64: 43893 | Y64: =TEXT(W64,"ddddd") -> martes
F65: =VLOOKUP(K65,DNI!$A$1:$B$10000,2,FALSE) -> 16683616 | G65: =H65&-O65 -> AYU-VA-64 | H65: AYU-VA | I65: VARIAS | J65: AYUDANTE DE PRODUCCION | K65: VILCHEZ VILLEGAS MANUEL ULISES | L65: 4ta | M65: 50 | N65: MECANOS | O65: 064 | W65: 43894 | Y65: =TEXT(W65,"ddddd") -> miércoles
F66: =VLOOKUP(K66,DNI!$A$1:$B$10000,2,FALSE) -> 16778242 | G66: =H66&-O66 -> AYU-VA-65 | H66: AYU-VA | I66: VARIAS | J66: AYUDANTE DE PRODUCCION | K66: CHANGANAQUE CHERO VICENTE | L66: 5ta | M66: 45 | N66: TALLERES | O66: 065 | W66: 43895 | Y66: =TEXT(W66,"ddddd") -> jueves
F67: =VLOOKUP(K67,DNI!$A$1:$B$10000,2,FALSE) -> 47503482 | G67: =H67&-O67 -> MAE-06-66 | H67: MAE-06 | I67: CORTE Y PLEGADO | J67: MAESTRO DE CORTE Y PLEGADO | K67: GARCIA PAREDES JESUS ALBERTO | L67: 5ta | M67: 76.666667 | N67: TALLERES | O67: 066 | W67: 43896 | Y67: =TEXT(W67,"ddddd") -> viernes
F68: =VLOOKUP(K68,DNI!$A$1:$B$10000,2,FALSE) -> 75169535 | G68: =H68&-O68 -> MAE-07-67 | H68: MAE-07 | I68: FACTORIA | J68: MAESTRO MECANICO DE FACTORIA | K68: GASTELO MONTEZA JERSON JHAIR | L68: 5ta | M68: 80 | N68: TALLERES | O68: 067 | W68: 43897 | Y68: =TEXT(W68,"ddddd") -> sábado
F69: =VLOOKUP(K69,DNI!$A$1:$B$10000,2,FALSE) -> 46685005 | G69: =H69&-O69 -> AYU-VA-68 | H69: AYU-VA | I69: VARIAS | J69: AYUDANTE DE PRODUCCION | K69: JULCA VALLEJOS ADAN | L69: 4ta | M69: 55 | N69: TALLERES | O69: 068 | W69: 43898 | X69: 1 | Y69: =TEXT(W69,"ddddd") -> domingo
F70: =VLOOKUP(K70,DNI!$A$1:$B$10000,2,FALSE) -> 73941535 | G70: =H70&-O70 -> TEC-07-69 | H70: TEC-07 | I70: FACTORIA | J70: TECNICO MECANICO DE FACTORIA | K70: LARIOS LLEMPEN JUNIOR DAVID | L70: 4ta | M70: 65 | N70: TALLERES | O70: 069 | W70: 43899 | Y70: =TEXT(W70,"ddddd") -> lunes
F71: =VLOOKUP(K71,DNI!$A$1:$B$10000,2,FALSE) -> 47444665 | G71: =H71&-O71 -> MAE-07-70 | H71: MAE-07 | I71: FACTORIA | J71: MAESTRO MECANICO DE FACTORIA | K71: LIZA PISFIL NEYSSER | L71: 5ta | M71: 70 | N71: TALLERES | O71: 070 | W71: 43900 | Y71: =TEXT(W71,"ddddd") -> martes
F72: =VLOOKUP(K72,DNI!$A$1:$B$10000,2,FALSE) -> 106394571 | G72: =H72&-O72 -> OPE-06-71 | H72: OPE-06 | I72: CORTE Y PLEGADO | J72: OPERARIO DE CORTE Y PLEGADO | K72: MATA SEOANE ROMAN | L72: 4ta | M72: 60 | N72: TALLERES | O72: 071 | W72: 43901 | Y72: =TEXT(W72,"ddddd") -> miércoles
F73: =VLOOKUP(K73,DNI!$A$1:$B$10000,2,FALSE) -> 46853568 | G73: =H73&-O73 -> TEC-07-72 | H73: TEC-07 | I73: FACTORIA | J73: TECNICO MECANICO DE FACTORIA | K73: REYES RAMOS JUAN LUIS | L73: 5ta | M73: 60 | N73: TALLERES | O73: 072 | W73: 43902 | Y73: =TEXT(W73,"ddddd") -> jueves
F74: =VLOOKUP(K74,DNI!$A$1:$B$10000,2,FALSE) -> 47184596 | G74: =H74&-O74 -> OPE-06-73 | H74: OPE-06 | I74: CORTE Y PLEGADO | J74: OPERARIO DE CORTE Y PLEGADO | K74: VELIZ TEJADA EDWIN | L74: 4ta | M74: 60 | N74: TALLERES | O74: 073 | W74: 43903 | Y74: =TEXT(W74,"ddddd") -> viernes
F75: =VLOOKUP(K75,DNI!$A$1:$B$10000,2,FALSE) -> 46859101 | G75: =H75&-O75 -> MAE-08-74 | H75: MAE-08 | I75: PINTURA | J75: MAESTRO PINTOR | K75: ZETA DELGADO DERWIS YENNER | L75: 5ta | M75: 70 | N75: MECANOS | O75: 074 | W75: 43904 | Y75: =TEXT(W75,"ddddd") -> sábado
F76: =VLOOKUP(K76,DNI!$A$1:$B$10000,2,FALSE) -> 16495851 | H76: X1 | I76: SERVICIOS GENERALES | J76: ASISTENTE DE MANTENIEMIENTO | K76: CORDOVA CORDOVA ADAN | L76: 5ta | M76: 50 | N76: DELCOR | O76: 075 | W76: 43905 | X76: 1 | Y76: =TEXT(W76,"ddddd") -> domingo
F77: =VLOOKUP(K77,DNI!$A$1:$B$10000,2,FALSE) -> 16716665 | H77: X2 | I77: PRODUCCION | J77: SUPERVISOR DE PRODUCCION | K77: PAZ RAMOS ALFREDO ANIBAL | L77: 5ta | M77: =3500/26 -> 134.61538 | N77: DELCOR | O77: 076 | W77: 43906 | Y77: =TEXT(W77,"ddddd") -> lunes
F78: =VLOOKUP(K78,DNI!$A$1:$B$10000,2,FALSE) -> 47373880 | H78: X3 | I78: PRODUCCION | J78: SUPERVISOR DE CONTROL DE CALIDAD | K78: ZAPATA IDROGO LEONARDO ENRIQUE | L78: 5ta | M78: =2000/30 -> 66.666667 | N78: DELCOR | O78: 077 | W78: 43907 | Y78: =TEXT(W78,"ddddd") -> martes
F79: =VLOOKUP(K79,DNI!$A$1:$B$10000,2,FALSE) -> 41126636 | H79: X4 | I79: ALMACEN | J79: AUXILIAR DE ALMACEN | K79: LOPEZ DELGADO PEDRO PABLO | L79: 4ta | M79: 35.77 | N79: DELCOR | O79: 078 | W79: 43908 | Y79: =TEXT(W79,"ddddd") -> miércoles
F80: =VLOOKUP(K80,DNI!$A$1:$B$10000,2,FALSE) -> 42742746 | H80: X5 | I80: ALMACEN | J80: AUXILIAR DE ALMACEN | K80: SARMIENTO MONJA JORGE | L80: 4ta | M80: 38.7 | N80: DELCOR | O80: 079 | W80: 43909 | Y80: =TEXT(W80,"ddddd") -> jueves
F81: =VLOOKUP(K81,DNI!$A$1:$B$10000,2,FALSE) -> 45327555 | H81: X6 | I81: PRODUCCION | J81: SUPERVISOR DE MONTAJE Y DESMONTAJE | K81: HERRERA NAVARRO OSMER | L81: 5ta | M81: 62.31 | N81: MECANOS | O81: 080 | W81: 43910 | Y81: =TEXT(W81,"ddddd") -> viernes
F82: =VLOOKUP(K82,DNI!$A$1:$B$10000,2,FALSE) -> 44792584 | G82: =H82&-O82 -> OPE-01-81 | H82: OPE-01 | I82: SOLDADURA | J82: OPERARIO SOLDADOR | K82: ENRIQUEZ GONZALES WILLIAM RICARDO | L82: 4ta | M82: 60 | N82: MECANOS | O82: 081 | W82: 43911 | Y82: =TEXT(W82,"ddddd") -> sábado
F83: =VLOOKUP(K83,DNI!$A$1:$B$10000,2,FALSE) -> 47951049 | G83: =H83&-O83 -> AYU-VA-82 | H83: AYU-VA | I83: VARIAS | J83: AYUDANTE DE PRODUCCION | K83: RIVERA YANGUA VICTOR MIGUEL | L83: 4ta | M83: 50 | N83: MECANOS | O83: 082 | W83: 43912 | X83: 1 | Y83: =TEXT(W83,"ddddd") -> domingo
F84: =VLOOKUP(K84,DNI!$A$1:$B$10000,2,FALSE) -> 46933574 | G84: =H84&-O84 -> TEC-01-83 | H84: TEC-01 | I84: SOLDADURA | J84: TECNICO SOLDADOR | K84: MUÑOZ EXEBIO IRWIS MANUEL | L84: 5ta | M84: 65 | N84: MECANOS | O84: 083 | W84: 43913 | Y84: =TEXT(W84,"ddddd") -> lunes
F85: =VLOOKUP(K85,DNI!$A$1:$B$10000,2,FALSE) -> 47265187 | G85: =H85&-O85 -> AYU-VA-84 | H85: AYU-VA | I85: VARIAS | J85: AYUDANTE DE PRODUCCION | K85: PURIZACA SEVERINO JUAN CARLOS | L85: 4ta | M85: 55 | N85: MECANOS | O85: 084 | W85: 43914 | Y85: =TEXT(W85,"ddddd") -> martes
F86: 71479954 | G86: =H86&-O86 -> OPE-03-85 | H86: OPE-03 | I86: ELECTRICIDAD | J86: OPERARIO ELECTRICO | K86: CUEVA CUZQUEN MARLON ALEJANDRO | L86: 5ta | M86: 29.55 | N86: MECANOS | O86: 085 | W86: 43915 | Y86: =TEXT(W86,"ddddd") -> miércoles
F87: 76281226 | G87: =H87&-O87 -> OPE-03-86 | H87: OPE-03 | I87: ELECTRICIDAD | J87: OPERARIO ELECTRICO | K87: AGAPITO AYASTA ANDERSON ANTHONY | L87: 5ta | M87: 46.15 | N87: MECANOS | O87: 086 | W87: 43916 | Y87: =TEXT(W87,"ddddd") -> jueves
F88: 46801821 | G88: =H88&-O88 -> OPE-03-87 | H88: OPE-03 | I88: ELECTRICIDAD | J88: OPERARIO ELECTRICO | K88: BARRAGAN SALAZAR JHONATAN PEDRO | L88: 5ta | M88: 43.5 | N88: MECANOS | O88: 087 | W88: 43917 | Y88: =TEXT(W88,"ddddd") -> viernes
F89: 42445595 | J89: CONDUCTOR | K89: TEJADA SUYON JHON JAMES | L89: 4ta | M89: 50 | N89: MECANOS | O89: 88 | W89: 43918 | Y89: =TEXT(W89,"ddddd") -> sábado
F90: 73241681 | G90: =H90&-O90 -> TEC-01-89 | H90: TEC-01 | I90: SOLDADURA | J90: TECNICO SOLDADOR | K90: CACHAY ACOSTA CARLOS ALEXANDER | L90: 4ta | M90: 60 | N90: MECANOS | O90: 89 | W90: 43919 | X90: 1 | Y90: =TEXT(W90,"ddddd") -> domingo
F91: 76802885 | G91: =H91&-O91 -> TEC-01-90 | H91: TEC-01 | I91: SOLDADURA | J91: TECNICO SOLDADOR | K91: MIO LLOCYA JOSE ALEXANDER | L91: 4ta | M91: 60 | N91: MECANOS | O91: 90 | W91: 43920 | Y91: =TEXT(W91,"ddddd") -> lunes
F92: 45728597 | G92: =H92&-O92 -> TEC-01-91 | H92: TEC-01 | I92: SOLDADURA | J92: TECNICO SOLDADOR | K92: TUÑOQUE SANTISTEBAN CRISTOBAL | L92: 4ta | M92: 75 | N92: MECANOS | O92: 91 | W92: 43921 | Y92: =TEXT(W92,"ddddd") -> martes
G93: =H93&-O93 -> AYU-VA-92 | H93: AYU-VA | I93: VARIAS | J93: AYUDANTE DE PRODUCCION | K93: TUÑOQUE ZEÑA JOSE ARMANDO | L93: 4ta | M93: 50 | N93: MECANOS | O93: 92 | W93: 43922 | Y93: =TEXT(W93,"ddddd") -> miércoles
F94: 75494335 | G94: =H94&-O94 -> TEC-01-93 | H94: TEC-01 | I94: SOLDADURA | J94: TECNICO SOLDADOR | K94: DAMIAN DAMIAN MIGUEL ANGEL | L94: 4ta | M94: 90 | N94: MECANOS | O94: 93 | W94: 43923 | Y94: =TEXT(W94,"ddddd") -> jueves
F95: 76288149 | G95: =H95&-O95 -> AYU-VA-94 | H95: AYU-VA | I95: VARIAS | J95: AYUDANTE DE PRODUCCION | K95: DELGADO CORONADO ROBERTO | L95: 5ta | M95: 44.32 | N95: MECANOS | O95: 94 | W95: 43924 | Y95: =TEXT(W95,"ddddd") -> viernes
F96: 77234132 | G96: =H96&-O96 -> AYU-VA-95 | H96: AYU-VA | I96: VARIAS | J96: AYUDANTE DE PRODUCCION | K96: GUILLE DEZA BRYAN | L96: 4ta | M96: 50 | N96: MECANOS | O96: 95 | W96: 43925 | Y96: =TEXT(W96,"ddddd") -> sábado
F97: 72927801 | G97: =H97&-O97 -> TEC-01-96 | H97: TEC-01 | I97: SOLDADURA | J97: TECNICO SOLDADOR | K97: SALAZAR FERNANDEZ WALTER | L97: 5ta | M97: 60 | N97: MECANOS | O97: 96 | W97: 43926 | X97: 1 | Y97: =TEXT(W97,"ddddd") -> domingo | Z97: jueves santo | AA97: 1
F98: 71022077 | G98: =H98&-O98 -> TEC-01-97 | H98: TEC-01 | I98: SOLDADURA | J98: TECNICO SOLDADOR | K98: SANCHEZ LLAMO D'ESTEFANO | L98: 4ta | M98: 65 | N98: MECANOS | O98: 97 | W98: 43927 | Y98: =TEXT(W98,"ddddd") -> lunes | Z98: viernes santo | AA98: 1
F99: 46817362 | G99: =H99&-O99 -> AYU-VA-98 | H99: AYU-VA | I99: VARIAS | J99: AYUDANTE DE PRODUCCION | K99: SIRLOPU ALVARADO EMERSON | L99: 4ta | M99: 55 | N99: MECANOS | O99: 98 | W99: 43928 | Y99: =TEXT(W99,"ddddd") -> martes
F100: 41740010 | G100: =H100&-O100 -> -99 | K100: TORRES ZEVALLOS JUAN FRANCISCO | L100: 4ta | M100: 60 | N100: MECANOS | O100: 99 | W100: 43929 | Y100: =TEXT(W100,"ddddd") -> miércoles
...

Sheet BD
AS1: 1 | AT1: PLANTA | AU1: 0.375 | AV1: L-V | AW1: 0.33333333 | AX1: 0.29166667 | AY1: S
M3: HORARIO | AS3: 2 | AT3: OBRA | AU3: 0.33333333 | AV3: L-S
N4: ALMUERZO | T4: MAGIA FIORELA | AF4: EXTRA | AH4: 4TA | AJ4: 5TA
A5: DIA | B5: PUNTO | C5: N° SEMANA | D5: N° MES | E5: CONDICION | F5: PERFIL | G5: DETALLE PERFIL | H5: TRABAJADOR | I5: FECHA | J5: DESTINO | K5: DNI | L5: DIARIO | M5: INGRESO | N5: INICIO | O5: FIN | P5: SALIDA | Q5: T.HORAS | R5: H.NORMALES | S5: H.EXTRAS | T5: HORAS 25 % | U5: HORAS 35% | V5: C.HORA.25 | W5: C.HORA.35 | X5: CST_H_E | Y5: C.H | Z5: T.H | AA5: H.N | AB5: H.E | AC5: COS.BASE 2 | AD5: COS.BASE 3 | AE5: COS.B+E | AF5: F | AG5: D | AH5: COS.F1 | AI5: COS.D1 | AJ5: COS F2 | AK5: COS D2 | AL5: ALIMENTACION | AM5: PRESTAMO | AN5: PASAJES | AO5: MONTO 4 TA | AP5: MONTO 5TA | AS5: 8 | AT5: OBRA | AU5: 0.33333333 | AV5: L-S
A6: =TEXT(Tabla1[[#This Row],[FECHA ]],"DDDDD") -> viernes | B6: =_xlfn.IFNA(VLOOKUP(Tabla1[[#This Row],[DESTINO]],RUBRO!$Q$1:$R$9996,2,FALSE)," ") -> PLANTA | C6: =WEEKNUM(Tabla1[[#This Row],[FECHA ]],2) -> 19 | D6: =TEXT(Tabla1[[#This Row],[FECHA ]],"MMM-YY") -> may-YY | E6: =VLOOKUP(Tabla1[[#This Row],[DNI ]],RUBRO!$F$1:$O$9996,7,FALSE) -> 5ta | F6: =VLOOKUP(Tabla1[[#This Row],[DNI ]],RUBRO!$F$1:$O$88,3,FALSE) -> TEC-02 | G6: =VLOOKUP(Tabla1[[#This Row],[DNI ]],RUBRO!$F$1:$O$9996,5,FALSE) -> TECNICO MECANICO MONTAJISTA DE MAQUINARIA | H6: =VLOOKUP(Tabla1[[#This Row],[DNI ]],RUBRO!$F$1:$O$9996,6,FALSE) -> ALVAREZ ALVINES JUAN MANUEL | I6: 44323 | J6: 1 | K6: 46108491 | L6: =VLOOKUP(Tabla1[[#This Row],[DNI ]],RUBRO!$F$2:$O$9996,8,FALSE) -> 50 | M6: 0.29166667 | N6: 0.54166667 | O6: 0.58333333 | P6: 0.70833333 | Q6: =(Tabla1[[#This Row],[SALIDA]]-Tabla1[[#This Row],[FIN ]])+(Tabla1[[#This Row],[INICIO]]-Tabla1[[#This Row],[INGRESO]]) -> 0.375 | R6: =IF(J6=1,IF(Q6>$AU$1,$AU$1,Q6),0)+IF(J6=2,IF(Q6>$AU$3,$AU$3,Q6),0)+IF(J6=8,IF(Q6>$AU$5,$AU$5,Q6),0) -> 0.375 | S6: =IF(J6=1,IF(Q6>$AU$1,(Q6-R6),0),0)+IF(J6=2,IF(Q6>$AU$3,(Q6-R6),0),0)+IF(J6=8,IF(Q6>$AU$5,(Q6-R6),0),0) -> 0 | V6: =(Tabla1[[#This Row],[COS.BASE 3]]*0.25+Tabla1[[#This Row],[COS.BASE 3]])*Tabla1[[#This Row],[HORAS 25 % ]] -> 0 | W6: =(Tabla1[[#This Row],[COS.BASE 3]]*0.35+Tabla1[[#This Row],[COS.BASE 3]])*Tabla1[[#This Row],[HORAS 35% ]] -> 0 | X6: =SUM(Tabla1[[#This Row],[C.HORA.35]],Tabla1[[#This Row],[C.HORA.25]]) -> 0 | Z6: =Tabla1[[#This Row],[T.HORAS]]*24 -> 9 | AA6: =Tabla1[[#This Row],[H.NORMALES]]*24 -> 9 | AB6: =Tabla1[[#This Row],[H.EXTRAS]]*24 -> 0 | AC6: =IF(J6=1,(((R6*24)*(L6/9))),0)+IF(J6=2,(((R6*24)*(L6/8))),0)+IF(J6=8,(((R6*24)*(L6/8))),0) -> 50 | AD6: =Tabla1[[#This Row],[COS.BASE 2]]/8 -> 6.25 | AE6: =Tabla1[[#This Row],[CST_H_E]]+Tabla1[[#This Row],[COS.BASE 2]] -> 50 | AF6: =+_xlfn.IFNA(INDEX(RUBRO!$W$2:$AA$732,MATCH(Tabla1[[#This Row],[FECHA ]],RUBRO!$W$2:$W$732,0),5)," ") -> 0 | AG6: =+_xlfn.IFNA(INDEX(RUBRO!$W$2:$AA$732,MATCH(Tabla1[[#This Row],[FECHA ]],RUBRO!$W$2:$W$732,0),2)," ") -> 0 | AH6: =IFERROR(Tabla1[[#This Row],[F]]*Tabla1[[#This Row],[COS.B+E]]," ") -> 0 | AI6: =IFERROR(Tabla1[[#This Row],[COS.B+E]]*Tabla1[[#This Row],[D]]," ") -> 0 | AJ6: =IFERROR(Tabla1[[#This Row],[F]]*#REF!," ") | AK6: =IFERROR(#REF!*Tabla1[[#This Row],[D]]," ") | AO6: =+Tabla1[[#This Row],[COS.B+E]]+Tabla1[[#This Row],[COS.F1]]+Tabla1[[#This Row],[COS.D1]]+Tabla1[[#This Row],[ALIMENTACION]]+Tabla1[[#This Row],[PRESTAMO]]+AN6 -> 50 | AP6: =+#REF!+Tabla1[[#This Row],[COS F2]]+Tabla1[[#This Row],[COS D2]]+Tabla1[[#This Row],[ALIMENTACION]]+Tabla1[[#This Row],[PRESTAMO]]+Tabla1[[#This Row],[PASAJES]] -> #REF!
A7: =TEXT(Tabla1[[#This Row],[FECHA ]],"DDDDD") -> viernes | B7: =_xlfn.IFNA(VLOOKUP(Tabla1[[#This Row],[DESTINO]],RUBRO!$Q$1:$R$9996,2,FALSE)," ") -> PLANTA | C7: =WEEKNUM(Tabla1[[#This Row],[FECHA ]],2) -> 19 | D7: =TEXT(Tabla1[[#This Row],[FECHA ]],"MMM-YY") -> may-YY | E7: =VLOOKUP(Tabla1[[#This Row],[DNI ]],RUBRO!$F$1:$O$9996,7,FALSE) -> 4ta | F7: =VLOOKUP(Tabla1[[#This Row],[DNI ]],RUBRO!$F$1:$O$88,3,FALSE) -> OPE-03 | G7: =VLOOKUP(Tabla1[[#This Row],[DNI ]],RUBRO!$F$1:$O$9996,5,FALSE) -> OPERARIO ELECTRICO | H7: =VLOOKUP(Tabla1[[#This Row],[DNI ]],RUBRO!$F$1:$O$9996,6,FALSE) -> AYALA RAMIREZ RUBEN ISAI | I7: 44323 | J7: 1 | K7: 75557820 | L7: =VLOOKUP(Tabla1[[#This Row],[DNI ]],RUBRO!$F$2:$O$9996,8,FALSE) -> 50 | M7: 0.29166667 | N7: 0.54166667 | O7: 0.58333333 | P7: 0.70833333 | Q7: =(Tabla1[[#This Row],[SALIDA]]-Tabla1[[#This Row],[FIN ]])+(Tabla1[[#This Row],[INICIO]]-Tabla1[[#This Row],[INGRESO]]) -> 0.375 | R7: =IF(J7=1,IF(Q7>$AU$1,$AU$1,Q7),0)+IF(J7=2,IF(Q7>$AU$3,$AU$3,Q7),0)+IF(J7=8,IF(Q7>$AU$5,$AU$5,Q7),0) -> 0.375 | S7: =IF(J7=1,IF(Q7>$AU$1,(Q7-R7),0),0)+IF(J7=2,IF(Q7>$AU$3,(Q7-R7),0),0)+IF(J7=8,IF(Q7>$AU$5,(Q7-R7),0),0) -> 0 | V7: =(Tabla1[[#This Row],[COS.BASE 3]]*0.25+Tabla1[[#This Row],[COS.BASE 3]])*Tabla1[[#This Row],[HORAS 25 % ]] -> 0 | W7: =(Tabla1[[#This Row],[COS.BASE 3]]*0.35+Tabla1[[#This Row],[COS.BASE 3]])*Tabla1[[#This Row],[HORAS 35% ]] -> 0 | X7: =SUM(Tabla1[[#This Row],[C.HORA.35]],Tabla1[[#This Row],[C.HORA.25]]) -> 0 | Z7: =Tabla1[[#This Row],[T.HORAS]]*24 -> 9 | AA7: =Tabla1[[#This Row],[H.NORMALES]]*24 -> 9 | AB7: =Tabla1[[#This Row],[H.EXTRAS]]*24 -> 0 | AC7: =IF(J7=1,(((R7*24)*(L7/9))),0)+IF(J7=2,(((R7*24)*(L7/8))),0)+IF(J7=8,(((R7*24)*(L7/8))),0) -> 50 | AD7: =Tabla1[[#This Row],[COS.BASE 2]]/8 -> 6.25 | AE7: =Tabla1[[#This Row],[CST_H_E]]+Tabla1[[#This Row],[COS.BASE 2]] -> 50 | AF7: =+_xlfn.IFNA(INDEX(RUBRO!$W$2:$AA$732,MATCH(Tabla1[[#This Row],[FECHA ]],RUBRO!$W$2:$W$732,0),5)," ") -> 0 | AG7: =+_xlfn.IFNA(INDEX(RUBRO!$W$2:$AA$732,MATCH(Tabla1[[#This Row],[FECHA ]],RUBRO!$W$2:$W$732,0),2)," ") -> 0 | AH7: =IFERROR(Tabla1[[#This Row],[F]]*Tabla1[[#This Row],[COS.B+E]]," ") -> 0 | AI7: =IFERROR(Tabla1[[#This Row],[COS.B+E]]*Tabla1[[#This Row],[D]]," ") -> 0 | AJ7: =IFERROR(Tabla1[[#This Row],[F]]*#REF!," ") | AK7: =IFERROR(#REF!*Tabla1[[#This Row],[D]]," ") | AO7: =+Tabla1[[#This Row],[COS.B+E]]+Tabla1[[#This Row],[COS.F1]]+Tabla1[[#This Row],[COS.D1]]+Tabla1[[#This Row],[ALIMENTACION]]+Tabla1[[#This Row],[PRESTAMO]]+AN7 -> 50 | AP7: =+#REF!+Tabla1[[#This Row],[COS F2]]+Tabla1[[#This Row],[COS D2]]+Tabla1[[#This Row],[ALIMENTACION]]+Tabla1[[#This Row],[PRESTAMO]]+Tabla1[[#This Row],[PASAJES]] -> #REF!
A8: =TEXT(Tabla1[[#This Row],[FECHA ]],"DDDDD") -> viernes | B8: =_xlfn.IFNA(VLOOKUP(Tabla1[[#This Row],[DESTINO]],RUBRO!$Q$1:$R$9996,2,FALSE)," ") -> OBRA | C8: =WEEKNUM(Tabla1[[#This Row],[FECHA ]],2) -> 19 | D8: =TEXT(Tabla1[[#This Row],[FECHA ]],"MMM-YY") -> may-YY | E8: =VLOOKUP(Tabla1[[#This Row],[DNI ]],RUBRO!$F$1:$O$9996,7,FALSE) -> 5ta | F8: =VLOOKUP(Tabla1[[#This Row],[DNI ]],RUBRO!$F$1:$O$88,3,FALSE) -> OPE-03 | G8: =VLOOKUP(Tabla1[[#This Row],[DNI ]],RUBRO!$F$1:$O$9996,5,FALSE) -> OPERARIO ELECTRICO | H8: =VLOOKUP(Tabla1[[#This Row],[DNI ]],RUBRO!$F$1:$O$9996,6,FALSE) -> BARRAGAN SALAZAR JHONATAN PEDRO | I8: 44323 | J8: 2 | K8: 46801821 | L8: =VLOOKUP(Tabla1[[#This Row],[DNI ]],RUBRO!$F$2:$O$9996,8,FALSE) -> 43.5 | M8: 0.29166667 | N8: 0.54166667 | O8: 0.58333333 | P8: 0.75 | Q8: =(Tabla1[[#This Row],[SALIDA]]-Tabla1[[#This Row],[FIN ]])+(Tabla1[[#This Row],[INICIO]]-Tabla1[[#This Row],[INGRESO]]) -> 0.41666667 | R8: =IF(J8=1,IF(Q8>$AU$1,$AU$1,Q8),0)+IF(J8=2,IF(Q8>$AU$3,$AU$3,Q8),0)+IF(J8=8,IF(Q8>$AU$5,$AU$5,Q8),0) -> 0.33333333 | S8: =IF(J8=1,IF(Q8>$AU$1,(Q8-R8),0),0)+IF(J8=2,IF(Q8>$AU$3,(Q8-R8),0),0)+IF(J8=8,IF(Q8>$AU$5,(Q8-R8),0),0) -> 0.083333333 | T8: 1 | U8: 1 | V8: =(Tabla1[[#This Row],[COS.BASE 3]]*0.25+Tabla1[[#This Row],[COS.BASE 3]])*Tabla1[[#This Row],[HORAS 25 % ]] -> 6.796875 | W8: =(Tabla1[[#This Row],[COS.BASE 3]]*0.35+Tabla1[[#This Row],[COS.BASE 3]])*Tabla1[[#This Row],[HORAS 35% ]] -> 7.340625 | X8: =SUM(Tabla1[[#This Row],[C.HORA.35]],Tabla1[[#This Row],[C.HORA.25]]) -> 14.1375 | Z8: =Tabla1[[#This Row],[T.HORAS]]*24 -> 10 | AA8: =Tabla1[[#This Row],[H.NORMALES]]*24 -> 8 | AB8: =Tabla1[[#This Row],[H.EXTRAS]]*24 -> 2 | AC8: =IF(J8=1,(((R8*24)*(L8/9))),0)+IF(J8=2,(((R8*24)*(L8/8))),0)+IF(J8=8,(((R8*24)*(L8/8))),0) -> 43.5 | AD8: =Tabla1[[#This Row],[COS.BASE 2]]/8 -> 5.4375 | AE8: =Tabla1[[#This Row],[CST_H_E]]+Tabla1[[#This Row],[COS.BASE 2]] -> 57.6375 | AF8: =+_xlfn.IFNA(INDEX(RUBRO!$W$2:$AA$732,MATCH(Tabla1[[#This Row],[FECHA ]],RUBRO!$W$2:$W$732,0),5)," ") -> 0 | AG8: =+_xlfn.IFNA(INDEX(RUBRO!$W$2:$AA$732,MATCH(Tabla1[[#This Row],[FECHA ]],RUBRO!$W$2:$W$732,0),2)," ") -> 0 | AH8: =IFERROR(Tabla1[[#This Row],[F]]*Tabla1[[#This Row],[COS.B+E]]," ") -> 0 | AI8: =IFERROR(Tabla1[[#This Row],[COS.B+E]]*Tabla1[[#This Row],[D]]," ") -> 0 | AJ8: =IFERROR(Tabla1[[#This Row],[F]]*#REF!," ") | AK8: =IFERROR(#REF!*Tabla1[[#This Row],[D]]," ") | AO8: =+Tabla1[[#This Row],[COS.B+E]]+Tabla1[[#This Row],[COS.F1]]+Tabla1[[#This Row],[COS.D1]]+Tabla1[[#This Row],[ALIMENTACION]]+Tabla1[[#This Row],[PRESTAMO]]+AN8 -> 57.6375 | AP8: =+#REF!+Tabla1[[#This Row],[COS F2]]+Tabla1[[#This Row],[COS D2]]+Tabla1[[#This Row],[ALIMENTACION]]+Tabla1[[#This Row],[PRESTAMO]]+Tabla1[[#This Row],[PASAJES]] -> #REF!
A9: =TEXT(Tabla1[[#This Row],[FECHA ]],"DDDDD") -> viernes | B9: =_xlfn.IFNA(VLOOKUP(Tabla1[[#This Row],[DESTINO]],RUBRO!$Q$1:$R$9996,2,FALSE)," ") -> PLANTA | C9: =WEEKNUM(Tabla1[[#This Row],[FECHA ]],2) -> 19 | D9: =TEXT(Tabla1[[#This Row],[FECHA ]],"MMM-YY") -> may-YY | E9: =VLOOKUP(Tabla1[[#This Row],[DNI ]],RUBRO!$F$1:$O$9996,7,FALSE) -> 5ta | F9: =VLOOKUP(Tabla1[[#This Row],[DNI ]],RUBRO!$F$1:$O$88,3,FALSE) -> OPE-01 | G9: =VLOOKUP(Tabla1[[#This Row],[DNI ]],RUBRO!$F$1:$O$9996,5,FALSE) -> OPERARIO SOLDADOR | H9: =VLOOKUP(Tabla1[[#This Row],[DNI ]],RUBRO!$F$1:$O$9996,6,FALSE) -> BENDEZU PISCO JORGE GUILLERMO | I9: 44323 | J9: 1 | K9: 10664396 | L9: =VLOOKUP(Tabla1[[#This Row],[DNI ]],RUBRO!$F$2:$O$9996,8,FALSE) -> 60 | M9: 0.29166667 | N9: 0.54166667 | O9: 0.58333333 | P9: 0.70833333 | Q9: =(Tabla1[[#This Row],[SALIDA]]-Tabla1[[#This Row],[FIN ]])+(Tabla1[[#This Row],[INICIO]]-Tabla1[[#This Row],[INGRESO]]) -> 0.375 | R9: =IF(J9=1,IF(Q9>$AU$1,$AU$1,Q9),0)+IF(J9=2,IF(Q9>$AU$3,$AU$3,Q9),0)+IF(J9=8,IF(Q9>$AU$5,$AU$5,Q9),0) -> 0.375 | S9: =IF(J9=1,IF(Q9>$AU$1,(Q9-R9),0),0)+IF(J9=2,IF(Q9>$AU$3,(Q9-R9),0),0)+IF(J9=8,IF(Q9>$AU$5,(Q9-R9),0),0) -> 0 | V9: =(Tabla1[[#This Row],[COS.BASE 3]]*0.25+Tabla1[[#This Row],[COS.BASE 3]])*Tabla1[[#This Row],[HORAS 25 % ]] -> 0 | W9: =(Tabla1[[#This Row],[COS.BASE 3]]*0.35+Tabla1[[#This Row],[COS.BASE 3]])*Tabla1[[#This Row],[HORAS 35% ]] -> 0 | X9: =SUM(Tabla1[[#This Row],[C.HORA.35]],Tabla1[[#This Row],[C.HORA.25]]) -> 0 | Z9: =Tabla1[[#This Row],[T.HORAS]]*24 -> 9 | AA9: =Tabla1[[#This Row],[H.NORMALES]]*24 -> 9 | AB9: =Tabla1[[#This Row],[H.EXTRAS]]*24 -> 0 | AC9: =IF(J9=1,(((R9*24)*(L9/9))),0)+IF(J9=2,(((R9*24)*(L9/8))),0)+IF(J9=8,(((R9*24)*(L9/8))),0) -> 60 | AD9: =Tabla1[[#This Row],[COS.BASE 2]]/8 -> 7.5 | AE9: =Tabla1[[#This Row],[CST_H_E]]+Tabla1[[#This Row],[COS.BASE 2]] -> 60 | AF9: =+_xlfn.IFNA(INDEX(RUBRO!$W$2:$AA$732,MATCH(Tabla1[[#This Row],[FECHA ]],RUBRO!$W$2:$W$732,0),5)," ") -> 0 | AG9: =+_xlfn.IFNA(INDEX(RUBRO!$W$2:$AA$732,MATCH(Tabla1[[#This Row],[FECHA ]],RUBRO!$W$2:$W$732,0),2)," ") -> 0 | AH9: =IFERROR(Tabla1[[#This Row],[F]]*Tabla1[[#This Row],[COS.B+E]]," ") -> 0 | AI9: =IFERROR(Tabla1[[#This Row],[COS.B+E]]*Tabla1[[#This Row],[D]]," ") -> 0 | AJ9: =IFERROR(Tabla1[[#This Row],[F]]*#REF!," ") | AK9: =IFERROR(#REF!*Tabla1[[#This Row],[D]]," ") | AO9: =+Tabla1[[#This Row],[COS.B+E]]+Tabla1[[#This Row],[COS.F1]]+Tabla1[[#This Row],[COS.D1]]+Tabla1[[#This Row],[ALIMENTACION]]+Tabla1[[#This Row],[PRESTAMO]]+AN9 -> 60 | AP9: =+#REF!+Tabla1[[#This Row],[COS F2]]+Tabla1[[#This Row],[COS D2]]+Tabla1[[#This Row],[ALIMENTACION]]+Tabla1[[#This Row],[PRESTAMO]]+Tabla1[[#This Row],[PASAJES]] -> #REF!
A10: =TEXT(Tabla1[[#This Row],[FECHA ]],"DDDDD") -> viernes | B10: =_xlfn.IFNA(VLOOKUP(Tabla1[[#This Row],[DESTINO]],RUBRO!$Q$1:$R$9996,2,FALSE)," ") -> FALTA | C10: =WEEKNUM(Tabla1[[#This Row],[FECHA ]],2) -> 19 | D10: =TEXT(Tabla1[[#This Row],[FECHA ]],"MMM-YY") -> may-YY | E10: =VLOOKUP(Tabla1[[#This Row],[DNI ]],RUBRO!$F$1:$O$9996,7,FALSE) -> 4ta | F10: =VLOOKUP(Tabla1[[#This Row],[DNI ]],RUBRO!$F$1:$O$88,3,FALSE) -> OPE-01 | G10: =VLOOKUP(Tabla1[[#This Row],[DNI ]],RUBRO!$F$1:$O$9996,5,FALSE) -> OPERARIO SOLDADOR | H10: =VLOOKUP(Tabla1[[#This Row],[DNI ]],RUBRO!$F$1:$O$9996,6,FALSE) -> BONILLA CHAVEZ LUIS DANIEL | I10: 44323 | J10: 4 | K10: 71995358 | L10: =VLOOKUP(Tabla1[[#This Row],[DNI ]],RUBRO!$F$2:$O$9996,8,FALSE) -> 45 | Q10: =(Tabla1[[#This Row],[SALIDA]]-Tabla1[[#This Row],[FIN ]])+(Tabla1[[#This Row],[INICIO]]-Tabla1[[#This Row],[INGRESO]]) -> 0 | R10: =IF(J10=1,IF(Q10>$AU$1,$AU$1,Q10),0)+IF(J10=2,IF(Q10>$AU$3,$AU$3,Q10),0)+IF(J10=8,IF(Q10>$AU$5,$AU$5,Q10),0) -> 0 | S10: =IF(J10=1,IF(Q10>$AU$1,(Q10-R10),0),0)+IF(J10=2,IF(Q10>$AU$3,(Q10-R10),0),0)+IF(J10=8,IF(Q10>$AU$5,(Q10-R10),0),0) -> 0 | V10: =(Tabla1[[#This Row],[COS.BASE 3]]*0.25+Tabla1[[#This Row],[COS.BASE 3]])*Tabla1[[#This Row],[HORAS 25 % ]] -> 0 | W10: =(Tabla1[[#This Row],[COS.BASE 3]]*0.35+Tabla1[[#This Row],[COS.BASE 3]])*Tabla1[[#This Row],[HORAS 35% ]] -> 0 | X10: =SUM(Tabla1[[#This Row],[C.HORA.35]],Tabla1[[#This Row],[C.HORA.25]]) -> 0 | Z10: =Tabla1[[#This Row],[T.HORAS]]*24 -> 0 | AA10: =Tabla1[[#This Row],[H.NORMALES]]*24 -> 0 | AB10: =Tabla1[[#This Row],[H.EXTRAS]]*24 -> 0 | AC10: =IF(J10=1,(((R10*24)*(L10/9))),0)+IF(J10=2,(((R10*24)*(L10/8))),0)+IF(J10=8,(((R10*24)*(L10/8))),0) -> 0 | AD10: =Tabla1[[#This Row],[COS.BASE 2]]/8 -> 0 | AE10: =Tabla1[[#This Row],[CST_H_E]]+Tabla1[[#This Row],[COS.BASE 2]] -> 0 | AF10: =+_xlfn.IFNA(INDEX(RUBRO!$W$2:$AA$732,MATCH(Tabla1[[#This Row],[FECHA ]],RUBRO!$W$2:$W$732,0),5)," ") -> 0 | AG10: =+_xlfn.IFNA(INDEX(RUBRO!$W$2:$AA$732,MATCH(Tabla1[[#This Row],[FECHA ]],RUBRO!$W$2:$W$732,0),2)," ") -> 0 | AH10: =IFERROR(Tabla1[[#This Row],[F]]*Tabla1[[#This Row],[COS.B+E]]," ") -> 0 | AI10: =IFERROR(Tabla1[[#This Row],[COS.B+E]]*Tabla1[[#This Row],[D]]," ") -> 0 | AJ10: =IFERROR(Tabla1[[#This Row],[F]]*#REF!," ") | AK10: =IFERROR(#REF!*Tabla1[[#This Row],[D]]," ") | AO10: =+Tabla1[[#This Row],[COS.B+E]]+Tabla1[[#This Row],[COS.F1]]+Tabla1[[#This Row],[COS.D1]]+Tabla1[[#This Row],[ALIMENTACION]]+Tabla1[[#This Row],[PRESTAMO]]+AN10 -> 0 | AP10: =+#REF!+Tabla1[[#This Row],[COS F2]]+Tabla1[[#This Row],[COS D2]]+Tabla1[[#This Row],[ALIMENTACION]]+Tabla1[[#This Row],[PRESTAMO]]+Tabla1[[#This Row],[PASAJES]] -> #REF!
A11: =TEXT(Tabla1[[#This Row],[FECHA ]],"DDDDD") -> viernes | B11: =_xlfn.IFNA(VLOOKUP(Tabla1[[#This Row],[DESTINO]],RUBRO!$Q$1:$R$9996,2,FALSE)," ") -> OBRA | C11: =WEEKNUM(Tabla1[[#This Row],[FECHA ]],2) -> 19 | D11: =TEXT(Tabla1[[#This Row],[FECHA ]],"MMM-YY") -> may-YY | E11: =VLOOKUP(Tabla1[[#This Row],[DNI ]],RUBRO!$F$1:$O$9996,7,FALSE) -> 5ta | F11: =VLOOKUP(Tabla1[[#This Row],[DNI ]],RUBRO!$F$1:$O$88,3,FALSE) -> MEC-04 | G11: =VLOOKUP(Tabla1[[#This Row],[DNI ]],RUBRO!$F$1:$O$9996,5,FALSE) -> MECANICO MONTAJISTA DE MAQUINARIA EXTRANJERA | H11: =VLOOKUP(Tabla1[[#This Row],[DNI ]],RUBRO!$F$1:$O$9996,6,FALSE) -> BUSTAMANTE GONZALES CARLOS | I11: 44323 | J11: 2 | K11: 27291529 | L11: =VLOOKUP(Tabla1[[#This Row],[DNI ]],RUBRO!$F$2:$O$9996,8,FALSE) -> 72.54 | M11: 0.29166667 | N11: 0.54166667 | O11: 0.58333333 | P11: 0.75 | Q11: =(Tabla1[[#This Row],[SALIDA]]-Tabla1[[#This Row],[FIN ]])+(Tabla1[[#This Row],[INICIO]]-Tabla1[[#This Row],[INGRESO]]) -> 0.41666667 | R11: =IF(J11=1,IF(Q11>$AU$1,$AU$1,Q11),0)+IF(J11=2,IF(Q11>$AU$3,$AU$3,Q11),0)+IF(J11=8,IF(Q11>$AU$5,$AU$5,Q11),0) -> 0.33333333 | S11: =IF(J11=1,IF(Q11>$AU$1,(Q11-R11),0),0)+IF(J11=2,IF(Q11>$AU$3,(Q11-R11),0),0)+IF(J11=8,IF(Q11>$AU$5,(Q11-R11),0),0) -> 0.083333333 | V11: =(Tabla1[[#This Row],[COS.BASE 3]]*0.25+Tabla1[[#This Row],[COS.BASE 3]])*Tabla1[[#This Row],[HORAS 25 % ]] -> 0 | W11: =(Tabla1[[#This Row],[COS.BASE 3]]*0.35+Tabla1[[#This Row],[COS.BASE 3]])*Tabla1[[#This Row],[HORAS 35% ]] -> 0 | X11: =SUM(Tabla1[[#This Row],[C.HORA.35]],Tabla1[[#This Row],[C.HORA.25]]) -> 0 | Z11: =Tabla1[[#This Row],[T.HORAS]]*24 -> 10 | AA11: =Tabla1[[#This Row],[H.NORMALES]]*24 -> 8 | AB11: =Tabla1[[#This Row],[H.EXTRAS]]*24 -> 2 | AC11: =IF(J11=1,(((R11*24)*(L11/9))),0)+IF(J11=2,(((R11*24)*(L11/8))),0)+IF(J11=8,(((R11*24)*(L11/8))),0) -> 72.54 | AD11: =Tabla1[[#This Row],[COS.BASE 2]]/8 -> 9.0675 | AE11: =Tabla1[[#This Row],[CST_H_E]]+Tabla1[[#This Row],[COS.BASE 2]] -> 72.54 | AF11: =+_xlfn.IFNA(INDEX(RUBRO!$W$2:$AA$732,MATCH(Tabla1[[#This Row],[FECHA ]],RUBRO!$W$2:$W$732,0),5)," ") -> 0 | AG11: =+_xlfn.IFNA(INDEX(RUBRO!$W$2:$AA$732,MATCH(Tabla1[[#This Row],[FECHA ]],RUBRO!$W$2:$W$732,0),2)," ") -> 0 | AH11: =IFERROR(Tabla1[[#This Row],[F]]*Tabla1[[#This Row],[COS.B+E]]," ") -> 0 | AI11: =IFERROR(Tabla1[[#This Row],[COS.B+E]]*Tabla1[[#This Row],[D]]," ") -> 0 | AJ11: =IFERROR(Tabla1[[#This Row],[F]]*#REF!," ") | AK11: =IFERROR(#REF!*Tabla1[[#This Row],[D]]," ") | AO11: =+Tabla1[[#This Row],[COS.B+E]]+Tabla1[[#This Row],[COS.F1]]+Tabla1[[#This Row],[COS.D1]]+Tabla1[[#This Row],[ALIMENTACION]]+Tabla1[[#This Row],[PRESTAMO]]+AN11 -> 72.54 | AP11: =+#REF!+Tabla1[[#This Row],[COS F2]]+Tabla1[[#This Row],[COS D2]]+Tabla1[[#This Row],[ALIMENTACION]]+Tabla1[[#This Row],[PRESTAMO]]+Tabla1[[#This Row],[PASAJES]] -> #REF!
A12: =TEXT(Tabla1[[#This Row],[FECHA ]],"DDDDD") -> viernes | B12: =_xlfn.IFNA(VLOOKUP(Tabla1[[#This Row],[DESTINO]],RUBRO!$Q$1:$R$9996,2,FALSE)," ") -> PLANTA | C12: =WEEKNUM(Tabla1[[#This Row],[FECHA ]],2) -> 19 | D12: =TEXT(Tabla1[[#This Row],[FECHA ]],"MMM-YY") -> may-YY | E12: =VLOOKUP(Tabla1[[#This Row],[DNI ]],RUBRO!$F$1:$O$9996,7,FALSE) -> 5ta | F12: =VLOOKUP(Tabla1[[#This Row],[DNI ]],RUBRO!$F$1:$O$88,3,FALSE) -> TECMN-03 | G12: =VLOOKUP(Tabla1[[#This Row],[DNI ]],RUBRO!$F$1:$O$9996,5,FALSE) -> TECNICO ELECTRICO MONTAJISTA DE MAQUINARIA | H12: =VLOOKUP(Tabla1[[#This Row],[DNI ]],RUBRO!$F$1:$O$9996,6,FALSE) -> CAMIZAN CUNIAS LENDER NEYDEN | I12: 44323 | J12: 1 | K12: 47711616 | L12: =VLOOKUP(Tabla1[[#This Row],[DNI ]],RUBRO!$F$2:$O$9996,8,FALSE) -> 47.73 | M12: 0.29166667 | N12: 0.54166667 | O12: 0.58333333 | P12: 0.70833333 | Q12: =(Tabla1[[#This Row],[SALIDA]]-Tabla1[[#This Row],[FIN ]])+(Tabla1[[#This Row],[INICIO]]-Tabla1[[#This Row],[INGRESO]]) -> 0.375 | R12: =IF(J12=1,IF(Q12>$AU$1,$AU$1,Q12),0)+IF(J12=2,IF(Q12>$AU$3,$AU$3,Q12),0)+IF(J12=8,IF(Q12>$AU$5,$AU$5,Q12),0) -> 0.375 | S12: =IF(J12=1,IF(Q12>$AU$1,(Q12-R12),0),0)+IF(J12=2,IF(Q12>$AU$3,(Q12-R12),0),0)+IF(J12=8,IF(Q12>$AU$5,(Q12-R12),0),0) -> 0 | V12: =(Tabla1[[#This Row],[COS.BASE 3]]*0.25+Tabla1[[#This Row],[COS.BASE 3]])*Tabla1[[#This Row],[HORAS 25 % ]] -> 0 | W12: =(Tabla1[[#This Row],[COS.BASE 3]]*0.35+Tabla1[[#This Row],[COS.BASE 3]])*Tabla1[[#This Row],[HORAS 35% ]] -> 0 | X12: =SUM(Tabla1[[#This Row],[C.HORA.35]],Tabla1[[#This Row],[C.HORA.25]]) -> 0 | Z12: =Tabla1[[#This Row],[T.HORAS]]*24 -> 9 | AA12: =Tabla1[[#This Row],[H.NORMALES]]*24 -> 9 | AB12: =Tabla1[[#This Row],[H.EXTRAS]]*24 -> 0 | AC12: =IF(J12=1,(((R12*24)*(L12/9))),0)+IF(J12=2,(((R12*24)*(L12/8))),0)+IF(J12=8,(((R12*24)*(L12/8))),0) -> 47.73 | AD12: =Tabla1[[#This Row],[COS.BASE 2]]/8 -> 5.96625 | AE12: =Tabla1[[#This Row],[CST_H_E]]+Tabla1[[#This Row],[COS.BASE 2]] -> 47.73 | AF12: =+_xlfn.IFNA(INDEX(RUBRO!$W$2:$AA$732,MATCH(Tabla1[[#This Row],[FECHA ]],RUBRO!$W$2:$W$732,0),5)," ") -> 0 | AG12: =+_xlfn.IFNA(INDEX(RUBRO!$W$2:$AA$732,MATCH(Tabla1[[#This Row],[FECHA ]],RUBRO!$W$2:$W$732,0),2)," ") -> 0 | AH12: =IFERROR(Tabla1[[#This Row],[F]]*Tabla1[[#This Row],[COS.B+E]]," ") -> 0 | AI12: =IFERROR(Tabla1[[#This Row],[COS.B+E]]*Tabla1[[#This Row],[D]]," ") -> 0 | AJ12: =IFERROR(Tabla1[[#This Row],[F]]*#REF!," ") | AK12: =IFERROR(#REF!*Tabla1[[#This Row],[D]]," ") | AO12: =+Tabla1[[#This Row],[COS.B+E]]+Tabla1[[#This Row],[COS.F1]]+Tabla1[[#This Row],[COS.D1]]+Tabla1[[#This Row],[ALIMENTACION]]+Tabla1[[#This Row],[PRESTAMO]]+AN12 -> 47.73 | AP12: =+#REF!+Tabla1[[#This Row],[COS F2]]+Tabla1[[#This Row],[COS D2]]+Tabla1[[#This Row],[ALIMENTACION]]+Tabla1[[#This Row],[PRESTAMO]]+Tabla1[[#This Row],[PASAJES]] -> #REF!
A13: =TEXT(Tabla1[[#This Row],[FECHA ]],"DDDDD") -> viernes | B13: =_xlfn.IFNA(VLOOKUP(Tabla1[[#This Row],[DESTINO]],RUBRO!$Q$1:$R$9996,2,FALSE)," ") -> OBRA | C13: =WEEKNUM(Tabla1[[#This Row],[FECHA ]],2) -> 19 | D13: =TEXT(Tabla1[[#This Row],[FECHA ]],"MMM-YY") -> may-YY | E13: =VLOOKUP(Tabla1[[#This Row],[DNI ]],RUBRO!$F$1:$O$9996,7,FALSE) -> 5ta | F13: =VLOOKUP(Tabla1[[#This Row],[DNI ]],RUBRO!$F$1:$O$88,3,FALSE) -> TEC-05 | G13: =VLOOKUP(Tabla1[[#This Row],[DNI ]],RUBRO!$F$1:$O$9996,5,FALSE) -> TECNICO MECANICO MONTAJISTA DE NAVE INDUSTRIAL | H13: =VLOOKUP(Tabla1[[#This Row],[DNI ]],RUBRO!$F$1:$O$9996,6,FALSE) -> CAVERO ANCAJIMA JHONATAN | I13: 44323 | J13: 2 | K13: 48237026 | L13: =VLOOKUP(Tabla1[[#This Row],[DNI ]],RUBRO!$F$2:$O$9996,8,FALSE) -> 52.2 | M13: 0.29166667 | N13: 0.54166667 | O13: 0.58333333 | P13: 0.75 | Q13: =(Tabla1[[#This Row],[SALIDA]]-Tabla1[[#This Row],[FIN ]])+(Tabla1[[#This Row],[INICIO]]-Tabla1[[#This Row],[INGRESO]]) -> 0.41666667 | R13: =IF(J13=1,IF(Q13>$AU$1,$AU$1,Q13),0)+IF(J13=2,IF(Q13>$AU$3,$AU$3,Q13),0)+IF(J13=8,IF(Q13>$AU$5,$AU$5,Q13),0) -> 0.33333333 | S13: =IF(J13=1,IF(Q13>$AU$1,(Q13-R13),0),0)+IF(J13=2,IF(Q13>$AU$3,(Q13-R13),0),0)+IF(J13=8,IF(Q13>$AU$5,(Q13-R13),0),0) -> 0.083333333 | V13: =(Tabla1[[#This Row],[COS.BASE 3]]*0.25+Tabla1[[#This Row],[COS.BASE 3]])*Tabla1[[#This Row],[HORAS 25 % ]] -> 0 | W13: =(Tabla1[[#This Row],[COS.BASE 3]]*0.35+Tabla1[[#This Row],[COS.BASE 3]])*Tabla1[[#This Row],[HORAS 35% ]] -> 0 | X13: =SUM(Tabla1[[#This Row],[C.HORA.35]],Tabla1[[#This Row],[C.HORA.25]]) -> 0 | Z13: =Tabla1[[#This Row],[T.HORAS]]*24 -> 10 | AA13: =Tabla1[[#This Row],[H.NORMALES]]*24 -> 8 | AB13: =Tabla1[[#This Row],[H.EXTRAS]]*24 -> 2 | AC13: =IF(J13=1,(((R13*24)*(L13/9))),0)+IF(J13=2,(((R13*24)*(L13/8))),0)+IF(J13=8,(((R13*24)*(L13/8))),0) -> 52.2 | AD13: =Tabla1[[#This Row],[COS.BASE 2]]/8 -> 6.525 | AE13: =Tabla1[[#This Row],[CST_H_E]]+Tabla1[[#This Row],[COS.BASE 2]] -> 52.2 | AF13: =+_xlfn.IFNA(INDEX(RUBRO!$W$2:$AA$732,MATCH(Tabla1[[#This Row],[FECHA ]],RUBRO!$W$2:$W$732,0),5)," ") -> 0 | AG13: =+_xlfn.IFNA(INDEX(RUBRO!$W$2:$AA$732,MATCH(Tabla1[[#This Row],[FECHA ]],RUBRO!$W$2:$W$732,0),2)," ") -> 0 | AH13: =IFERROR(Tabla1[[#This Row],[F]]*Tabla1[[#This Row],[COS.B+E]]," ") -> 0 | AI13: =IFERROR(Tabla1[[#This Row],[COS.B+E]]*Tabla1[[#This Row],[D]]," ") -> 0 | AJ13: =IFERROR(Tabla1[[#This Row],[F]]*#REF!," ") | AK13: =IFERROR(#REF!*Tabla1[[#This Row],[D]]," ") | AO13: =+Tabla1[[#This Row],[COS.B+E]]+Tabla1[[#This Row],[COS.F1]]+Tabla1[[#This Row],[COS.D1]]+Tabla1[[#This Row],[ALIMENTACION]]+Tabla1[[#This Row],[PRESTAMO]]+AN13 -> 52.2 | AP13: =+#REF!+Tabla1[[#This Row],[COS F2]]+Tabla1[[#This Row],[COS D2]]+Tabla1[[#This Row],[ALIMENTACION]]+Tabla1[[#This Row],[PRESTAMO]]+Tabla1[[#This Row],[PASAJES]] -> #REF!
A14: =TEXT(Tabla1[[#This Row],[FECHA ]],"DDDDD") -> viernes | B14: =_xlfn.IFNA(VLOOKUP(Tabla1[[#This Row],[DESTINO]],RUBRO!$Q$1:$R$9996,2,FALSE)," ") -> OBRA | C14: =WEEKNUM(Tabla1[[#This Row],[FECHA ]],2) -> 19 | D14: =TEXT(Tabla1[[#This Row],[FECHA ]],"MMM-YY") -> may-YY | E14: =VLOOKUP(Tabla1[[#This Row],[DNI ]],RUBRO!$F$1:$O$9996,7,FALSE) -> 5ta | F14: =VLOOKUP(Tabla1[[#This Row],[DNI ]],RUBRO!$F$1:$O$88,3,FALSE) -> TECME-03 | G14: =VLOOKUP(Tabla1[[#This Row],[DNI ]],RUBRO!$F$1:$O$9996,5,FALSE) -> TECNICO ELECTRICO MONTAJISTA DE MAQUINARIA EXTRANJERA | H14: =VLOOKUP(Tabla1[[#This Row],[DNI ]],RUBRO!$F$1:$O$9996,6,FALSE) -> CHAQUILA JIMENEZ VICTOR JHEYNER | I14: 44323 | J14: 2 | K14: 47055982 | L14: =VLOOKUP(Tabla1[[#This Row],[DNI ]],RUBRO!$F$2:$O$9996,8,FALSE) -> 73.72 | M14: 0.29166667 | N14: 0.54166667 | O14: 0.58333333 | P14: 0.75 | Q14: =(Tabla1[[#This Row],[SALIDA]]-Tabla1[[#This Row],[FIN ]])+(Tabla1[[#This Row],[INICIO]]-Tabla1[[#This Row],[INGRESO]]) -> 0.41666667 | R14: =IF(J14=1,IF(Q14>$AU$1,$AU$1,Q14),0)+IF(J14=2,IF(Q14>$AU$3,$AU$3,Q14),0)+IF(J14=8,IF(Q14>$AU$5,$AU$5,Q14),0) -> 0.33333333 | S14: =IF(J14=1,IF(Q14>$AU$1,(Q14-R14),0),0)+IF(J14=2,IF(Q14>$AU$3,(Q14-R14),0),0)+IF(J14=8,IF(Q14>$AU$5,(Q14-R14),0),0) -> 0.083333333 | V14: =(Tabla1[[#This Row],[COS.BASE 3]]*0.25+Tabla1[[#This Row],[COS.BASE 3]])*Tabla1[[#This Row],[HORAS 25 % ]] -> 0 | W14: =(Tabla1[[#This Row],[COS.BASE 3]]*0.35+Tabla1[[#This Row],[COS.BASE 3]])*Tabla1[[#This Row],[HORAS 35% ]] -> 0 | X14: =SUM(Tabla1[[#This Row],[C.HORA.35]],Tabla1[[#This Row],[C.HORA.25]]) -> 0 | Z14: =Tabla1[[#This Row],[T.HORAS]]*24 -> 10 | AA14: =Tabla1[[#This Row],[H.NORMALES]]*24 -> 8 | AB14: =Tabla1[[#This Row],[H.EXTRAS]]*24 -> 2 | AC14: =IF(J14=1,(((R14*24)*(L14/9))),0)+IF(J14=2,(((R14*24)*(L14/8))),0)+IF(J14=8,(((R14*24)*(L14/8))),0) -> 73.72 | AD14: =Tabla1[[#This Row],[COS.BASE 2]]/8 -> 9.215 | AE14: =Tabla1[[#This Row],[CST_H_E]]+Tabla1[[#This Row],[COS.BASE 2]] -> 73.72 | AF14: =+_xlfn.IFNA(INDEX(RUBRO!$W$2:$AA$732,MATCH(Tabla1[[#This Row],[FECHA ]],RUBRO!$W$2:$W$732,0),5)," ") -> 0 | AG14: =+_xlfn.IFNA(INDEX(RUBRO!$W$2:$AA$732,MATCH(Tabla1[[#This Row],[FECHA ]],RUBRO!$W$2:$W$732,0),2)," ") -> 0 | AH14: =IFERROR(Tabla1[[#This Row],[F]]*Tabla1[[#This Row],[COS.B+E]]," ") -> 0 | AI14: =IFERROR(Tabla1[[#This Row],[COS.B+E]]*Tabla1[[#This Row],[D]]," ") -> 0 | AJ14: =IFERROR(Tabla1[[#This Row],[F]]*#REF!," ") | AK14: =IFERROR(#REF!*Tabla1[[#This Row],[D]]," ") | AO14: =+Tabla1[[#This Row],[COS.B+E]]+Tabla1[[#This Row],[COS.F1]]+Tabla1[[#This Row],[COS.D1]]+Tabla1[[#This Row],[ALIMENTACION]]+Tabla1[[#This Row],[PRESTAMO]]+AN14 -> 73.72 | AP14: =+#REF!+Tabla1[[#This Row],[COS F2]]+Tabla1[[#This Row],[COS D2]]+Tabla1[[#This Row],[ALIMENTACION]]+Tabla1[[#This Row],[PRESTAMO]]+Tabla1[[#This Row],[PASAJES]] -> #REF!
A15: =TEXT(Tabla1[[#This Row],[FECHA ]],"DDDDD") -> viernes | B15: =_xlfn.IFNA(VLOOKUP(Tabla1[[#This Row],[DESTINO]],RUBRO!$Q$1:$R$9996,2,FALSE)," ") -> OBRA | C15: =WEEKNUM(Tabla1[[#This Row],[FECHA ]],2) -> 19 | D15: =TEXT(Tabla1[[#This Row],[FECHA ]],"MMM-YY") -> may-YY | E15: =VLOOKUP(Tabla1[[#This Row],[DNI ]],RUBRO!$F$1:$O$9996,7,FALSE) -> 5ta | F15: =VLOOKUP(Tabla1[[#This Row],[DNI ]],RUBRO!$F$1:$O$88,3,FALSE) -> #N/A | G15: =VLOOKUP(Tabla1[[#This Row],[DNI ]],RUBRO!$F$1:$O$9996,5,FALSE) -> AYUDANTE DE PRODUCCION | H15: =VLOOKUP(Tabla1[[#This Row],[DNI ]],RUBRO!$F$1:$O$9996,6,FALSE) -> COPIA BALDERA NILSON | I15: 44323 | J15: 2 | K15: 48359730 | L15: =VLOOKUP(Tabla1[[#This Row],[DNI ]],RUBRO!$F$2:$O$9996,8,FALSE) -> 55 | M15: 0.29166667 | N15: 0.54166667 | O15: 0.58333333 | P15: 0.75 | Q15: =(Tabla1[[#This Row],[SALIDA]]-Tabla1[[#This Row],[FIN ]])+(Tabla1[[#This Row],[INICIO]]-Tabla1[[#This Row],[INGRESO]]) -> 0.41666667 | R15: =IF(J15=1,IF(Q15>$AU$1,$AU$1,Q15),0)+IF(J15=2,IF(Q15>$AU$3,$AU$3,Q15),0)+IF(J15=8,IF(Q15>$AU$5,$AU$5,Q15),0) -> 0.33333333 | S15: =IF(J15=1,IF(Q15>$AU$1,(Q15-R15),0),0)+IF(J15=2,IF(Q15>$AU$3,(Q15-R15),0),0)+IF(J15=8,IF(Q15>$AU$5,(Q15-R15),0),0) -> 0.083333333 | V15: =(Tabla1[[#This Row],[COS.BASE 3]]*0.25+Tabla1[[#This Row],[COS.BASE 3]])*Tabla1[[#This Row],[HORAS 25 % ]] -> 0 | W15: =(Tabla1[[#This Row],[COS.BASE 3]]*0.35+Tabla1[[#This Row],[COS.BASE 3]])*Tabla1[[#This Row],[HORAS 35% ]] -> 0 | X15: =SUM(Tabla1[[#This Row],[C.HORA.35]],Tabla1[[#This Row],[C.HORA.25]]) -> 0 | Z15: =Tabla1[[#This Row],[T.HORAS]]*24 -> 10 | AA15: =Tabla1[[#This Row],[H.NORMALES]]*24 -> 8 | AB15: =Tabla1[[#This Row],[H.EXTRAS]]*24 -> 2 | AC15: =IF(J15=1,(((R15*24)*(L15/9))),0)+IF(J15=2,(((R15*24)*(L15/8))),0)+IF(J15=8,(((R15*24)*(L15/8))),0) -> 55 | AD15: =Tabla1[[#This Row],[COS.BASE 2]]/8 -> 6.875 | AE15: =Tabla1[[#This Row],[CST_H_E]]+Tabla1[[#This Row],[COS.BASE 2]] -> 55 | AF15: =+_xlfn.IFNA(INDEX(RUBRO!$W$2:$AA$732,MATCH(Tabla1[[#This Row],[FECHA ]],RUBRO!$W$2:$W$732,0),5)," ") -> 0 | AG15: =+_xlfn.IFNA(INDEX(RUBRO!$W$2:$AA$732,MATCH(Tabla1[[#This Row],[FECHA ]],RUBRO!$W$2:$W$732,0),2)," ") -> 0 | AH15: =IFERROR(Tabla1[[#This Row],[F]]*Tabla1[[#This Row],[COS.B+E]]," ") -> 0 | AI15: =IFERROR(Tabla1[[#This Row],[COS.B+E]]*Tabla1[[#This Row],[D]]," ") -> 0 | AJ15: =IFERROR(Tabla1[[#This Row],[F]]*#REF!," ") | AK15: =IFERROR(#REF!*Tabla1[[#This Row],[D]]," ") | AO15: =+Tabla1[[#This Row],[COS.B+E]]+Tabla1[[#This Row],[COS.F1]]+Tabla1[[#This Row],[COS.D1]]+Tabla1[[#This Row],[ALIMENTACION]]+Tabla1[[#This Row],[PRESTAMO]]+AN15 -> 55 | AP15: =+#REF!+Tabla1[[#This Row],[COS F2]]+Tabla1[[#This Row],[COS D2]]+Tabla1[[#This Row],[ALIMENTACION]]+Tabla1[[#This Row],[PRESTAMO]]+Tabla1[[#This Row],[PASAJES]] -> #REF!
A16: =TEXT(Tabla1[[#This Row],[FECHA ]],"DDDDD") -> viernes | B16: =_xlfn.IFNA(VLOOKUP(Tabla1[[#This Row],[DESTINO]],RUBRO!$Q$1:$R$9996,2,FALSE)," ") -> PLANTA | C16: =WEEKNUM(Tabla1[[#This Row],[FECHA ]],2) -> 19 | D16: =TEXT(Tabla1[[#This Row],[FECHA ]],"MMM-YY") -> may-YY | E16: =VLOOKUP(Tabla1[[#This Row],[DNI ]],RUBRO!$F$1:$O$9996,7,FALSE) -> 5ta | F16: =VLOOKUP(Tabla1[[#This Row],[DNI ]],RUBRO!$F$1:$O$88,3,FALSE) -> OPE-01 | G16: =VLOOKUP(Tabla1[[#This Row],[DNI ]],RUBRO!$F$1:$O$9996,5,FALSE) -> OPERARIO SOLDADOR | H16: =VLOOKUP(Tabla1[[#This Row],[DNI ]],RUBRO!$F$1:$O$9996,6,FALSE) -> CORDOVA OJEDA JHON GIAMPIERRE | I16: 44323 | J16: 1 | K16: 74359947 | L16: =VLOOKUP(Tabla1[[#This Row],[DNI ]],RUBRO!$F$2:$O$9996,8,FALSE) -> 57.62 | M16: 0.29166667 | N16: 0.54166667 | O16: 0.58333333 | P16: 0.79166667 | Q16: =(Tabla1[[#This Row],[SALIDA]]-Tabla1[[#This Row],[FIN ]])+(Tabla1[[#This Row],[INICIO]]-Tabla1[[#This Row],[INGRESO]]) -> 0.45833333 | R16: =IF(J16=1,IF(Q16>$AU$1,$AU$1,Q16),0)+IF(J16=2,IF(Q16>$AU$3,$AU$3,Q16),0)+IF(J16=8,IF(Q16>$AU$5,$AU$5,Q16),0) -> 0.375 | S16: =IF(J16=1,IF(Q16>$AU$1,(Q16-R16),0),0)+IF(J16=2,IF(Q16>$AU$3,(Q16-R16),0),0)+IF(J16=8,IF(Q16>$AU$5,(Q16-R16),0),0) -> 0.083333333 | V16: =(Tabla1[[#This Row],[COS.BASE 3]]*0.25+Tabla1[[#This Row],[COS.BASE 3]])*Tabla1[[#This Row],[HORAS 25 % ]] -> 0 | W16: =(Tabla1[[#This Row],[COS.BASE 3]]*0.35+Tabla1[[#This Row],[COS.BASE 3]])*Tabla1[[#This Row],[HORAS 35% ]] -> 0 | X16: =SUM(Tabla1[[#This Row],[C.HORA.35]],Tabla1[[#This Row],[C.HORA.25]]) -> 0 | Z16: =Tabla1[[#This Row],[T.HORAS]]*24 -> 11 | AA16: =Tabla1[[#This Row],[H.NORMALES]]*24 -> 9 | AB16: =Tabla1[[#This Row],[H.EXTRAS]]*24 -> 2 | AC16: =IF(J16=1,(((R16*24)*(L16/9))),0)+IF(J16=2,(((R16*24)*(L16/8))),0)+IF(J16=8,(((R16*24)*(L16/8))),0) -> 57.62 | AD16: =Tabla1[[#This Row],[COS.BASE 2]]/8 -> 7.2025 | AE16: =Tabla1[[#This Row],[CST_H_E]]+Tabla1[[#This Row],[COS.BASE 2]] -> 57.62 | AF16: =+_xlfn.IFNA(INDEX(RUBRO!$W$2:$AA$732,MATCH(Tabla1[[#This Row],[FECHA ]],RUBRO!$W$2:$W$732,0),5)," ") -> 0 | AG16: =+_xlfn.IFNA(INDEX(RUBRO!$W$2:$AA$732,MATCH(Tabla1[[#This Row],[FECHA ]],RUBRO!$W$2:$W$732,0),2)," ") -> 0 | AH16: =IFERROR(Tabla1[[#This Row],[F]]*Tabla1[[#This Row],[COS.B+E]]," ") -> 0 | AI16: =IFERROR(Tabla1[[#This Row],[COS.B+E]]*Tabla1[[#This Row],[D]]," ") -> 0 | AJ16: =IFERROR(Tabla1[[#This Row],[F]]*#REF!," ") | AK16: =IFERROR(#REF!*Tabla1[[#This Row],[D]]," ") | AO16: =+Tabla1[[#This Row],[COS.B+E]]+Tabla1[[#This Row],[COS.F1]]+Tabla1[[#This Row],[COS.D1]]+Tabla1[[#This Row],[ALIMENTACION]]+Tabla1[[#This Row],[PRESTAMO]]+AN16 -> 57.62 | AP16: =+#REF!+Tabla1[[#This Row],[COS F2]]+Tabla1[[#This Row],[COS D2]]+Tabla1[[#This Row],[ALIMENTACION]]+Tabla1[[#This Row],[PRESTAMO]]+Tabla1[[#This Row],[PASAJES]] -> #REF!
A17: =TEXT(Tabla1[[#This Row],[FECHA ]],"DDDDD") -> viernes | B17: =_xlfn.IFNA(VLOOKUP(Tabla1[[#This Row],[DESTINO]],RUBRO!$Q$1:$R$9996,2,FALSE)," ") -> PLANTA | C17: =WEEKNUM(Tabla1[[#This Row],[FECHA ]],2) -> 19 | D17: =TEXT(Tabla1[[#This Row],[FECHA ]],"MMM-YY") -> may-YY | E17: =VLOOKUP(Tabla1[[#This Row],[DNI ]],RUBRO!$F$1:$O$9996,7,FALSE) -> 5ta | F17: =VLOOKUP(Tabla1[[#This Row],[DNI ]],RUBRO!$F$1:$O$88,3,FALSE) -> TEC-02 | G17: =VLOOKUP(Tabla1[[#This Row],[DNI ]],RUBRO!$F$1:$O$9996,5,FALSE) -> TECNICO MECANICO MONTAJISTA DE MAQUINARIA | H17: =VLOOKUP(Tabla1[[#This Row],[DNI ]],RUBRO!$F$1:$O$9996,6,FALSE) -> CORREA TORRES NOYLER | I17: 44323 | J17: 1 | K17: 47321409 | L17: =VLOOKUP(Tabla1[[#This Row],[DNI ]],RUBRO!$F$2:$O$9996,8,FALSE) -> 65 | M17: 0.29166667 | N17: 0.54166667 | O17: 0.58333333 | P17: 0.70833333 | Q17: =(Tabla1[[#This Row],[SALIDA]]-Tabla1[[#This Row],[FIN ]])+(Tabla1[[#This Row],[INICIO]]-Tabla1[[#This Row],[INGRESO]]) -> 0.375 | R17: =IF(J17=1,IF(Q17>$AU$1,$AU$1,Q17),0)+IF(J17=2,IF(Q17>$AU$3,$AU$3,Q17),0)+IF(J17=8,IF(Q17>$AU$5,$AU$5,Q17),0) -> 0.375 | S17: =IF(J17=1,IF(Q17>$AU$1,(Q17-R17),0),0)+IF(J17=2,IF(Q17>$AU$3,(Q17-R17),0),0)+IF(J17=8,IF(Q17>$AU$5,(Q17-R17),0),0) -> 0 | V17: =(Tabla1[[#This Row],[COS.BASE 3]]*0.25+Tabla1[[#This Row],[COS.BASE 3]])*Tabla1[[#This Row],[HORAS 25 % ]] -> 0 | W17: =(Tabla1[[#This Row],[COS.BASE 3]]*0.35+Tabla1[[#This Row],[COS.BASE 3]])*Tabla1[[#This Row],[HORAS 35% ]] -> 0 | X17: =SUM(Tabla1[[#This Row],[C.HORA.35]],Tabla1[[#This Row],[C.HORA.25]]) -> 0 | Z17: =Tabla1[[#This Row],[T.HORAS]]*24 -> 9 | AA17: =Tabla1[[#This Row],[H.NORMALES]]*24 -> 9 | AB17: =Tabla1[[#This Row],[H.EXTRAS]]*24 -> 0 | AC17: =IF(J17=1,(((R17*24)*(L17/9))),0)+IF(J17=2,(((R17*24)*(L17/8))),0)+IF(J17=8,(((R17*24)*(L17/8))),0) -> 65 | AD17: =Tabla1[[#This Row],[COS.BASE 2]]/8 -> 8.125 | AE17: =Tabla1[[#This Row],[CST_H_E]]+Tabla1[[#This Row],[COS.BASE 2]] -> 65 | AF17: =+_xlfn.IFNA(INDEX(RUBRO!$W$2:$AA$732,MATCH(Tabla1[[#This Row],[FECHA ]],RUBRO!$W$2:$W$732,0),5)," ") -> 0 | AG17: =+_xlfn.IFNA(INDEX(RUBRO!$W$2:$AA$732,MATCH(Tabla1[[#This Row],[FECHA ]],RUBRO!$W$2:$W$732,0),2)," ") -> 0 | AH17: =IFERROR(Tabla1[[#This Row],[F]]*Tabla1[[#This Row],[COS.B+E]]," ") -> 0 | AI17: =IFERROR(Tabla1[[#This Row],[COS.B+E]]*Tabla1[[#This Row],[D]]," ") -> 0 | AJ17: =IFERROR(Tabla1[[#This Row],[F]]*#REF!," ") | AK17: =IFERROR(#REF!*Tabla1[[#This Row],[D]]," ") | AO17: =+Tabla1[[#This Row],[COS.B+E]]+Tabla1[[#This Row],[COS.F1]]+Tabla1[[#This Row],[COS.D1]]+Tabla1[[#This Row],[ALIMENTACION]]+Tabla1[[#This Row],[PRESTAMO]]+AN17 -> 65 | AP17: =+#REF!+Tabla1[[#This Row],[COS F2]]+Tabla1[[#This Row],[COS D2]]+Tabla1[[#This Row],[ALIMENTACION]]+Tabla1[[#This Row],[PRESTAMO]]+Tabla1[[#This Row],[PASAJES]] -> #REF!
A18: =TEXT(Tabla1[[#This Row],[FECHA ]],"DDDDD") -> viernes | B18: =_xlfn.IFNA(VLOOKUP(Tabla1[[#This Row],[DESTINO]],RUBRO!$Q$1:$R$9996,2,FALSE)," ") -> OBRA | C18: =WEEKNUM(Tabla1[[#This Row],[FECHA ]],2) -> 19 | D18: =TEXT(Tabla1[[#This Row],[FECHA ]],"MMM-YY") -> may-YY | E18: =VLOOKUP(Tabla1[[#This Row],[DNI ]],RUBRO!$F$1:$O$9996,7,FALSE) -> 5ta | F18: =VLOOKUP(Tabla1[[#This Row],[DNI ]],RUBRO!$F$1:$O$88,3,FALSE) -> TEC-04 | G18: =VLOOKUP(Tabla1[[#This Row],[DNI ]],RUBRO!$F$1:$O$9996,5,FALSE) -> TECNICO MECANICO MONTAJISTA DE MAQUINARIA EXTRANJERA | H18: =VLOOKUP(Tabla1[[#This Row],[DNI ]],RUBRO!$F$1:$O$9996,6,FALSE) -> CUYA CAYCHO DANIEL LORENZO | I18: 44323 | J18: 2 | K18: 70133802 | L18: =VLOOKUP(Tabla1[[#This Row],[DNI ]],RUBRO!$F$2:$O$9996,8,FALSE) -> 66.92 | M18: 0.29166667 | N18: 0.54166667 | O18: 0.58333333 | P18: 0.75 | Q18: =(Tabla1[[#This Row],[SALIDA]]-Tabla1[[#This Row],[FIN ]])+(Tabla1[[#This Row],[INICIO]]-Tabla1[[#This Row],[INGRESO]]) -> 0.41666667 | R18: =IF(J18=1,IF(Q18>$AU$1,$AU$1,Q18),0)+IF(J18=2,IF(Q18>$AU$3,$AU$3,Q18),0)+IF(J18=8,IF(Q18>$AU$5,$AU$5,Q18),0) -> 0.33333333 | S18: =IF(J18=1,IF(Q18>$AU$1,(Q18-R18),0),0)+IF(J18=2,IF(Q18>$AU$3,(Q18-R18),0),0)+IF(J18=8,IF(Q18>$AU$5,(Q18-R18),0),0) -> 0.083333333 | V18: =(Tabla1[[#This Row],[COS.BASE 3]]*0.25+Tabla1[[#This Row],[COS.BASE 3]])*Tabla1[[#This Row],[HORAS 25 % ]] -> 0 | W18: =(Tabla1[[#This Row],[COS.BASE 3]]*0.35+Tabla1[[#This Row],[COS.BASE 3]])*Tabla1[[#This Row],[HORAS 35% ]] -> 0 | X18: =SUM(Tabla1[[#This Row],[C.HORA.35]],Tabla1[[#This Row],[C.HORA.25]]) -> 0 | Z18: =Tabla1[[#This Row],[T.HORAS]]*24 -> 10 | AA18: =Tabla1[[#This Row],[H.NORMALES]]*24 -> 8 | AB18: =Tabla1[[#This Row],[H.EXTRAS]]*24 -> 2 | AC18: =IF(J18=1,(((R18*24)*(L18/9))),0)+IF(J18=2,(((R18*24)*(L18/8))),0)+IF(J18=8,(((R18*24)*(L18/8))),0) -> 66.92 | AD18: =Tabla1[[#This Row],[COS.BASE 2]]/8 -> 8.365 | AE18: =Tabla1[[#This Row],[CST_H_E]]+Tabla1[[#This Row],[COS.BASE 2]] -> 66.92 | AF18: =+_xlfn.IFNA(INDEX(RUBRO!$W$2:$AA$732,MATCH(Tabla1[[#This Row],[FECHA ]],RUBRO!$W$2:$W$732,0),5)," ") -> 0 | AG18: =+_xlfn.IFNA(INDEX(RUBRO!$W$2:$AA$732,MATCH(Tabla1[[#This Row],[FECHA ]],RUBRO!$W$2:$W$732,0),2)," ") -> 0 | AH18: =IFERROR(Tabla1[[#This Row],[F]]*Tabla1[[#This Row],[COS.B+E]]," ") -> 0 | AI18: =IFERROR(Tabla1[[#This Row],[COS.B+E]]*Tabla1[[#This Row],[D]]," ") -> 0 | AJ18: =IFERROR(Tabla1[[#This Row],[F]]*#REF!," ") | AK18: =IFERROR(#REF!*Tabla1[[#This Row],[D]]," ") | AO18: =+Tabla1[[#This Row],[COS.B+E]]+Tabla1[[#This Row],[COS.F1]]+Tabla1[[#This Row],[COS.D1]]+Tabla1[[#This Row],[ALIMENTACION]]+Tabla1[[#This Row],[PRESTAMO]]+AN18 -> 66.92 | AP18: =+#REF!+Tabla1[[#This Row],[COS F2]]+Tabla1[[#This Row],[COS D2]]+Tabla1[[#This Row],[ALIMENTACION]]+Tabla1[[#This Row],[PRESTAMO]]+Tabla1[[#This Row],[PASAJES]] -> #REF!
A19: =TEXT(Tabla1[[#This Row],[FECHA ]],"DDDDD") -> viernes | B19: =_xlfn.IFNA(VLOOKUP(Tabla1[[#This Row],[DESTINO]],RUBRO!$Q$1:$R$9996,2,FALSE)," ") -> PLANTA | C19: =WEEKNUM(Tabla1[[#This Row],[FECHA ]],2) -> 19 | D19: =TEXT(Tabla1[[#This Row],[FECHA ]],"MMM-YY") -> may-YY | E19: =VLOOKUP(Tabla1[[#This Row],[DNI ]],RUBRO!$F$1:$O$9996,7,FALSE) -> 4ta | F19: =VLOOKUP(Tabla1[[#This Row],[DNI ]],RUBRO!$F$1:$O$88,3,FALSE) -> #N/A | G19: =VLOOKUP(Tabla1[[#This Row],[DNI ]],RUBRO!$F$1:$O$9996,5,FALSE) -> TECNICO SOLDADOR | H19: =VLOOKUP(Tabla1[[#This Row],[DNI ]],RUBRO!$F$1:$O$9996,6,FALSE) -> DAMIAN DAMIAN MIGUEL ANGEL | I19: 44323 | J19: 1 | K19: 75494335 | L19: =VLOOKUP(Tabla1[[#This Row],[DNI ]],RUBRO!$F$2:$O$9996,8,FALSE) -> 90 | M19: 0.29166667 | N19: 0.54166667 | O19: 0.55208333 | P19: 0.67708333 | Q19: =(Tabla1[[#This Row],[SALIDA]]-Tabla1[[#This Row],[FIN ]])+(Tabla1[[#This Row],[INICIO]]-Tabla1[[#This Row],[INGRESO]]) -> 0.375 | R19: =IF(J19=1,IF(Q19>$AU$1,$AU$1,Q19),0)+IF(J19=2,IF(Q19>$AU$3,$AU$3,Q19),0)+IF(J19=8,IF(Q19>$AU$5,$AU$5,Q19),0) -> 0.375 | S19: =IF(J19=1,IF(Q19>$AU$1,(Q19-R19),0),0)+IF(J19=2,IF(Q19>$AU$3,(Q19-R19),0),0)+IF(J19=8,IF(Q19>$AU$5,(Q19-R19),0),0) -> 0 | V19: =(Tabla1[[#This Row],[COS.BASE 3]]*0.25+Tabla1[[#This Row],[COS.BASE 3]])*Tabla1[[#This Row],[HORAS 25 % ]] -> 0 | W19: =(Tabla1[[#This Row],[COS.BASE 3]]*0.35+Tabla1[[#This Row],[COS.BASE 3]])*Tabla1[[#This Row],[HORAS 35% ]] -> 0 | X19: =SUM(Tabla1[[#This Row],[C.HORA.35]],Tabla1[[#This Row],[C.HORA.25]]) -> 0 | Z19: =Tabla1[[#This Row],[T.HORAS]]*24 -> 9 | AA19: =Tabla1[[#This Row],[H.NORMALES]]*24 -> 9 | AB19: =Tabla1[[#This Row],[H.EXTRAS]]*24 -> 0 | AC19: =IF(J19=1,(((R19*24)*(L19/9))),0)+IF(J19=2,(((R19*24)*(L19/8))),0)+IF(J19=8,(((R19*24)*(L19/8))),0) -> 90 | AD19: =Tabla1[[#This Row],[COS.BASE 2]]/8 -> 11.25 | AE19: =Tabla1[[#This Row],[CST_H_E]]+Tabla1[[#This Row],[COS.BASE 2]] -> 90 | AF19: =+_xlfn.IFNA(INDEX(RUBRO!$W$2:$AA$732,MATCH(Tabla1[[#This Row],[FECHA ]],RUBRO!$W$2:$W$732,0),5)," ") -> 0 | AG19: =+_xlfn.IFNA(INDEX(RUBRO!$W$2:$AA$732,MATCH(Tabla1[[#This Row],[FECHA ]],RUBRO!$W$2:$W$732,0),2)," ") -> 0 | AH19: =IFERROR(Tabla1[[#This Row],[F]]*Tabla1[[#This Row],[COS.B+E]]," ") -> 0 | AI19: =IFERROR(Tabla1[[#This Row],[COS.B+E]]*Tabla1[[#This Row],[D]]," ") -> 0 | AJ19: =IFERROR(Tabla1[[#This Row],[F]]*#REF!," ") | AK19: =IFERROR(#REF!*Tabla1[[#This Row],[D]]," ") | AO19: =+Tabla1[[#This Row],[COS.B+E]]+Tabla1[[#This Row],[COS.F1]]+Tabla1[[#This Row],[COS.D1]]+Tabla1[[#This Row],[ALIMENTACION]]+Tabla1[[#This Row],[PRESTAMO]]+AN19 -> 90 | AP19: =+#REF!+Tabla1[[#This Row],[COS F2]]+Tabla1[[#This Row],[COS D2]]+Tabla1[[#This Row],[ALIMENTACION]]+Tabla1[[#This Row],[PRESTAMO]]+Tabla1[[#This Row],[PASAJES]] -> #REF!
A20: =TEXT(Tabla1[[#This Row],[FECHA ]],"DDDDD") -> viernes | B20: =_xlfn.IFNA(VLOOKUP(Tabla1[[#This Row],[DESTINO]],RUBRO!$Q$1:$R$9996,2,FALSE)," ") -> PLANTA | C20: =WEEKNUM(Tabla1[[#This Row],[FECHA ]],2) -> 19 | D20: =TEXT(Tabla1[[#This Row],[FECHA ]],"MMM-YY") -> may-YY | E20: =VLOOKUP(Tabla1[[#This Row],[DNI ]],RUBRO!$F$1:$O$9996,7,FALSE) -> 5ta | F20: =VLOOKUP(Tabla1[[#This Row],[DNI ]],RUBRO!$F$1:$O$88,3,FALSE) -> #N/A | G20: =VLOOKUP(Tabla1[[#This Row],[DNI ]],RUBRO!$F$1:$O$9996,5,FALSE) -> AYUDANTE DE PRODUCCION | H20: =VLOOKUP(Tabla1[[#This Row],[DNI ]],RUBRO!$F$1:$O$9996,6,FALSE) -> DELGADO CORONADO ROBERTO | I20: 44323 | J20: 1 | K20: 76288149 | L20: =VLOOKUP(Tabla1[[#This Row],[DNI ]],RUBRO!$F$2:$O$9996,8,FALSE) -> 44.32 | M20: 0.29166667 | N20: 0.54166667 | O20: 0.58333333 | P20: 0.75 | Q20: =(Tabla1[[#This Row],[SALIDA]]-Tabla1[[#This Row],[FIN ]])+(Tabla1[[#This Row],[INICIO]]-Tabla1[[#This Row],[INGRESO]]) -> 0.41666667 | R20: =IF(J20=1,IF(Q20>$AU$1,$AU$1,Q20),0)+IF(J20=2,IF(Q20>$AU$3,$AU$3,Q20),0)+IF(J20=8,IF(Q20>$AU$5,$AU$5,Q20),0) -> 0.375 | S20: =IF(J20=1,IF(Q20>$AU$1,(Q20-R20),0),0)+IF(J20=2,IF(Q20>$AU$3,(Q20-R20),0),0)+IF(J20=8,IF(Q20>$AU$5,(Q20-R20),0),0) -> 0.041666667 | V20: =(Tabla1[[#This Row],[COS.BASE 3]]*0.25+Tabla1[[#This Row],[COS.BASE 3]])*Tabla1[[#This Row],[HORAS 25 % ]] -> 0 | W20: =(Tabla1[[#This Row],[COS.BASE 3]]*0.35+Tabla1[[#This Row],[COS.BASE 3]])*Tabla1[[#This Row],[HORAS 35% ]] -> 0 | X20: =SUM(Tabla1[[#This Row],[C.HORA.35]],Tabla1[[#This Row],[C.HORA.25]]) -> 0 | Z20: =Tabla1[[#This Row],[T.HORAS]]*24 -> 10 | AA20: =Tabla1[[#This Row],[H.NORMALES]]*24 -> 9 | AB20: =Tabla1[[#This Row],[H.EXTRAS]]*24 -> 1 | AC20: =IF(J20=1,(((R20*24)*(L20/9))),0)+IF(J20=2,(((R20*24)*(L20/8))),0)+IF(J20=8,(((R20*24)*(L20/8))),0) -> 44.32 | AD20: =Tabla1[[#This Row],[COS.BASE 2]]/8 -> 5.54 | AE20: =Tabla1[[#This Row],[CST_H_E]]+Tabla1[[#This Row],[COS.BASE 2]] -> 44.32 | AF20: =+_xlfn.IFNA(INDEX(RUBRO!$W$2:$AA$732,MATCH(Tabla1[[#This Row],[FECHA ]],RUBRO!$W$2:$W$732,0),5)," ") -> 0 | AG20: =+_xlfn.IFNA(INDEX(RUBRO!$W$2:$AA$732,MATCH(Tabla1[[#This Row],[FECHA ]],RUBRO!$W$2:$W$732,0),2)," ") -> 0 | AH20: =IFERROR(Tabla1[[#This Row],[F]]*Tabla1[[#This Row],[COS.B+E]]," ") -> 0 | AI20: =IFERROR(Tabla1[[#This Row],[COS.B+E]]*Tabla1[[#This Row],[D]]," ") -> 0 | AJ20: =IFERROR(Tabla1[[#This Row],[F]]*#REF!," ") | AK20: =IFERROR(#REF!*Tabla1[[#This Row],[D]]," ") | AO20: =+Tabla1[[#This Row],[COS.B+E]]+Tabla1[[#This Row],[COS.F1]]+Tabla1[[#This Row],[COS.D1]]+Tabla1[[#This Row],[ALIMENTACION]]+Tabla1[[#This Row],[PRESTAMO]]+AN20 -> 44.32 | AP20: =+#REF!+Tabla1[[#This Row],[COS F2]]+Tabla1[[#This Row],[COS D2]]+Tabla1[[#This Row],[ALIMENTACION]]+Tabla1[[#This Row],[PRESTAMO]]+Tabla1[[#This Row],[PASAJES]] -> #REF!
A21: =TEXT(Tabla1[[#This Row],[FECHA ]],"DDDDD") -> viernes | B21: =_xlfn.IFNA(VLOOKUP(Tabla1[[#This Row],[DESTINO]],RUBRO!$Q$1:$R$9996,2,FALSE)," ") -> OBRA | C21: =WEEKNUM(Tabla1[[#This Row],[FECHA ]],2) -> 19 | D21: =TEXT(Tabla1[[#This Row],[FECHA ]],"MMM-YY") -> may-YY | E21: =VLOOKUP(Tabla1[[#This Row],[DNI ]],RUBRO!$F$1:$O$9996,7,FALSE) -> 5ta | F21: =VLOOKUP(Tabla1[[#This Row],[DNI ]],RUBRO!$F$1:$O$88,3,FALSE) -> #N/A | G21: =VLOOKUP(Tabla1[[#This Row],[DNI ]],RUBRO!$F$1:$O$9996,5,FALSE) -> AYUDANTE DE PRODUCCION | H21: =VLOOKUP(Tabla1[[#This Row],[DNI ]],RUBRO!$F$1:$O$9996,6,FALSE) -> DIAZ CABREJOS KELVIN | I21: 44323 | J21: 2 | K21: 75809362 | L21: =VLOOKUP(Tabla1[[#This Row],[DNI ]],RUBRO!$F$2:$O$9996,8,FALSE) -> 65 | M21: 0.29166667 | N21: 0.54166667 | O21: 0.58333333 | P21: 0.75 | Q21: =(Tabla1[[#This Row],[SALIDA]]-Tabla1[[#This Row],[FIN ]])+(Tabla1[[#This Row],[INICIO]]-Tabla1[[#This Row],[INGRESO]]) -> 0.41666667 | R21: =IF(J21=1,IF(Q21>$AU$1,$AU$1,Q21),0)+IF(J21=2,IF(Q21>$AU$3,$AU$3,Q21),0)+IF(J21=8,IF(Q21>$AU$5,$AU$5,Q21),0) -> 0.33333333 | S21: =IF(J21=1,IF(Q21>$AU$1,(Q21-R21),0),0)+IF(J21=2,IF(Q21>$AU$3,(Q21-R21),0),0)+IF(J21=8,IF(Q21>$AU$5,(Q21-R21),0),0) -> 0.083333333 | V21: =(Tabla1[[#This Row],[COS.BASE 3]]*0.25+Tabla1[[#This Row],[COS.BASE 3]])*Tabla1[[#This Row],[HORAS 25 % ]] -> 0 | W21: =(Tabla1[[#This Row],[COS.BASE 3]]*0.35+Tabla1[[#This Row],[COS.BASE 3]])*Tabla1[[#This Row],[HORAS 35% ]] -> 0 | X21: =SUM(Tabla1[[#This Row],[C.HORA.35]],Tabla1[[#This Row],[C.HORA.25]]) -> 0 | Z21: =Tabla1[[#This Row],[T.HORAS]]*24 -> 10 | AA21: =Tabla1[[#This Row],[H.NORMALES]]*24 -> 8 | AB21: =Tabla1[[#This Row],[H.EXTRAS]]*24 -> 2 | AC21: =IF(J21=1,(((R21*24)*(L21/9))),0)+IF(J21=2,(((R21*24)*(L21/8))),0)+IF(J21=8,(((R21*24)*(L21/8))),0) -> 65 | AD21: =Tabla1[[#This Row],[COS.BASE 2]]/8 -> 8.125 | AE21: =Tabla1[[#This Row],[CST_H_E]]+Tabla1[[#This Row],[COS.BASE 2]] -> 65 | AF21: =+_xlfn.IFNA(INDEX(RUBRO!$W$2:$AA$732,MATCH(Tabla1[[#This Row],[FECHA ]],RUBRO!$W$2:$W$732,0),5)," ") -> 0 | AG21: =+_xlfn.IFNA(INDEX(RUBRO!$W$2:$AA$732,MATCH(Tabla1[[#This Row],[FECHA ]],RUBRO!$W$2:$W$732,0),2)," ") -> 0 | AH21: =IFERROR(Tabla1[[#This Row],[F]]*Tabla1[[#This Row],[COS.B+E]]," ") -> 0 | AI21: =IFERROR(Tabla1[[#This Row],[COS.B+E]]*Tabla1[[#This Row],[D]]," ") -> 0 | AJ21: =IFERROR(Tabla1[[#This Row],[F]]*#REF!," ") | AK21: =IFERROR(#REF!*Tabla1[[#This Row],[D]]," ") | AO21: =+Tabla1[[#This Row],[COS.B+E]]+Tabla1[[#This Row],[COS.F1]]+Tabla1[[#This Row],[COS.D1]]+Tabla1[[#This Row],[ALIMENTACION]]+Tabla1[[#This Row],[PRESTAMO]]+AN21 -> 65 | AP21: =+#REF!+Tabla1[[#This Row],[COS F2]]+Tabla1[[#This Row],[COS D2]]+Tabla1[[#This Row],[ALIMENTACION]]+Tabla1[[#This Row],[PRESTAMO]]+Tabla1[[#This Row],[PASAJES]] -> #REF!
A22: =TEXT(Tabla1[[#This Row],[FECHA ]],"DDDDD") -> viernes | B22: =_xlfn.IFNA(VLOOKUP(Tabla1[[#This Row],[DESTINO]],RUBRO!$Q$1:$R$9996,2,FALSE)," ") -> PLANTA | C22: =WEEKNUM(Tabla1[[#This Row],[FECHA ]],2) -> 19 | D22: =TEXT(Tabla1[[#This Row],[FECHA ]],"MMM-YY") -> may-YY | E22: =VLOOKUP(Tabla1[[#This Row],[DNI ]],RUBRO!$F$1:$O$9996,7,FALSE) -> 4ta | F22: =VLOOKUP(Tabla1[[#This Row],[DNI ]],RUBRO!$F$1:$O$88,3,FALSE) -> OPE-01 | G22: =VLOOKUP(Tabla1[[#This Row],[DNI ]],RUBRO!$F$1:$O$9996,5,FALSE) -> OPERARIO SOLDADOR | H22: =VLOOKUP(Tabla1[[#This Row],[DNI ]],RUBRO!$F$1:$O$9996,6,FALSE) -> ENRIQUEZ GONZALES MIGUEL ANGEL | I22: 44323 | J22: 1 | K22: 42558469 | L22: =VLOOKUP(Tabla1[[#This Row],[DNI ]],RUBRO!$F$2:$O$9996,8,FALSE) -> 60 | M22: 0.29166667 | N22: 0.54166667 | O22: 0.58333333 | P22: 0.75 | Q22: =(Tabla1[[#This Row],[SALIDA]]-Tabla1[[#This Row],[FIN ]])+(Tabla1[[#This Row],[INICIO]]-Tabla1[[#This Row],[INGRESO]]) -> 0.41666667 | R22: =IF(J22=1,IF(Q22>$AU$1,$AU$1,Q22),0)+IF(J22=2,IF(Q22>$AU$3,$AU$3,Q22),0)+IF(J22=8,IF(Q22>$AU$5,$AU$5,Q22),0) -> 0.375 | S22: =IF(J22=1,IF(Q22>$AU$1,(Q22-R22),0),0)+IF(J22=2,IF(Q22>$AU$3,(Q22-R22),0),0)+IF(J22=8,IF(Q22>$AU$5,(Q22-R22),0),0) -> 0.041666667 | V22: =(Tabla1[[#This Row],[COS.BASE 3]]*0.25+Tabla1[[#This Row],[COS.BASE 3]])*Tabla1[[#This Row],[HORAS 25 % ]] -> 0 | W22: =(Tabla1[[#This Row],[COS.BASE 3]]*0.35+Tabla1[[#This Row],[COS.BASE 3]])*Tabla1[[#This Row],[HORAS 35% ]] -> 0 | X22: =SUM(Tabla1[[#This Row],[C.HORA.35]],Tabla1[[#This Row],[C.HORA.25]]) -> 0 | Z22: =Tabla1[[#This Row],[T.HORAS]]*24 -> 10 | AA22: =Tabla1[[#This Row],[H.NORMALES]]*24 -> 9 | AB22: =Tabla1[[#This Row],[H.EXTRAS]]*24 -> 1 | AC22: =IF(J22=1,(((R22*24)*(L22/9))),0)+IF(J22=2,(((R22*24)*(L22/8))),0)+IF(J22=8,(((R22*24)*(L22/8))),0) -> 60 | AD22: =Tabla1[[#This Row],[COS.BASE 2]]/8 -> 7.5 | AE22: =Tabla1[[#This Row],[CST_H_E]]+Tabla1[[#This Row],[COS.BASE 2]] -> 60 | AF22: =+_xlfn.IFNA(INDEX(RUBRO!$W$2:$AA$732,MATCH(Tabla1[[#This Row],[FECHA ]],RUBRO!$W$2:$W$732,0),5)," ") -> 0 | AG22: =+_xlfn.IFNA(INDEX(RUBRO!$W$2:$AA$732,MATCH(Tabla1[[#This Row],[FECHA ]],RUBRO!$W$2:$W$732,0),2)," ") -> 0 | AH22: =IFERROR(Tabla1[[#This Row],[F]]*Tabla1[[#This Row],[COS.B+E]]," ") -> 0 | AI22: =IFERROR(Tabla1[[#This Row],[COS.B+E]]*Tabla1[[#This Row],[D]]," ") -> 0 | AJ22: =IFERROR(Tabla1[[#This Row],[F]]*#REF!," ") | AK22: =IFERROR(#REF!*Tabla1[[#This Row],[D]]," ") | AO22: =+Tabla1[[#This Row],[COS.B+E]]+Tabla1[[#This Row],[COS.F1]]+Tabla1[[#This Row],[COS.D1]]+Tabla1[[#This Row],[ALIMENTACION]]+Tabla1[[#This Row],[PRESTAMO]]+AN22 -> 60 | AP22: =+#REF!+Tabla1[[#This Row],[COS F2]]+Tabla1[[#This Row],[COS D2]]+Tabla1[[#This Row],[ALIMENTACION]]+Tabla1[[#This Row],[PRESTAMO]]+Tabla1[[#This Row],[PASAJES]] -> #REF!
A23: =TEXT(Tabla1[[#This Row],[FECHA ]],"DDDDD") -> viernes | B23: =_xlfn.IFNA(VLOOKUP(Tabla1[[#This Row],[DESTINO]],RUBRO!$Q$1:$R$9996,2,FALSE)," ") -> PLANTA | C23: =WEEKNUM(Tabla1[[#This Row],[FECHA ]],2) -> 19 | D23: =TEXT(Tabla1[[#This Row],[FECHA ]],"MMM-YY") -> may-YY | E23: =VLOOKUP(Tabla1[[#This Row],[DNI ]],RUBRO!$F$1:$O$9996,7,FALSE) -> 5ta | F23: =VLOOKUP(Tabla1[[#This Row],[DNI ]],RUBRO!$F$1:$O$88,3,FALSE) -> MAE-02 | G23: =VLOOKUP(Tabla1[[#This Row],[DNI ]],RUBRO!$F$1:$O$9996,5,FALSE) -> MAESTRO MECANICO MONTAJISTA DE MAQUINARIA | H23: =VLOOKUP(Tabla1[[#This Row],[DNI ]],RUBRO!$F$1:$O$9996,6,FALSE) -> GRAUS JUAREZ MIGUEL RICARDO | I23: 44323 | J23: 1 | K23: 48046568 | L23: =VLOOKUP(Tabla1[[#This Row],[DNI ]],RUBRO!$F$2:$O$9996,8,FALSE) -> 68.15 | M23: 0.29166667 | N23: 0.54166667 | O23: 0.58333333 | P23: 0.70833333 | Q23: =(Tabla1[[#This Row],[SALIDA]]-Tabla1[[#This Row],[FIN ]])+(Tabla1[[#This Row],[INICIO]]-Tabla1[[#This Row],[INGRESO]]) -> 0.375 | R23: =IF(J23=1,IF(Q23>$AU$1,$AU$1,Q23),0)+IF(J23=2,IF(Q23>$AU$3,$AU$3,Q23),0)+IF(J23=8,IF(Q23>$AU$5,$AU$5,Q23),0) -> 0.375 | S23: =IF(J23=1,IF(Q23>$AU$1,(Q23-R23),0),0)+IF(J23=2,IF(Q23>$AU$3,(Q23-R23),0),0)+IF(J23=8,IF(Q23>$AU$5,(Q23-R23),0),0) -> 0 | V23: =(Tabla1[[#This Row],[COS.BASE 3]]*0.25+Tabla1[[#This Row],[COS.BASE 3]])*Tabla1[[#This Row],[HORAS 25 % ]] -> 0 | W23: =(Tabla1[[#This Row],[COS.BASE 3]]*0.35+Tabla1[[#This Row],[COS.BASE 3]])*Tabla1[[#This Row],[HORAS 35% ]] -> 0 | X23: =SUM(Tabla1[[#This Row],[C.HORA.35]],Tabla1[[#This Row],[C.HORA.25]]) -> 0 | Z23: =Tabla1[[#This Row],[T.HORAS]]*24 -> 9 | AA23: =Tabla1[[#This Row],[H.NORMALES]]*24 -> 9 | AB23: =Tabla1[[#This Row],[H.EXTRAS]]*24 -> 0 | AC23: =IF(J23=1,(((R23*24)*(L23/9))),0)+IF(J23=2,(((R23*24)*(L23/8))),0)+IF(J23=8,(((R23*24)*(L23/8))),0) -> 68.15 | AD23: =Tabla1[[#This Row],[COS.BASE 2]]/8 -> 8.51875 | AE23: =Tabla1[[#This Row],[CST_H_E]]+Tabla1[[#This Row],[COS.BASE 2]] -> 68.15 | AF23: =+_xlfn.IFNA(INDEX(RUBRO!$W$2:$AA$732,MATCH(Tabla1[[#This Row],[FECHA ]],RUBRO!$W$2:$W$732,0),5)," ") -> 0 | AG23: =+_xlfn.IFNA(INDEX(RUBRO!$W$2:$AA$732,MATCH(Tabla1[[#This Row],[FECHA ]],RUBRO!$W$2:$W$732,0),2)," ") -> 0 | AH23: =IFERROR(Tabla1[[#This Row],[F]]*Tabla1[[#This Row],[COS.B+E]]," ") -> 0 | AI23: =IFERROR(Tabla1[[#This Row],[COS.B+E]]*Tabla1[[#This Row],[D]]," ") -> 0 | AJ23: =IFERROR(Tabla1[[#This Row],[F]]*#REF!," ") | AK23: =IFERROR(#REF!*Tabla1[[#This Row],[D]]," ") | AO23: =+Tabla1[[#This Row],[COS.B+E]]+Tabla1[[#This Row],[COS.F1]]+Tabla1[[#This Row],[COS.D1]]+Tabla1[[#This Row],[ALIMENTACION]]+Tabla1[[#This Row],[PRESTAMO]]+AN23 -> 68.15 | AP23: =+#REF!+Tabla1[[#This Row],[COS F2]]+Tabla1[[#This Row],[COS D2]]+Tabla1[[#This Row],[ALIMENTACION]]+Tabla1[[#This Row],[PRESTAMO]]+Tabla1[[#This Row],[PASAJES]] -> #REF!
A24: =TEXT(Tabla1[[#This Row],[FECHA ]],"DDDDD") -> viernes | B24: =_xlfn.IFNA(VLOOKUP(Tabla1[[#This Row],[DESTINO]],RUBRO!$Q$1:$R$9996,2,FALSE)," ") -> PLANTA | C24: =WEEKNUM(Tabla1[[#This Row],[FECHA ]],2) -> 19 | D24: =TEXT(Tabla1[[#This Row],[FECHA ]],"MMM-YY") -> may-YY | E24: =VLOOKUP(Tabla1[[#This Row],[DNI ]],RUBRO!$F$1:$O$9996,7,FALSE) -> 5ta | F24: =VLOOKUP(Tabla1[[#This Row],[DNI ]],RUBRO!$F$1:$O$88,3,FALSE) -> #N/A | G24: =VLOOKUP(Tabla1[[#This Row],[DNI ]],RUBRO!$F$1:$O$9996,5,FALSE) -> AYUDANTE DE PRODUCCION | H24: =VLOOKUP(Tabla1[[#This Row],[DNI ]],RUBRO!$F$1:$O$9996,6,FALSE) -> GUERRERO CORDOVA ISMAEL | I24: 44323 | J24: 1 | K24: 75790434 | L24: =VLOOKUP(Tabla1[[#This Row],[DNI ]],RUBRO!$F$2:$O$9996,8,FALSE) -> 35.81 | M24: 0.29166667 | P24: 0.58333333 | Q24: =(Tabla1[[#This Row],[SALIDA]]-Tabla1[[#This Row],[FIN ]])+(Tabla1[[#This Row],[INICIO]]-Tabla1[[#This Row],[INGRESO]]) -> 0.29166667 | R24: =IF(J24=1,IF(Q24>$AU$1,$AU$1,Q24),0)+IF(J24=2,IF(Q24>$AU$3,$AU$3,Q24),0)+IF(J24=8,IF(Q24>$AU$5,$AU$5,Q24),0) -> 0.29166667 | S24: =IF(J24=1,IF(Q24>$AU$1,(Q24-R24),0),0)+IF(J24=2,IF(Q24>$AU$3,(Q24-R24),0),0)+IF(J24=8,IF(Q24>$AU$5,(Q24-R24),0),0) -> 0 | V24: =(Tabla1[[#This Row],[COS.BASE 3]]*0.25+Tabla1[[#This Row],[COS.BASE 3]])*Tabla1[[#This Row],[HORAS 25 % ]] -> 0 | W24: =(Tabla1[[#This Row],[COS.BASE 3]]*0.35+Tabla1[[#This Row],[COS.BASE 3]])*Tabla1[[#This Row],[HORAS 35% ]] -> 0 | X24: =SUM(Tabla1[[#This Row],[C.HORA.35]],Tabla1[[#This Row],[C.HORA.25]]) -> 0 | Z24: =Tabla1[[#This Row],[T.HORAS]]*24 -> 7 | AA24: =Tabla1[[#This Row],[H.NORMALES]]*24 -> 7 | AB24: =Tabla1[[#This Row],[H.EXTRAS]]*24 -> 0 | AC24: =IF(J24=1,(((R24*24)*(L24/9))),0)+IF(J24=2,(((R24*24)*(L24/8))),0)+IF(J24=8,(((R24*24)*(L24/8))),0) -> 27.852222 | AD24: =Tabla1[[#This Row],[COS.BASE 2]]/8 -> 3.4815278 | AE24: =Tabla1[[#This Row],[CST_H_E]]+Tabla1[[#This Row],[COS.BASE 2]] -> 27.852222 | AF24: =+_xlfn.IFNA(INDEX(RUBRO!$W$2:$AA$732,MATCH(Tabla1[[#This Row],[FECHA ]],RUBRO!$W$2:$W$732,0),5)," ") -> 0 | AG24: =+_xlfn.IFNA(INDEX(RUBRO!$W$2:$AA$732,MATCH(Tabla1[[#This Row],[FECHA ]],RUBRO!$W$2:$W$732,0),2)," ") -> 0 | AH24: =IFERROR(Tabla1[[#This Row],[F]]*Tabla1[[#This Row],[COS.B+E]]," ") -> 0 | AI24: =IFERROR(Tabla1[[#This Row],[COS.B+E]]*Tabla1[[#This Row],[D]]," ") -> 0 | AJ24: =IFERROR(Tabla1[[#This Row],[F]]*#REF!," ") | AK24: =IFERROR(#REF!*Tabla1[[#This Row],[D]]," ") | AO24: =+Tabla1[[#This Row],[COS.B+E]]+Tabla1[[#This Row],[COS.F1]]+Tabla1[[#This Row],[COS.D1]]+Tabla1[[#This Row],[ALIMENTACION]]+Tabla1[[#This Row],[PRESTAMO]]+AN24 -> 27.852222 | AP24: =+#REF!+Tabla1[[#This Row],[COS F2]]+Tabla1[[#This Row],[COS D2]]+Tabla1[[#This Row],[ALIMENTACION]]+Tabla1[[#This Row],[PRESTAMO]]+Tabla1[[#This Row],[PASAJES]] -> #REF!
A25: =TEXT(Tabla1[[#This Row],[FECHA ]],"DDDDD") -> viernes | B25: =_xlfn.IFNA(VLOOKUP(Tabla1[[#This Row],[DESTINO]],RUBRO!$Q$1:$R$9996,2,FALSE)," ") -> OBRA | C25: =WEEKNUM(Tabla1[[#This Row],[FECHA ]],2) -> 19 | D25: =TEXT(Tabla1[[#This Row],[FECHA ]],"MMM-YY") -> may-YY | E25: =VLOOKUP(Tabla1[[#This Row],[DNI ]],RUBRO!$F$1:$O$9996,7,FALSE) -> 4ta | F25: =VLOOKUP(Tabla1[[#This Row],[DNI ]],RUBRO!$F$1:$O$88,3,FALSE) -> TEC-01 | G25: =VLOOKUP(Tabla1[[#This Row],[DNI ]],RUBRO!$F$1:$O$9996,5,FALSE) -> TECNICO SOLDADOR | H25: =VLOOKUP(Tabla1[[#This Row],[DNI ]],RUBRO!$F$1:$O$9996,6,FALSE) -> GUEVARA PACHERREZ ERICK DANIEL | I25: 44323 | J25: 2 | K25: 45545014 | L25: =VLOOKUP(Tabla1[[#This Row],[DNI ]],RUBRO!$F$2:$O$9996,8,FALSE) -> 60 | M25: 0.29166667 | N25: 0.54166667 | O25: 0.58333333 | P25: 0.75 | Q25: =(Tabla1[[#This Row],[SALIDA]]-Tabla1[[#This Row],[FIN ]])+(Tabla1[[#This Row],[INICIO]]-Tabla1[[#This Row],[INGRESO]]) -> 0.41666667 | R25: =IF(J25=1,IF(Q25>$AU$1,$AU$1,Q25),0)+IF(J25=2,IF(Q25>$AU$3,$AU$3,Q25),0)+IF(J25=8,IF(Q25>$AU$5,$AU$5,Q25),0) -> 0.33333333 | S25: =IF(J25=1,IF(Q25>$AU$1,(Q25-R25),0),0)+IF(J25=2,IF(Q25>$AU$3,(Q25-R25),0),0)+IF(J25=8,IF(Q25>$AU$5,(Q25-R25),0),0) -> 0.083333333 | V25: =(Tabla1[[#This Row],[COS.BASE 3]]*0.25+Tabla1[[#This Row],[COS.BASE 3]])*Tabla1[[#This Row],[HORAS 25 % ]] -> 0 | W25: =(Tabla1[[#This Row],[COS.BASE 3]]*0.35+Tabla1[[#This Row],[COS.BASE 3]])*Tabla1[[#This Row],[HORAS 35% ]] -> 0 | X25: =SUM(Tabla1[[#This Row],[C.HORA.35]],Tabla1[[#This Row],[C.HORA.25]]) -> 0 | Z25: =Tabla1[[#This Row],[T.HORAS]]*24 -> 10 | AA25: =Tabla1[[#This Row],[H.NORMALES]]*24 -> 8 | AB25: =Tabla1[[#This Row],[H.EXTRAS]]*24 -> 2 | AC25: =IF(J25=1,(((R25*24)*(L25/9))),0)+IF(J25=2,(((R25*24)*(L25/8))),0)+IF(J25=8,(((R25*24)*(L25/8))),0) -> 60 | AD25: =Tabla1[[#This Row],[COS.BASE 2]]/8 -> 7.5 | AE25: =Tabla1[[#This Row],[CST_H_E]]+Tabla1[[#This Row],[COS.BASE 2]] -> 60 | AF25: =+_xlfn.IFNA(INDEX(RUBRO!$W$2:$AA$732,MATCH(Tabla1[[#This Row],[FECHA ]],RUBRO!$W$2:$W$732,0),5)," ") -> 0 | AG25: =+_xlfn.IFNA(INDEX(RUBRO!$W$2:$AA$732,MATCH(Tabla1[[#This Row],[FECHA ]],RUBRO!$W$2:$W$732,0),2)," ") -> 0 | AH25: =IFERROR(Tabla1[[#This Row],[F]]*Tabla1[[#This Row],[COS.B+E]]," ") -> 0 | AI25: =IFERROR(Tabla1[[#This Row],[COS.B+E]]*Tabla1[[#This Row],[D]]," ") -> 0 | AJ25: =IFERROR(Tabla1[[#This Row],[F]]*#REF!," ") | AK25: =IFERROR(#REF!*Tabla1[[#This Row],[D]]," ") | AO25: =+Tabla1[[#This Row],[COS.B+E]]+Tabla1[[#This Row],[COS.F1]]+Tabla1[[#This Row],[COS.D1]]+Tabla1[[#This Row],[ALIMENTACION]]+Tabla1[[#This Row],[PRESTAMO]]+AN25 -> 60 | AP25: =+#REF!+Tabla1[[#This Row],[COS F2]]+Tabla1[[#This Row],[COS D2]]+Tabla1[[#This Row],[ALIMENTACION]]+Tabla1[[#This Row],[PRESTAMO]]+Tabla1[[#This Row],[PASAJES]] -> #REF!
A26: =TEXT(Tabla1[[#This Row],[FECHA ]],"DDDDD") -> viernes | B26: =_xlfn.IFNA(VLOOKUP(Tabla1[[#This Row],[DESTINO]],RUBRO!$Q$1:$R$9996,2,FALSE)," ") -> OBRA | C26: =WEEKNUM(Tabla1[[#This Row],[FECHA ]],2) -> 19 | D26: =TEXT(Tabla1[[#This Row],[FECHA ]],"MMM-YY") -> may-YY | E26: =VLOOKUP(Tabla1[[#This Row],[DNI ]],RUBRO!$F$1:$O$9996,7,FALSE) -> 5ta | F26: =VLOOKUP(Tabla1[[#This Row],[DNI ]],RUBRO!$F$1:$O$88,3,FALSE) -> X6 | G26: =VLOOKUP(Tabla1[[#This Row],[DNI ]],RUBRO!$F$1:$O$9996,5,FALSE) -> SUPERVISOR DE MONTAJE Y DESMONTAJE | H26: =VLOOKUP(Tabla1[[#This Row],[DNI ]],RUBRO!$F$1:$O$9996,6,FALSE) -> HERRERA NAVARRO OSMER | I26: 44323 | J26: 2 | K26: 45327555 | L26: =VLOOKUP(Tabla1[[#This Row],[DNI ]],RUBRO!$F$2:$O$9996,8,FALSE) -> 62.31 | M26: 0.29166667 | N26: 0.54166667 | O26: 0.58333333 | P26: 0.75 | Q26: =(Tabla1[[#This Row],[SALIDA]]-Tabla1[[#This Row],[FIN ]])+(Tabla1[[#This Row],[INICIO]]-Tabla1[[#This Row],[INGRESO]]) -> 0.41666667 | R26: =IF(J26=1,IF(Q26>$AU$1,$AU$1,Q26),0)+IF(J26=2,IF(Q26>$AU$3,$AU$3,Q26),0)+IF(J26=8,IF(Q26>$AU$5,$AU$5,Q26),0) -> 0.33333333 | S26: =IF(J26=1,IF(Q26>$AU$1,(Q26-R26),0),0)+IF(J26=2,IF(Q26>$AU$3,(Q26-R26),0),0)+IF(J26=8,IF(Q26>$AU$5,(Q26-R26),0),0) -> 0.083333333 | V26: =(Tabla1[[#This Row],[COS.BASE 3]]*0.25+Tabla1[[#This Row],[COS.BASE 3]])*Tabla1[[#This Row],[HORAS 25 % ]] -> 0 | W26: =(Tabla1[[#This Row],[COS.BASE 3]]*0.35+Tabla1[[#This Row],[COS.BASE 3]])*Tabla1[[#This Row],[HORAS 35% ]] -> 0 | X26: =SUM(Tabla1[[#This Row],[C.HORA.35]],Tabla1[[#This Row],[C.HORA.25]]) -> 0 | Z26: =Tabla1[[#This Row],[T.HORAS]]*24 -> 10 | AA26: =Tabla1[[#This Row],[H.NORMALES]]*24 -> 8 | AB26: =Tabla1[[#This Row],[H.EXTRAS]]*24 -> 2 | AC26: =IF(J26=1,(((R26*24)*(L26/9))),0)+IF(J26=2,(((R26*24)*(L26/8))),0)+IF(J26=8,(((R26*24)*(L26/8))),0) -> 62.31 | AD26: =Tabla1[[#This Row],[COS.BASE 2]]/8 -> 7.78875 | AE26: =Tabla1[[#This Row],[CST_H_E]]+Tabla1[[#This Row],[COS.BASE 2]] -> 62.31 | AF26: =+_xlfn.IFNA(INDEX(RUBRO!$W$2:$AA$732,MATCH(Tabla1[[#This Row],[FECHA ]],RUBRO!$W$2:$W$732,0),5)," ") -> 0 | AG26: =+_xlfn.IFNA(INDEX(RUBRO!$W$2:$AA$732,MATCH(Tabla1[[#This Row],[FECHA ]],RUBRO!$W$2:$W$732,0),2)," ") -> 0 | AH26: =IFERROR(Tabla1[[#This Row],[F]]*Tabla1[[#This Row],[COS.B+E]]," ") -> 0 | AI26: =IFERROR(Tabla1[[#This Row],[COS.B+E]]*Tabla1[[#This Row],[D]]," ") -> 0 | AJ26: =IFERROR(Tabla1[[#This Row],[F]]*#REF!," ") | AK26: =IFERROR(#REF!*Tabla1[[#This Row],[D]]," ") | AO26: =+Tabla1[[#This Row],[COS.B+E]]+Tabla1[[#This Row],[COS.F1]]+Tabla1[[#This Row],[COS.D1]]+Tabla1[[#This Row],[ALIMENTACION]]+Tabla1[[#This Row],[PRESTAMO]]+AN26 -> 62.31 | AP26: =+#REF!+Tabla1[[#This Row],[COS F2]]+Tabla1[[#This Row],[COS D2]]+Tabla1[[#This Row],[ALIMENTACION]]+Tabla1[[#This Row],[PRESTAMO]]+Tabla1[[#This Row],[PASAJES]] -> #REF!
A27: =TEXT(Tabla1[[#This Row],[FECHA ]],"DDDDD") -> viernes | B27: =_xlfn.IFNA(VLOOKUP(Tabla1[[#This Row],[DESTINO]],RUBRO!$Q$1:$R$9996,2,FALSE)," ") -> PLANTA | C27: =WEEKNUM(Tabla1[[#This Row],[FECHA ]],2) -> 19 | D27: =TEXT(Tabla1[[#This Row],[FECHA ]],"MMM-YY") -> may-YY | E27: =VLOOKUP(Tabla1[[#This Row],[DNI ]],RUBRO!$F$1:$O$9996,7,FALSE) -> 5ta | F27: =VLOOKUP(Tabla1[[#This Row],[DNI ]],RUBRO!$F$1:$O$88,3,FALSE) -> TEC-04 | G27: =VLOOKUP(Tabla1[[#This Row],[DNI ]],RUBRO!$F$1:$O$9996,5,FALSE) -> TECNICO MECANICO MONTAJISTA DE MAQUINARIA EXTRANJERA | H27: =VLOOKUP(Tabla1[[#This Row],[DNI ]],RUBRO!$F$1:$O$9996,6,FALSE) -> IDROGO CHAVEZ EMANUEL | I27: 44323 | J27: 1 | K27: 46228460 | L27: =VLOOKUP(Tabla1[[#This Row],[DNI ]],RUBRO!$F$2:$O$9996,8,FALSE) -> 67.66 | M27: 0.29166667 | N27: 0.54166667 | O27: 0.58333333 | P27: 0.75 | Q27: =(Tabla1[[#This Row],[SALIDA]]-Tabla1[[#This Row],[FIN ]])+(Tabla1[[#This Row],[INICIO]]-Tabla1[[#This Row],[INGRESO]]) -> 0.41666667 | R27: =IF(J27=1,IF(Q27>$AU$1,$AU$1,Q27),0)+IF(J27=2,IF(Q27>$AU$3,$AU$3,Q27),0)+IF(J27=8,IF(Q27>$AU$5,$AU$5,Q27),0) -> 0.375 | S27: =IF(J27=1,IF(Q27>$AU$1,(Q27-R27),0),0)+IF(J27=2,IF(Q27>$AU$3,(Q27-R27),0),0)+IF(J27=8,IF(Q27>$AU$5,(Q27-R27),0),0) -> 0.041666667 | V27: =(Tabla1[[#This Row],[COS.BASE 3]]*0.25+Tabla1[[#This Row],[COS.BASE 3]])*Tabla1[[#This Row],[HORAS 25 % ]] -> 0 | W27: =(Tabla1[[#This Row],[COS.BASE 3]]*0.35+Tabla1[[#This Row],[COS.BASE 3]])*Tabla1[[#This Row],[HORAS 35% ]] -> 0 | X27: =SUM(Tabla1[[#This Row],[C.HORA.35]],Tabla1[[#This Row],[C.HORA.25]]) -> 0 | Z27: =Tabla1[[#This Row],[T.HORAS]]*24 -> 10 | AA27: =Tabla1[[#This Row],[H.NORMALES]]*24 -> 9 | AB27: =Tabla1[[#This Row],[H.EXTRAS]]*24 -> 1 | AC27: =IF(J27=1,(((R27*24)*(L27/9))),0)+IF(J27=2,(((R27*24)*(L27/8))),0)+IF(J27=8,(((R27*24)*(L27/8))),0) -> 67.66 | AD27: =Tabla1[[#This Row],[COS.BASE 2]]/8 -> 8.4575 | AE27: =Tabla1[[#This Row],[CST_H_E]]+Tabla1[[#This Row],[COS.BASE 2]] -> 67.66 | AF27: =+_xlfn.IFNA(INDEX(RUBRO!$W$2:$AA$732,MATCH(Tabla1[[#This Row],[FECHA ]],RUBRO!$W$2:$W$732,0),5)," ") -> 0 | AG27: =+_xlfn.IFNA(INDEX(RUBRO!$W$2:$AA$732,MATCH(Tabla1[[#This Row],[FECHA ]],RUBRO!$W$2:$W$732,0),2)," ") -> 0 | AH27: =IFERROR(Tabla1[[#This Row],[F]]*Tabla1[[#This Row],[COS.B+E]]," ") -> 0 | AI27: =IFERROR(Tabla1[[#This Row],[COS.B+E]]*Tabla1[[#This Row],[D]]," ") -> 0 | AJ27: =IFERROR(Tabla1[[#This Row],[F]]*#REF!," ") | AK27: =IFERROR(#REF!*Tabla1[[#This Row],[D]]," ") | AO27: =+Tabla1[[#This Row],[COS.B+E]]+Tabla1[[#This Row],[COS.F1]]+Tabla1[[#This Row],[COS.D1]]+Tabla1[[#This Row],[ALIMENTACION]]+Tabla1[[#This Row],[PRESTAMO]]+AN27 -> 67.66 | AP27: =+#REF!+Tabla1[[#This Row],[COS F2]]+Tabla1[[#This Row],[COS D2]]+Tabla1[[#This Row],[ALIMENTACION]]+Tabla1[[#This Row],[PRESTAMO]]+Tabla1[[#This Row],[PASAJES]] -> #REF!
A28: =TEXT(Tabla1[[#This Row],[FECHA ]],"DDDDD") -> viernes | B28: =_xlfn.IFNA(VLOOKUP(Tabla1[[#This Row],[DESTINO]],RUBRO!$Q$1:$R$9996,2,FALSE)," ") -> OBRA | C28: =WEEKNUM(Tabla1[[#This Row],[FECHA ]],2) -> 19 | D28: =TEXT(Tabla1[[#This Row],[FECHA ]],"MMM-YY") -> may-YY | E28: =VLOOKUP(Tabla1[[#This Row],[DNI ]],RUBRO!$F$1:$O$9996,7,FALSE) -> 5ta | F28: =VLOOKUP(Tabla1[[#This Row],[DNI ]],RUBRO!$F$1:$O$88,3,FALSE) -> #N/A | G28: =VLOOKUP(Tabla1[[#This Row],[DNI ]],RUBRO!$F$1:$O$9996,5,FALSE) -> AYUDANTE DE PRODUCCION | H28: =VLOOKUP(Tabla1[[#This Row],[DNI ]],RUBRO!$F$1:$O$9996,6,FALSE) -> JUNCO ORDOÑEZ SAMUEL | I28: 44323 | J28: 2 | K28: 75913657 | L28: =VLOOKUP(Tabla1[[#This Row],[DNI ]],RUBRO!$F$2:$O$9996,8,FALSE) -> 60 | M28: 0.29166667 | N28: 0.54166667 | O28: 0.58333333 | P28: 0.75 | Q28: =(Tabla1[[#This Row],[SALIDA]]-Tabla1[[#This Row],[FIN ]])+(Tabla1[[#This Row],[INICIO]]-Tabla1[[#This Row],[INGRESO]]) -> 0.41666667 | R28: =IF(J28=1,IF(Q28>$AU$1,$AU$1,Q28),0)+IF(J28=2,IF(Q28>$AU$3,$AU$3,Q28),0)+IF(J28=8,IF(Q28>$AU$5,$AU$5,Q28),0) -> 0.33333333 | S28: =IF(J28=1,IF(Q28>$AU$1,(Q28-R28),0),0)+IF(J28=2,IF(Q28>$AU$3,(Q28-R28),0),0)+IF(J28=8,IF(Q28>$AU$5,(Q28-R28),0),0) -> 0.083333333 | V28: =(Tabla1[[#This Row],[COS.BASE 3]]*0.25+Tabla1[[#This Row],[COS.BASE 3]])*Tabla1[[#This Row],[HORAS 25 % ]] -> 0 | W28: =(Tabla1[[#This Row],[COS.BASE 3]]*0.35+Tabla1[[#This Row],[COS.BASE 3]])*Tabla1[[#This Row],[HORAS 35% ]] -> 0 | X28: =SUM(Tabla1[[#This Row],[C.HORA.35]],Tabla1[[#This Row],[C.HORA.25]]) -> 0 | Z28: =Tabla1[[#This Row],[T.HORAS]]*24 -> 10 | AA28: =Tabla1[[#This Row],[H.NORMALES]]*24 -> 8 | AB28: =Tabla1[[#This Row],[H.EXTRAS]]*24 -> 2 | AC28: =IF(J28=1,(((R28*24)*(L28/9))),0)+IF(J28=2,(((R28*24)*(L28/8))),0)+IF(J28=8,(((R28*24)*(L28/8))),0) -> 60 | AD28: =Tabla1[[#This Row],[COS.BASE 2]]/8 -> 7.5 | AE28: =Tabla1[[#This Row],[CST_H_E]]+Tabla1[[#This Row],[COS.BASE 2]] -> 60 | AF28: =+_xlfn.IFNA(INDEX(RUBRO!$W$2:$AA$732,MATCH(Tabla1[[#This Row],[FECHA ]],RUBRO!$W$2:$W$732,0),5)," ") -> 0 | AG28: =+_xlfn.IFNA(INDEX(RUBRO!$W$2:$AA$732,MATCH(Tabla1[[#This Row],[FECHA ]],RUBRO!$W$2:$W$732,0),2)," ") -> 0 | AH28: =IFERROR(Tabla1[[#This Row],[F]]*Tabla1[[#This Row],[COS.B+E]]," ") -> 0 | AI28: =IFERROR(Tabla1[[#This Row],[COS.B+E]]*Tabla1[[#This Row],[D]]," ") -> 0 | AJ28: =IFERROR(Tabla1[[#This Row],[F]]*#REF!," ") | AK28: =IFERROR(#REF!*Tabla1[[#This Row],[D]]," ") | AO28: =+Tabla1[[#This Row],[COS.B+E]]+Tabla1[[#This Row],[COS.F1]]+Tabla1[[#This Row],[COS.D1]]+Tabla1[[#This Row],[ALIMENTACION]]+Tabla1[[#This Row],[PRESTAMO]]+AN28 -> 60 | AP28: =+#REF!+Tabla1[[#This Row],[COS F2]]+Tabla1[[#This Row],[COS D2]]+Tabla1[[#This Row],[ALIMENTACION]]+Tabla1[[#This Row],[PRESTAMO]]+Tabla1[[#This Row],[PASAJES]] -> #REF!
A29: =TEXT(Tabla1[[#This Row],[FECHA ]],"DDDDD") -> viernes | B29: =_xlfn.IFNA(VLOOKUP(Tabla1[[#This Row],[DESTINO]],RUBRO!$Q$1:$R$9996,2,FALSE)," ") -> PLANTA | C29: =WEEKNUM(Tabla1[[#This Row],[FECHA ]],2) -> 19 | D29: =TEXT(Tabla1[[#This Row],[FECHA ]],"MMM-YY") -> may-YY | E29: =VLOOKUP(Tabla1[[#This Row],[DNI ]],RUBRO!$F$1:$O$9996,7,FALSE) -> 5ta | F29: =VLOOKUP(Tabla1[[#This Row],[DNI ]],RUBRO!$F$1:$O$88,3,FALSE) -> MAE3G-01 | G29: =VLOOKUP(Tabla1[[#This Row],[DNI ]],RUBRO!$F$1:$O$9996,5,FALSE) -> MAESTRO SOLDADOR 3G | H29: =VLOOKUP(Tabla1[[#This Row],[DNI ]],RUBRO!$F$1:$O$9996,6,FALSE) -> LABAN SEVERINO EDWIN DENIS | I29: 44323 | J29: 1 | K29: 47466045 | L29: =VLOOKUP(Tabla1[[#This Row],[DNI ]],RUBRO!$F$2:$O$9996,8,FALSE) -> 70.38 | M29: 0.29166667 | N29: 0.54166667 | O29: 0.58333333 | P29: 0.70833333 | Q29: =(Tabla1[[#This Row],[SALIDA]]-Tabla1[[#This Row],[FIN ]])+(Tabla1[[#This Row],[INICIO]]-Tabla1[[#This Row],[INGRESO]]) -> 0.375 | R29: =IF(J29=1,IF(Q29>$AU$1,$AU$1,Q29),0)+IF(J29=2,IF(Q29>$AU$3,$AU$3,Q29),0)+IF(J29=8,IF(Q29>$AU$5,$AU$5,Q29),0) -> 0.375 | S29: =IF(J29=1,IF(Q29>$AU$1,(Q29-R29),0),0)+IF(J29=2,IF(Q29>$AU$3,(Q29-R29),0),0)+IF(J29=8,IF(Q29>$AU$5,(Q29-R29),0),0) -> 0 | V29: =(Tabla1[[#This Row],[COS.BASE 3]]*0.25+Tabla1[[#This Row],[COS.BASE 3]])*Tabla1[[#This Row],[HORAS 25 % ]] -> 0 | W29: =(Tabla1[[#This Row],[COS.BASE 3]]*0.35+Tabla1[[#This Row],[COS.BASE 3]])*Tabla1[[#This Row],[HORAS 35% ]] -> 0 | X29: =SUM(Tabla1[[#This Row],[C.HORA.35]],Tabla1[[#This Row],[C.HORA.25]]) -> 0 | Z29: =Tabla1[[#This Row],[T.HORAS]]*24 -> 9 | AA29: =Tabla1[[#This Row],[H.NORMALES]]*24 -> 9 | AB29: =Tabla1[[#This Row],[H.EXTRAS]]*24 -> 0 | AC29: =IF(J29=1,(((R29*24)*(L29/9))),0)+IF(J29=2,(((R29*24)*(L29/8))),0)+IF(J29=8,(((R29*24)*(L29/8))),0) -> 70.38 | AD29: =Tabla1[[#This Row],[COS.BASE 2]]/8 -> 8.7975 | AE29: =Tabla1[[#This Row],[CST_H_E]]+Tabla1[[#This Row],[COS.BASE 2]] -> 70.38 | AF29: =+_xlfn.IFNA(INDEX(RUBRO!$W$2:$AA$732,MATCH(Tabla1[[#This Row],[FECHA ]],RUBRO!$W$2:$W$732,0),5)," ") -> 0 | AG29: =+_xlfn.IFNA(INDEX(RUBRO!$W$2:$AA$732,MATCH(Tabla1[[#This Row],[FECHA ]],RUBRO!$W$2:$W$732,0),2)," ") -> 0 | AH29: =IFERROR(Tabla1[[#This Row],[F]]*Tabla1[[#This Row],[COS.B+E]]," ") -> 0 | AI29: =IFERROR(Tabla1[[#This Row],[COS.B+E]]*Tabla1[[#This Row],[D]]," ") -> 0 | AJ29: =IFERROR(Tabla1[[#This Row],[F]]*#REF!," ") | AK29: =IFERROR(#REF!*Tabla1[[#This Row],[D]]," ") | AO29: =+Tabla1[[#This Row],[COS.B+E]]+Tabla1[[#This Row],[COS.F1]]+Tabla1[[#This Row],[COS.D1]]+Tabla1[[#This Row],[ALIMENTACION]]+Tabla1[[#This Row],[PRESTAMO]]+AN29 -> 70.38 | AP29: =+#REF!+Tabla1[[#This Row],[COS F2]]+Tabla1[[#This Row],[COS D2]]+Tabla1[[#This Row],[ALIMENTACION]]+Tabla1[[#This Row],[PRESTAMO]]+Tabla1[[#This Row],[PASAJES]] -> #REF!
A30: =TEXT(Tabla1[[#This Row],[FECHA ]],"DDDDD") -> viernes | B30: =_xlfn.IFNA(VLOOKUP(Tabla1[[#This Row],[DESTINO]],RUBRO!$Q$1:$R$9996,2,FALSE)," ") -> OBRA | C30: =WEEKNUM(Tabla1[[#This Row],[FECHA ]],2) -> 19 | D30: =TEXT(Tabla1[[#This Row],[FECHA ]],"MMM-YY") -> may-YY | E30: =VLOOKUP(Tabla1[[#This Row],[DNI ]],RUBRO!$F$1:$O$9996,7,FALSE) -> 5ta | F30: =VLOOKUP(Tabla1[[#This Row],[DNI ]],RUBRO!$F$1:$O$88,3,FALSE) -> AYU-VA | G30: =VLOOKUP(Tabla1[[#This Row],[DNI ]],RUBRO!$F$1:$O$9996,5,FALSE) -> AYUDANTE DE PRODUCCION | H30: =VLOOKUP(Tabla1[[#This Row],[DNI ]],RUBRO!$F$1:$O$9996,6,FALSE) -> LOPEZ TANTARICO ELY | I30: 44323 | J30: 2 | K30: 62188868 | L30: =VLOOKUP(Tabla1[[#This Row],[DNI ]],RUBRO!$F$2:$O$9996,8,FALSE) -> 39.15 | M30: 0.29166667 | N30: 0.54166667 | O30: 0.58333333 | P30: 0.75 | Q30: =(Tabla1[[#This Row],[SALIDA]]-Tabla1[[#This Row],[FIN ]])+(Tabla1[[#This Row],[INICIO]]-Tabla1[[#This Row],[INGRESO]]) -> 0.41666667 | R30: =IF(J30=1,IF(Q30>$AU$1,$AU$1,Q30),0)+IF(J30=2,IF(Q30>$AU$3,$AU$3,Q30),0)+IF(J30=8,IF(Q30>$AU$5,$AU$5,Q30),0) -> 0.33333333 | S30: =IF(J30=1,IF(Q30>$AU$1,(Q30-R30),0),0)+IF(J30=2,IF(Q30>$AU$3,(Q30-R30),0),0)+IF(J30=8,IF(Q30>$AU$5,(Q30-R30),0),0) -> 0.083333333 | V30: =(Tabla1[[#This Row],[COS.BASE 3]]*0.25+Tabla1[[#This Row],[COS.BASE 3]])*Tabla1[[#This Row],[HORAS 25 % ]] -> 0 | W30: =(Tabla1[[#This Row],[COS.BASE 3]]*0.35+Tabla1[[#This Row],[COS.BASE 3]])*Tabla1[[#This Row],[HORAS 35% ]] -> 0 | X30: =SUM(Tabla1[[#This Row],[C.HORA.35]],Tabla1[[#This Row],[C.HORA.25]]) -> 0 | Z30: =Tabla1[[#This Row],[T.HORAS]]*24 -> 10 | AA30: =Tabla1[[#This Row],[H.NORMALES]]*24 -> 8 | AB30: =Tabla1[[#This Row],[H.EXTRAS]]*24 -> 2 | AC30: =IF(J30=1,(((R30*24)*(L30/9))),0)+IF(J30=2,(((R30*24)*(L30/8))),0)+IF(J30=8,(((R30*24)*(L30/8))),0) -> 39.15 | AD30: =Tabla1[[#This Row],[COS.BASE 2]]/8 -> 4.89375 | AE30: =Tabla1[[#This Row],[CST_H_E]]+Tabla1[[#This Row],[COS.BASE 2]] -> 39.15 | AF30: =+_xlfn.IFNA(INDEX(RUBRO!$W$2:$AA$732,MATCH(Tabla1[[#This Row],[FECHA ]],RUBRO!$W$2:$W$732,0),5)," ") -> 0 | AG30: =+_xlfn.IFNA(INDEX(RUBRO!$W$2:$AA$732,MATCH(Tabla1[[#This Row],[FECHA ]],RUBRO!$W$2:$W$732,0),2)," ") -> 0 | AH30: =IFERROR(Tabla1[[#This Row],[F]]*Tabla1[[#This Row],[COS.B+E]]," ") -> 0 | AI30: =IFERROR(Tabla1[[#This Row],[COS.B+E]]*Tabla1[[#This Row],[D]]," ") -> 0 | AJ30: =IFERROR(Tabla1[[#This Row],[F]]*#REF!," ") | AK30: =IFERROR(#REF!*Tabla1[[#This Row],[D]]," ") | AO30: =+Tabla1[[#This Row],[COS.B+E]]+Tabla1[[#This Row],[COS.F1]]+Tabla1[[#This Row],[COS.D1]]+Tabla1[[#This Row],[ALIMENTACION]]+Tabla1[[#This Row],[PRESTAMO]]+AN30 -> 39.15 | AP30: =+#REF!+Tabla1[[#This Row],[COS F2]]+Tabla1[[#This Row],[COS D2]]+Tabla1[[#This Row],[ALIMENTACION]]+Tabla1[[#This Row],[PRESTAMO]]+Tabla1[[#This Row],[PASAJES]] -> #REF!
A31: =TEXT(Tabla1[[#This Row],[FECHA ]],"DDDDD") -> viernes | B31: =_xlfn.IFNA(VLOOKUP(Tabla1[[#This Row],[DESTINO]],RUBRO!$Q$1:$R$9996,2,FALSE)," ") -> OBRA | C31: =WEEKNUM(Tabla1[[#This Row],[FECHA ]],2) -> 19 | D31: =TEXT(Tabla1[[#This Row],[FECHA ]],"MMM-YY") -> may-YY | E31: =VLOOKUP(Tabla1[[#This Row],[DNI ]],RUBRO!$F$1:$O$9996,7,FALSE) -> 5ta | F31: =VLOOKUP(Tabla1[[#This Row],[DNI ]],RUBRO!$F$1:$O$88,3,FALSE) -> TEC-02 | G31: =VLOOKUP(Tabla1[[#This Row],[DNI ]],RUBRO!$F$1:$O$9996,5,FALSE) -> TECNICO MECANICO MONTAJISTA DE MAQUINARIA | H31: =VLOOKUP(Tabla1[[#This Row],[DNI ]],RUBRO!$F$1:$O$9996,6,FALSE) -> MEJIA AYALA LUIS MANUEL | I31: 44323 | J31: 2 | K31: 73541627 | L31: =VLOOKUP(Tabla1[[#This Row],[DNI ]],RUBRO!$F$2:$O$9996,8,FALSE) -> 55 | M31: 0.29166667 | N31: 0.54166667 | O31: 0.58333333 | P31: 0.75 | Q31: =(Tabla1[[#This Row],[SALIDA]]-Tabla1[[#This Row],[FIN ]])+(Tabla1[[#This Row],[INICIO]]-Tabla1[[#This Row],[INGRESO]]) -> 0.41666667 | R31: =IF(J31=1,IF(Q31>$AU$1,$AU$1,Q31),0)+IF(J31=2,IF(Q31>$AU$3,$AU$3,Q31),0)+IF(J31=8,IF(Q31>$AU$5,$AU$5,Q31),0) -> 0.33333333 | S31: =IF(J31=1,IF(Q31>$AU$1,(Q31-R31),0),0)+IF(J31=2,IF(Q31>$AU$3,(Q31-R31),0),0)+IF(J31=8,IF(Q31>$AU$5,(Q31-R31),0),0) -> 0.083333333 | V31: =(Tabla1[[#This Row],[COS.BASE 3]]*0.25+Tabla1[[#This Row],[COS.BASE 3]])*Tabla1[[#This Row],[HORAS 25 % ]] -> 0 | W31: =(Tabla1[[#This Row],[COS.BASE 3]]*0.35+Tabla1[[#This Row],[COS.BASE 3]])*Tabla1[[#This Row],[HORAS 35% ]] -> 0 | X31: =SUM(Tabla1[[#This Row],[C.HORA.35]],Tabla1[[#This Row],[C.HORA.25]]) -> 0 | Z31: =Tabla1[[#This Row],[T.HORAS]]*24 -> 10 | AA31: =Tabla1[[#This Row],[H.NORMALES]]*24 -> 8 | AB31: =Tabla1[[#This Row],[H.EXTRAS]]*24 -> 2 | AC31: =IF(J31=1,(((R31*24)*(L31/9))),0)+IF(J31=2,(((R31*24)*(L31/8))),0)+IF(J31=8,(((R31*24)*(L31/8))),0) -> 55 | AD31: =Tabla1[[#This Row],[COS.BASE 2]]/8 -> 6.875 | AE31: =Tabla1[[#This Row],[CST_H_E]]+Tabla1[[#This Row],[COS.BASE 2]] -> 55 | AF31: =+_xlfn.IFNA(INDEX(RUBRO!$W$2:$AA$732,MATCH(Tabla1[[#This Row],[FECHA ]],RUBRO!$W$2:$W$732,0),5)," ") -> 0 | AG31: =+_xlfn.IFNA(INDEX(RUBRO!$W$2:$AA$732,MATCH(Tabla1[[#This Row],[FECHA ]],RUBRO!$W$2:$W$732,0),2)," ") -> 0 | AH31: =IFERROR(Tabla1[[#This Row],[F]]*Tabla1[[#This Row],[COS.B+E]]," ") -> 0 | AI31: =IFERROR(Tabla1[[#This Row],[COS.B+E]]*Tabla1[[#This Row],[D]]," ") -> 0 | AJ31: =IFERROR(Tabla1[[#This Row],[F]]*#REF!," ") | AK31: =IFERROR(#REF!*Tabla1[[#This Row],[D]]," ") | AO31: =+Tabla1[[#This Row],[COS.B+E]]+Tabla1[[#This Row],[COS.F1]]+Tabla1[[#This Row],[COS.D1]]+Tabla1[[#This Row],[ALIMENTACION]]+Tabla1[[#This Row],[PRESTAMO]]+AN31 -> 55 | AP31: =+#REF!+Tabla1[[#This Row],[COS F2]]+Tabla1[[#This Row],[COS D2]]+Tabla1[[#This Row],[ALIMENTACION]]+Tabla1[[#This Row],[PRESTAMO]]+Tabla1[[#This Row],[PASAJES]] -> #REF!
A32: =TEXT(Tabla1[[#This Row],[FECHA ]],"DDDDD") -> viernes | B32: =_xlfn.IFNA(VLOOKUP(Tabla1[[#This Row],[DESTINO]],RUBRO!$Q$1:$R$9996,2,FALSE)," ") -> OBRA | C32: =WEEKNUM(Tabla1[[#This Row],[FECHA ]],2) -> 19 | D32: =TEXT(Tabla1[[#This Row],[FECHA ]],"MMM-YY") -> may-YY | E32: =VLOOKUP(Tabla1[[#This Row],[DNI ]],RUBRO!$F$1:$O$9996,7,FALSE) -> 5ta | F32: =VLOOKUP(Tabla1[[#This Row],[DNI ]],RUBRO!$F$1:$O$88,3,FALSE) -> TEC-04 | G32: =VLOOKUP(Tabla1[[#This Row],[DNI ]],RUBRO!$F$1:$O$9996,5,FALSE) -> TECNICO MECANICO MONTAJISTA DE MAQUINARIA EXTRANJERA | H32: =VLOOKUP(Tabla1[[#This Row],[DNI ]],RUBRO!$F$1:$O$9996,6,FALSE) -> MEREGILDO CABRERA RICARDO JOEL | I32: 44323 | J32: 2 | K32: 76811302 | L32: =VLOOKUP(Tabla1[[#This Row],[DNI ]],RUBRO!$F$2:$O$9996,8,FALSE) -> 60 | M32: 0.29166667 | N32: 0.54166667 | O32: 0.58333333 | P32: 0.75 | Q32: =(Tabla1[[#This Row],[SALIDA]]-Tabla1[[#This Row],[FIN ]])+(Tabla1[[#This Row],[INICIO]]-Tabla1[[#This Row],[INGRESO]]) -> 0.41666667 | R32: =IF(J32=1,IF(Q32>$AU$1,$AU$1,Q32),0)+IF(J32=2,IF(Q32>$AU$3,$AU$3,Q32),0)+IF(J32=8,IF(Q32>$AU$5,$AU$5,Q32),0) -> 0.33333333 | S32: =IF(J32=1,IF(Q32>$AU$1,(Q32-R32),0),0)+IF(J32=2,IF(Q32>$AU$3,(Q32-R32),0),0)+IF(J32=8,IF(Q32>$AU$5,(Q32-R32),0),0) -> 0.083333333 | V32: =(Tabla1[[#This Row],[COS.BASE 3]]*0.25+Tabla1[[#This Row],[COS.BASE 3]])*Tabla1[[#This Row],[HORAS 25 % ]] -> 0 | W32: =(Tabla1[[#This Row],[COS.BASE 3]]*0.35+Tabla1[[#This Row],[COS.BASE 3]])*Tabla1[[#This Row],[HORAS 35% ]] -> 0 | X32: =SUM(Tabla1[[#This Row],[C.HORA.35]],Tabla1[[#This Row],[C.HORA.25]]) -> 0 | Z32: =Tabla1[[#This Row],[T.HORAS]]*24 -> 10 | AA32: =Tabla1[[#This Row],[H.NORMALES]]*24 -> 8 | AB32: =Tabla1[[#This Row],[H.EXTRAS]]*24 -> 2 | AC32: =IF(J32=1,(((R32*24)*(L32/9))),0)+IF(J32=2,(((R32*24)*(L32/8))),0)+IF(J32=8,(((R32*24)*(L32/8))),0) -> 60 | AD32: =Tabla1[[#This Row],[COS.BASE 2]]/8 -> 7.5 | AE32: =Tabla1[[#This Row],[CST_H_E]]+Tabla1[[#This Row],[COS.BASE 2]] -> 60 | AF32: =+_xlfn.IFNA(INDEX(RUBRO!$W$2:$AA$732,MATCH(Tabla1[[#This Row],[FECHA ]],RUBRO!$W$2:$W$732,0),5)," ") -> 0 | AG32: =+_xlfn.IFNA(INDEX(RUBRO!$W$2:$AA$732,MATCH(Tabla1[[#This Row],[FECHA ]],RUBRO!$W$2:$W$732,0),2)," ") -> 0 | AH32: =IFERROR(Tabla1[[#This Row],[F]]*Tabla1[[#This Row],[COS.B+E]]," ") -> 0 | AI32: =IFERROR(Tabla1[[#This Row],[COS.B+E]]*Tabla1[[#This Row],[D]]," ") -> 0 | AJ32: =IFERROR(Tabla1[[#This Row],[F]]*#REF!," ") | AK32: =IFERROR(#REF!*Tabla1[[#This Row],[D]]," ") | AO32: =+Tabla1[[#This Row],[COS.B+E]]+Tabla1[[#This Row],[COS.F1]]+Tabla1[[#This Row],[COS.D1]]+Tabla1[[#This Row],[ALIMENTACION]]+Tabla1[[#This Row],[PRESTAMO]]+AN32 -> 60 | AP32: =+#REF!+Tabla1[[#This Row],[COS F2]]+Tabla1[[#This Row],[COS D2]]+Tabla1[[#This Row],[ALIMENTACION]]+Tabla1[[#This Row],[PRESTAMO]]+Tabla1[[#This Row],[PASAJES]] -> #REF!
A33: =TEXT(Tabla1[[#This Row],[FECHA ]],"DDDDD") -> viernes | B33: =_xlfn.IFNA(VLOOKUP(Tabla1[[#This Row],[DESTINO]],RUBRO!$Q$1:$R$9996,2,FALSE)," ") -> OBRA | C33: =WEEKNUM(Tabla1[[#This Row],[FECHA ]],2) -> 19 | D33: =TEXT(Tabla1[[#This Row],[FECHA ]],"MMM-YY") -> may-YY | E33: =VLOOKUP(Tabla1[[#This Row],[DNI ]],RUBRO!$F$1:$O$9996,7,FALSE) -> 5ta | F33: =VLOOKUP(Tabla1[[#This Row],[DNI ]],RUBRO!$F$1:$O$88,3,FALSE) -> AYU-VA | G33: =VLOOKUP(Tabla1[[#This Row],[DNI ]],RUBRO!$F$1:$O$9996,5,FALSE) -> AYUDANTE DE PRODUCCION | H33: =VLOOKUP(Tabla1[[#This Row],[DNI ]],RUBRO!$F$1:$O$9996,6,FALSE) -> MIO QUIÑONES ALEXIS | I33: 44323 | J33: 2 | K33: 76457697 | L33: =VLOOKUP(Tabla1[[#This Row],[DNI ]],RUBRO!$F$2:$O$9996,8,FALSE) -> 45 | M33: 0.29166667 | N33: 0.54166667 | O33: 0.58333333 | P33: 0.75 | Q33: =(Tabla1[[#This Row],[SALIDA]]-Tabla1[[#This Row],[FIN ]])+(Tabla1[[#This Row],[INICIO]]-Tabla1[[#This Row],[INGRESO]]) -> 0.41666667 | R33: =IF(J33=1,IF(Q33>$AU$1,$AU$1,Q33),0)+IF(J33=2,IF(Q33>$AU$3,$AU$3,Q33),0)+IF(J33=8,IF(Q33>$AU$5,$AU$5,Q33),0) -> 0.33333333 | S33: =IF(J33=1,IF(Q33>$AU$1,(Q33-R33),0),0)+IF(J33=2,IF(Q33>$AU$3,(Q33-R33),0),0)+IF(J33=8,IF(Q33>$AU$5,(Q33-R33),0),0) -> 0.083333333 | V33: =(Tabla1[[#This Row],[COS.BASE 3]]*0.25+Tabla1[[#This Row],[COS.BASE 3]])*Tabla1[[#This Row],[HORAS 25 % ]] -> 0 | W33: =(Tabla1[[#This Row],[COS.BASE 3]]*0.35+Tabla1[[#This Row],[COS.BASE 3]])*Tabla1[[#This Row],[HORAS 35% ]] -> 0 | X33: =SUM(Tabla1[[#This Row],[C.HORA.35]],Tabla1[[#This Row],[C.HORA.25]]) -> 0 | Z33: =Tabla1[[#This Row],[T.HORAS]]*24 -> 10 | AA33: =Tabla1[[#This Row],[H.NORMALES]]*24 -> 8 | AB33: =Tabla1[[#This Row],[H.EXTRAS]]*24 -> 2 | AC33: =IF(J33=1,(((R33*24)*(L33/9))),0)+IF(J33=2,(((R33*24)*(L33/8))),0)+IF(J33=8,(((R33*24)*(L33/8))),0) -> 45 | AD33: =Tabla1[[#This Row],[COS.BASE 2]]/8 -> 5.625 | AE33: =Tabla1[[#This Row],[CST_H_E]]+Tabla1[[#This Row],[COS.BASE 2]] -> 45 | AF33: =+_xlfn.IFNA(INDEX(RUBRO!$W$2:$AA$732,MATCH(Tabla1[[#This Row],[FECHA ]],RUBRO!$W$2:$W$732,0),5)," ") -> 0 | AG33: =+_xlfn.IFNA(INDEX(RUBRO!$W$2:$AA$732,MATCH(Tabla1[[#This Row],[FECHA ]],RUBRO!$W$2:$W$732,0),2)," ") -> 0 | AH33: =IFERROR(Tabla1[[#This Row],[F]]*Tabla1[[#This Row],[COS.B+E]]," ") -> 0 | AI33: =IFERROR(Tabla1[[#This Row],[COS.B+E]]*Tabla1[[#This Row],[D]]," ") -> 0 | AJ33: =IFERROR(Tabla1[[#This Row],[F]]*#REF!," ") | AK33: =IFERROR(#REF!*Tabla1[[#This Row],[D]]," ") | AO33: =+Tabla1[[#This Row],[COS.B+E]]+Tabla1[[#This Row],[COS.F1]]+Tabla1[[#This Row],[COS.D1]]+Tabla1[[#This Row],[ALIMENTACION]]+Tabla1[[#This Row],[PRESTAMO]]+AN33 -> 45 | AP33: =+#REF!+Tabla1[[#This Row],[COS F2]]+Tabla1[[#This Row],[COS D2]]+Tabla1[[#This Row],[ALIMENTACION]]+Tabla1[[#This Row],[PRESTAMO]]+Tabla1[[#This Row],[PASAJES]] -> #REF!
A34: =TEXT(Tabla1[[#This Row],[FECHA ]],"DDDDD") -> viernes | B34: =_xlfn.IFNA(VLOOKUP(Tabla1[[#This Row],[DESTINO]],RUBRO!$Q$1:$R$9996,2,FALSE)," ") -> OBRA | C34: =WEEKNUM(Tabla1[[#This Row],[FECHA ]],2) -> 19 | D34: =TEXT(Tabla1[[#This Row],[FECHA ]],"MMM-YY") -> may-YY | E34: =VLOOKUP(Tabla1[[#This Row],[DNI ]],RUBRO!$F$1:$O$9996,7,FALSE) -> 0 | F34: =VLOOKUP(Tabla1[[#This Row],[DNI ]],RUBRO!$F$1:$O$88,3,FALSE) -> #N/A | G34: =VLOOKUP(Tabla1[[#This Row],[DNI ]],RUBRO!$F$1:$O$9996,5,FALSE) -> 0 | H34: =VLOOKUP(Tabla1[[#This Row],[DNI ]],RUBRO!$F$1:$O$9996,6,FALSE) -> MONJA ACOSTA RONALD | I34: 44323 | J34: 2 | K34: 75561146 | L34: =VLOOKUP(Tabla1[[#This Row],[DNI ]],RUBRO!$F$2:$O$9996,8,FALSE) -> 0 | M34: 0.29166667 | N34: 0.54166667 | O34: 0.58333333 | P34: 0.75 | Q34: =(Tabla1[[#This Row],[SALIDA]]-Tabla1[[#This Row],[FIN ]])+(Tabla1[[#This Row],[INICIO]]-Tabla1[[#This Row],[INGRESO]]) -> 0.41666667 | R34: =IF(J34=1,IF(Q34>$AU$1,$AU$1,Q34),0)+IF(J34=2,IF(Q34>$AU$3,$AU$3,Q34),0)+IF(J34=8,IF(Q34>$AU$5,$AU$5,Q34),0) -> 0.33333333 | S34: =IF(J34=1,IF(Q34>$AU$1,(Q34-R34),0),0)+IF(J34=2,IF(Q34>$AU$3,(Q34-R34),0),0)+IF(J34=8,IF(Q34>$AU$5,(Q34-R34),0),0) -> 0.083333333 | V34: =(Tabla1[[#This Row],[COS.BASE 3]]*0.25+Tabla1[[#This Row],[COS.BASE 3]])*Tabla1[[#This Row],[HORAS 25 % ]] -> 0 | W34: =(Tabla1[[#This Row],[COS.BASE 3]]*0.35+Tabla1[[#This Row],[COS.BASE 3]])*Tabla1[[#This Row],[HORAS 35% ]] -> 0 | X34: =SUM(Tabla1[[#This Row],[C.HORA.35]],Tabla1[[#This Row],[C.HORA.25]]) -> 0 | Z34: =Tabla1[[#This Row],[T.HORAS]]*24 -> 10 | AA34: =Tabla1[[#This Row],[H.NORMALES]]*24 -> 8 | AB34: =Tabla1[[#This Row],[H.EXTRAS]]*24 -> 2 | AC34: =IF(J34=1,(((R34*24)*(L34/9))),0)+IF(J34=2,(((R34*24)*(L34/8))),0)+IF(J34=8,(((R34*24)*(L34/8))),0) -> 0 | AD34: =Tabla1[[#This Row],[COS.BASE 2]]/8 -> 0 | AE34: =Tabla1[[#This Row],[CST_H_E]]+Tabla1[[#This Row],[COS.BASE 2]] -> 0 | AF34: =+_xlfn.IFNA(INDEX(RUBRO!$W$2:$AA$732,MATCH(Tabla1[[#This Row],[FECHA ]],RUBRO!$W$2:$W$732,0),5)," ") -> 0 | AG34: =+_xlfn.IFNA(INDEX(RUBRO!$W$2:$AA$732,MATCH(Tabla1[[#This Row],[FECHA ]],RUBRO!$W$2:$W$732,0),2)," ") -> 0 | AH34: =IFERROR(Tabla1[[#This Row],[F]]*Tabla1[[#This Row],[COS.B+E]]," ") -> 0 | AI34: =IFERROR(Tabla1[[#This Row],[COS.B+E]]*Tabla1[[#This Row],[D]]," ") -> 0 | AJ34: =IFERROR(Tabla1[[#This Row],[F]]*#REF!," ") | AK34: =IFERROR(#REF!*Tabla1[[#This Row],[D]]," ") | AO34: =+Tabla1[[#This Row],[COS.B+E]]+Tabla1[[#This Row],[COS.F1]]+Tabla1[[#This Row],[COS.D1]]+Tabla1[[#This Row],[ALIMENTACION]]+Tabla1[[#This Row],[PRESTAMO]]+AN34 -> 0 | AP34: =+#REF!+Tabla1[[#This Row],[COS F2]]+Tabla1[[#This Row],[COS D2]]+Tabla1[[#This Row],[ALIMENTACION]]+Tabla1[[#This Row],[PRESTAMO]]+Tabla1[[#This Row],[PASAJES]] -> #REF!
A35: =TEXT(Tabla1[[#This Row],[FECHA ]],"DDDDD") -> viernes | B35: =_xlfn.IFNA(VLOOKUP(Tabla1[[#This Row],[DESTINO]],RUBRO!$Q$1:$R$9996,2,FALSE)," ") -> PLANTA | C35: =WEEKNUM(Tabla1[[#This Row],[FECHA ]],2) -> 19 | D35: =TEXT(Tabla1[[#This Row],[FECHA ]],"MMM-YY") -> may-YY | E35: =VLOOKUP(Tabla1[[#This Row],[DNI ]],RUBRO!$F$1:$O$9996,7,FALSE) -> 0 | F35: =VLOOKUP(Tabla1[[#This Row],[DNI ]],RUBRO!$F$1:$O$88,3,FALSE) -> #N/A | G35: =VLOOKUP(Tabla1[[#This Row],[DNI ]],RUBRO!$F$1:$O$9996,5,FALSE) -> 0 | H35: =VLOOKUP(Tabla1[[#This Row],[DNI ]],RUBRO!$F$1:$O$9996,6,FALSE) -> MONTENEGRO DAVILA EVER | I35: 44323 | J35: 1 | K35: 76847602 | L35: =VLOOKUP(Tabla1[[#This Row],[DNI ]],RUBRO!$F$2:$O$9996,8,FALSE) -> 0 | M35: 0.29166667 | N35: 0.54166667 | O35: 0.58333333 | P35: 0.79166667 | Q35: =(Tabla1[[#This Row],[SALIDA]]-Tabla1[[#This Row],[FIN ]])+(Tabla1[[#This Row],[INICIO]]-Tabla1[[#This Row],[INGRESO]]) -> 0.45833333 | R35: =IF(J35=1,IF(Q35>$AU$1,$AU$1,Q35),0)+IF(J35=2,IF(Q35>$AU$3,$AU$3,Q35),0)+IF(J35=8,IF(Q35>$AU$5,$AU$5,Q35),0) -> 0.375 | S35: =IF(J35=1,IF(Q35>$AU$1,(Q35-R35),0),0)+IF(J35=2,IF(Q35>$AU$3,(Q35-R35),0),0)+IF(J35=8,IF(Q35>$AU$5,(Q35-R35),0),0) -> 0.083333333 | V35: =(Tabla1[[#This Row],[COS.BASE 3]]*0.25+Tabla1[[#This Row],[COS.BASE 3]])*Tabla1[[#This Row],[HORAS 25 % ]] -> 0 | W35: =(Tabla1[[#This Row],[COS.BASE 3]]*0.35+Tabla1[[#This Row],[COS.BASE 3]])*Tabla1[[#This Row],[HORAS 35% ]] -> 0 | X35: =SUM(Tabla1[[#This Row],[C.HORA.35]],Tabla1[[#This Row],[C.HORA.25]]) -> 0 | Z35: =Tabla1[[#This Row],[T.HORAS]]*24 -> 11 | AA35: =Tabla1[[#This Row],[H.NORMALES]]*24 -> 9 | AB35: =Tabla1[[#This Row],[H.EXTRAS]]*24 -> 2 | AC35: =IF(J35=1,(((R35*24)*(L35/9))),0)+IF(J35=2,(((R35*24)*(L35/8))),0)+IF(J35=8,(((R35*24)*(L35/8))),0) -> 0 | AD35: =Tabla1[[#This Row],[COS.BASE 2]]/8 -> 0 | AE35: =Tabla1[[#This Row],[CST_H_E]]+Tabla1[[#This Row],[COS.BASE 2]] -> 0 | AF35: =+_xlfn.IFNA(INDEX(RUBRO!$W$2:$AA$732,MATCH(Tabla1[[#This Row],[FECHA ]],RUBRO!$W$2:$W$732,0),5)," ") -> 0 | AG35: =+_xlfn.IFNA(INDEX(RUBRO!$W$2:$AA$732,MATCH(Tabla1[[#This Row],[FECHA ]],RUBRO!$W$2:$W$732,0),2)," ") -> 0 | AH35: =IFERROR(Tabla1[[#This Row],[F]]*Tabla1[[#This Row],[COS.B+E]]," ") -> 0 | AI35: =IFERROR(Tabla1[[#This Row],[COS.B+E]]*Tabla1[[#This Row],[D]]," ") -> 0 | AJ35: =IFERROR(Tabla1[[#This Row],[F]]*#REF!," ") | AK35: =IFERROR(#REF!*Tabla1[[#This Row],[D]]," ") | AO35: =+Tabla1[[#This Row],[COS.B+E]]+Tabla1[[#This Row],[COS.F1]]+Tabla1[[#This Row],[COS.D1]]+Tabla1[[#This Row],[ALIMENTACION]]+Tabla1[[#This Row],[PRESTAMO]]+AN35 -> 0 | AP35: =+#REF!+Tabla1[[#This Row],[COS F2]]+Tabla1[[#This Row],[COS D2]]+Tabla1[[#This Row],[ALIMENTACION]]+Tabla1[[#This Row],[PRESTAMO]]+Tabla1[[#This Row],[PASAJES]] -> #REF!
A36: =TEXT(Tabla1[[#This Row],[FECHA ]],"DDDDD") -> viernes | B36: =_xlfn.IFNA(VLOOKUP(Tabla1[[#This Row],[DESTINO]],RUBRO!$Q$1:$R$9996,2,FALSE)," ") -> FALTA | C36: =WEEKNUM(Tabla1[[#This Row],[FECHA ]],2) -> 19 | D36: =TEXT(Tabla1[[#This Row],[FECHA ]],"MMM-YY") -> may-YY | E36: =VLOOKUP(Tabla1[[#This Row],[DNI ]],RUBRO!$F$1:$O$9996,7,FALSE) -> 5ta | F36: =VLOOKUP(Tabla1[[#This Row],[DNI ]],RUBRO!$F$1:$O$88,3,FALSE) -> TEC-01 | G36: =VLOOKUP(Tabla1[[#This Row],[DNI ]],RUBRO!$F$1:$O$9996,5,FALSE) -> TECNICO SOLDADOR | H36: =VLOOKUP(Tabla1[[#This Row],[DNI ]],RUBRO!$F$1:$O$9996,6,FALSE) -> MUÑOZ EXEBIO IRWIS MANUEL | I36: 44323 | J36: 4 | K36: 46933574 | L36: =VLOOKUP(Tabla1[[#This Row],[DNI ]],RUBRO!$F$2:$O$9996,8,FALSE) -> 65 | Q36: =(Tabla1[[#This Row],[SALIDA]]-Tabla1[[#This Row],[FIN ]])+(Tabla1[[#This Row],[INICIO]]-Tabla1[[#This Row],[INGRESO]]) -> 0 | R36: =IF(J36=1,IF(Q36>$AU$1,$AU$1,Q36),0)+IF(J36=2,IF(Q36>$AU$3,$AU$3,Q36),0)+IF(J36=8,IF(Q36>$AU$5,$AU$5,Q36),0) -> 0 | S36: =IF(J36=1,IF(Q36>$AU$1,(Q36-R36),0),0)+IF(J36=2,IF(Q36>$AU$3,(Q36-R36),0),0)+IF(J36=8,IF(Q36>$AU$5,(Q36-R36),0),0) -> 0 | V36: =(Tabla1[[#This Row],[COS.BASE 3]]*0.25+Tabla1[[#This Row],[COS.BASE 3]])*Tabla1[[#This Row],[HORAS 25 % ]] -> 0 | W36: =(Tabla1[[#This Row],[COS.BASE 3]]*0.35+Tabla1[[#This Row],[COS.BASE 3]])*Tabla1[[#This Row],[HORAS 35% ]] -> 0 | X36: =SUM(Tabla1[[#This Row],[C.HORA.35]],Tabla1[[#This Row],[C.HORA.25]]) -> 0 | Z36: =Tabla1[[#This Row],[T.HORAS]]*24 -> 0 | AA36: =Tabla1[[#This Row],[H.NORMALES]]*24 -> 0 | AB36: =Tabla1[[#This Row],[H.EXTRAS]]*24 -> 0 | AC36: =IF(J36=1,(((R36*24)*(L36/9))),0)+IF(J36=2,(((R36*24)*(L36/8))),0)+IF(J36=8,(((R36*24)*(L36/8))),0) -> 0 | AD36: =Tabla1[[#This Row],[COS.BASE 2]]/8 -> 0 | AE36: =Tabla1[[#This Row],[CST_H_E]]+Tabla1[[#This Row],[COS.BASE 2]] -> 0 | AF36: =+_xlfn.IFNA(INDEX(RUBRO!$W$2:$AA$732,MATCH(Tabla1[[#This Row],[FECHA ]],RUBRO!$W$2:$W$732,0),5)," ") -> 0 | AG36: =+_xlfn.IFNA(INDEX(RUBRO!$W$2:$AA$732,MATCH(Tabla1[[#This Row],[FECHA ]],RUBRO!$W$2:$W$732,0),2)," ") -> 0 | AH36: =IFERROR(Tabla1[[#This Row],[F]]*Tabla1[[#This Row],[COS.B+E]]," ") -> 0 | AI36: =IFERROR(Tabla1[[#This Row],[COS.B+E]]*Tabla1[[#This Row],[D]]," ") -> 0 | AJ36: =IFERROR(Tabla1[[#This Row],[F]]*#REF!," ") | AK36: =IFERROR(#REF!*Tabla1[[#This Row],[D]]," ") | AO36: =+Tabla1[[#This Row],[COS.B+E]]+Tabla1[[#This Row],[COS.F1]]+Tabla1[[#This Row],[COS.D1]]+Tabla1[[#This Row],[ALIMENTACION]]+Tabla1[[#This Row],[PRESTAMO]]+AN36 -> 0 | AP36: =+#REF!+Tabla1[[#This Row],[COS F2]]+Tabla1[[#This Row],[COS D2]]+Tabla1[[#This Row],[ALIMENTACION]]+Tabla1[[#This Row],[PRESTAMO]]+Tabla1[[#This Row],[PASAJES]] -> #REF!
A37: =TEXT(Tabla1[[#This Row],[FECHA ]],"DDDDD") -> viernes | B37: =_xlfn.IFNA(VLOOKUP(Tabla1[[#This Row],[DESTINO]],RUBRO!$Q$1:$R$9996,2,FALSE)," ") -> PLANTA | C37: =WEEKNUM(Tabla1[[#This Row],[FECHA ]],2) -> 19 | D37: =TEXT(Tabla1[[#This Row],[FECHA ]],"MMM-YY") -> may-YY | E37: =VLOOKUP(Tabla1[[#This Row],[DNI ]],RUBRO!$F$1:$O$9996,7,FALSE) -> 5ta | F37: =VLOOKUP(Tabla1[[#This Row],[DNI ]],RUBRO!$F$1:$O$88,3,FALSE) -> #N/A | G37: =VLOOKUP(Tabla1[[#This Row],[DNI ]],RUBRO!$F$1:$O$9996,5,FALSE) -> 0 | H37: =VLOOKUP(Tabla1[[#This Row],[DNI ]],RUBRO!$F$1:$O$9996,6,FALSE) -> OLANO GARCIA | I37: 44323 | J37: 1 | K37: 41234982 | L37: =VLOOKUP(Tabla1[[#This Row],[DNI ]],RUBRO!$F$2:$O$9996,8,FALSE) -> 0 | M37: 0.29166667 | N37: 0.54166667 | O37: 0.58333333 | P37: 0.70833333 | Q37: =(Tabla1[[#This Row],[SALIDA]]-Tabla1[[#This Row],[FIN ]])+(Tabla1[[#This Row],[INICIO]]-Tabla1[[#This Row],[INGRESO]]) -> 0.375 | R37: =IF(J37=1,IF(Q37>$AU$1,$AU$1,Q37),0)+IF(J37=2,IF(Q37>$AU$3,$AU$3,Q37),0)+IF(J37=8,IF(Q37>$AU$5,$AU$5,Q37),0) -> 0.375 | S37: =IF(J37=1,IF(Q37>$AU$1,(Q37-R37),0),0)+IF(J37=2,IF(Q37>$AU$3,(Q37-R37),0),0)+IF(J37=8,IF(Q37>$AU$5,(Q37-R37),0),0) -> 0 | V37: =(Tabla1[[#This Row],[COS.BASE 3]]*0.25+Tabla1[[#This Row],[COS.BASE 3]])*Tabla1[[#This Row],[HORAS 25 % ]] -> 0 | W37: =(Tabla1[[#This Row],[COS.BASE 3]]*0.35+Tabla1[[#This Row],[COS.BASE 3]])*Tabla1[[#This Row],[HORAS 35% ]] -> 0 | X37: =SUM(Tabla1[[#This Row],[C.HORA.35]],Tabla1[[#This Row],[C.HORA.25]]) -> 0 | Z37: =Tabla1[[#This Row],[T.HORAS]]*24 -> 9 | AA37: =Tabla1[[#This Row],[H.NORMALES]]*24 -> 9 | AB37: =Tabla1[[#This Row],[H.EXTRAS]]*24 -> 0 | AC37: =IF(J37=1,(((R37*24)*(L37/9))),0)+IF(J37=2,(((R37*24)*(L37/8))),0)+IF(J37=8,(((R37*24)*(L37/8))),0) -> 0 | AD37: =Tabla1[[#This Row],[COS.BASE 2]]/8 -> 0 | AE37: =Tabla1[[#This Row],[CST_H_E]]+Tabla1[[#This Row],[COS.BASE 2]] -> 0 | AF37: =+_xlfn.IFNA(INDEX(RUBRO!$W$2:$AA$732,MATCH(Tabla1[[#This Row],[FECHA ]],RUBRO!$W$2:$W$732,0),5)," ") -> 0 | AG37: =+_xlfn.IFNA(INDEX(RUBRO!$W$2:$AA$732,MATCH(Tabla1[[#This Row],[FECHA ]],RUBRO!$W$2:$W$732,0),2)," ") -> 0 | AH37: =IFERROR(Tabla1[[#This Row],[F]]*Tabla1[[#This Row],[COS.B+E]]," ") -> 0 | AI37: =IFERROR(Tabla1[[#This Row],[COS.B+E]]*Tabla1[[#This Row],[D]]," ") -> 0 | AJ37: =IFERROR(Tabla1[[#This Row],[F]]*#REF!," ") | AK37: =IFERROR(#REF!*Tabla1[[#This Row],[D]]," ") | AO37: =+Tabla1[[#This Row],[COS.B+E]]+Tabla1[[#This Row],[COS.F1]]+Tabla1[[#This Row],[COS.D1]]+Tabla1[[#This Row],[ALIMENTACION]]+Tabla1[[#This Row],[PRESTAMO]]+AN37 -> 0 | AP37: =+#REF!+Tabla1[[#This Row],[COS F2]]+Tabla1[[#This Row],[COS D2]]+Tabla1[[#This Row],[ALIMENTACION]]+Tabla1[[#This Row],[PRESTAMO]]+Tabla1[[#This Row],[PASAJES]] -> #REF!
A38: =TEXT(Tabla1[[#This Row],[FECHA ]],"DDDDD") -> viernes | B38: =_xlfn.IFNA(VLOOKUP(Tabla1[[#This Row],[DESTINO]],RUBRO!$Q$1:$R$9996,2,FALSE)," ") -> PLANTA | C38: =WEEKNUM(Tabla1[[#This Row],[FECHA ]],2) -> 19 | D38: =TEXT(Tabla1[[#This Row],[FECHA ]],"MMM-YY") -> may-YY | E38: =VLOOKUP(Tabla1[[#This Row],[DNI ]],RUBRO!$F$1:$O$9996,7,FALSE) -> 5ta | F38: =VLOOKUP(Tabla1[[#This Row],[DNI ]],RUBRO!$F$1:$O$88,3,FALSE) -> TEC-05 | G38: =VLOOKUP(Tabla1[[#This Row],[DNI ]],RUBRO!$F$1:$O$9996,5,FALSE) -> TECNICO MECANICO MONTAJISTA DE NAVE INDUSTRIAL | H38: =VLOOKUP(Tabla1[[#This Row],[DNI ]],RUBRO!$F$1:$O$9996,6,FALSE) -> ORTIZ PANTALEON POLH MANIX | I38: 44323 | J38: 1 | K38: 45821420 | L38: =VLOOKUP(Tabla1[[#This Row],[DNI ]],RUBRO!$F$2:$O$9996,8,FALSE) -> 56.55 | M38: 0.29166667 | N38: 0.54166667 | O38: 0.58333333 | P38: 0.70833333 | Q38: =(Tabla1[[#This Row],[SALIDA]]-Tabla1[[#This Row],[FIN ]])+(Tabla1[[#This Row],[INICIO]]-Tabla1[[#This Row],[INGRESO]]) -> 0.375 | R38: =IF(J38=1,IF(Q38>$AU$1,$AU$1,Q38),0)+IF(J38=2,IF(Q38>$AU$3,$AU$3,Q38),0)+IF(J38=8,IF(Q38>$AU$5,$AU$5,Q38),0) -> 0.375 | S38: =IF(J38=1,IF(Q38>$AU$1,(Q38-R38),0),0)+IF(J38=2,IF(Q38>$AU$3,(Q38-R38),0),0)+IF(J38=8,IF(Q38>$AU$5,(Q38-R38),0),0) -> 0 | V38: =(Tabla1[[#This Row],[COS.BASE 3]]*0.25+Tabla1[[#This Row],[COS.BASE 3]])*Tabla1[[#This Row],[HORAS 25 % ]] -> 0 | W38: =(Tabla1[[#This Row],[COS.BASE 3]]*0.35+Tabla1[[#This Row],[COS.BASE 3]])*Tabla1[[#This Row],[HORAS 35% ]] -> 0 | X38: =SUM(Tabla1[[#This Row],[C.HORA.35]],Tabla1[[#This Row],[C.HORA.25]]) -> 0 | Z38: =Tabla1[[#This Row],[T.HORAS]]*24 -> 9 | AA38: =Tabla1[[#This Row],[H.NORMALES]]*24 -> 9 | AB38: =Tabla1[[#This Row],[H.EXTRAS]]*24 -> 0 | AC38: =IF(J38=1,(((R38*24)*(L38/9))),0)+IF(J38=2,(((R38*24)*(L38/8))),0)+IF(J38=8,(((R38*24)*(L38/8))),0) -> 56.55 | AD38: =Tabla1[[#This Row],[COS.BASE 2]]/8 -> 7.06875 | AE38: =Tabla1[[#This Row],[CST_H_E]]+Tabla1[[#This Row],[COS.BASE 2]] -> 56.55 | AF38: =+_xlfn.IFNA(INDEX(RUBRO!$W$2:$AA$732,MATCH(Tabla1[[#This Row],[FECHA ]],RUBRO!$W$2:$W$732,0),5)," ") -> 0 | AG38: =+_xlfn.IFNA(INDEX(RUBRO!$W$2:$AA$732,MATCH(Tabla1[[#This Row],[FECHA ]],RUBRO!$W$2:$W$732,0),2)," ") -> 0 | AH38: =IFERROR(Tabla1[[#This Row],[F]]*Tabla1[[#This Row],[COS.B+E]]," ") -> 0 | AI38: =IFERROR(Tabla1[[#This Row],[COS.B+E]]*Tabla1[[#This Row],[D]]," ") -> 0 | AJ38: =IFERROR(Tabla1[[#This Row],[F]]*#REF!," ") | AK38: =IFERROR(#REF!*Tabla1[[#This Row],[D]]," ") | AO38: =+Tabla1[[#This Row],[COS.B+E]]+Tabla1[[#This Row],[COS.F1]]+Tabla1[[#This Row],[COS.D1]]+Tabla1[[#This Row],[ALIMENTACION]]+Tabla1[[#This Row],[PRESTAMO]]+AN38 -> 56.55 | AP38: =+#REF!+Tabla1[[#This Row],[COS F2]]+Tabla1[[#This Row],[COS D2]]+Tabla1[[#This Row],[ALIMENTACION]]+Tabla1[[#This Row],[PRESTAMO]]+Tabla1[[#This Row],[PASAJES]] -> #REF!
A39: =TEXT(Tabla1[[#This Row],[FECHA ]],"DDDDD") -> viernes | B39: =_xlfn.IFNA(VLOOKUP(Tabla1[[#This Row],[DESTINO]],RUBRO!$Q$1:$R$9996,2,FALSE)," ") -> PLANTA | C39: =WEEKNUM(Tabla1[[#This Row],[FECHA ]],2) -> 19 | D39: =TEXT(Tabla1[[#This Row],[FECHA ]],"MMM-YY") -> may-YY | E39: =VLOOKUP(Tabla1[[#This Row],[DNI ]],RUBRO!$F$1:$O$9996,7,FALSE) -> 5ta | F39: =VLOOKUP(Tabla1[[#This Row],[DNI ]],RUBRO!$F$1:$O$88,3,FALSE) -> TEC-01 | G39: =VLOOKUP(Tabla1[[#This Row],[DNI ]],RUBRO!$F$1:$O$9996,5,FALSE) -> TECNICO SOLDADOR | H39: =VLOOKUP(Tabla1[[#This Row],[DNI ]],RUBRO!$F$1:$O$9996,6,FALSE) -> PANDO SALAZAR LUIS BRYAN | I39: 44323 | J39: 1 | K39: 47887505 | L39: =VLOOKUP(Tabla1[[#This Row],[DNI ]],RUBRO!$F$2:$O$9996,8,FALSE) -> 66.48 | M39: 0.29166667 | N39: 0.54166667 | O39: 0.58333333 | P39: 0.79166667 | Q39: =(Tabla1[[#This Row],[SALIDA]]-Tabla1[[#This Row],[FIN ]])+(Tabla1[[#This Row],[INICIO]]-Tabla1[[#This Row],[INGRESO]]) -> 0.45833333 | R39: =IF(J39=1,IF(Q39>$AU$1,$AU$1,Q39),0)+IF(J39=2,IF(Q39>$AU$3,$AU$3,Q39),0)+IF(J39=8,IF(Q39>$AU$5,$AU$5,Q39),0) -> 0.375 | S39: =IF(J39=1,IF(Q39>$AU$1,(Q39-R39),0),0)+IF(J39=2,IF(Q39>$AU$3,(Q39-R39),0),0)+IF(J39=8,IF(Q39>$AU$5,(Q39-R39),0),0) -> 0.083333333 | V39: =(Tabla1[[#This Row],[COS.BASE 3]]*0.25+Tabla1[[#This Row],[COS.BASE 3]])*Tabla1[[#This Row],[HORAS 25 % ]] -> 0 | W39: =(Tabla1[[#This Row],[COS.BASE 3]]*0.35+Tabla1[[#This Row],[COS.BASE 3]])*Tabla1[[#This Row],[HORAS 35% ]] -> 0 | X39: =SUM(Tabla1[[#This Row],[C.HORA.35]],Tabla1[[#This Row],[C.HORA.25]]) -> 0 | Z39: =Tabla1[[#This Row],[T.HORAS]]*24 -> 11 | AA39: =Tabla1[[#This Row],[H.NORMALES]]*24 -> 9 | AB39: =Tabla1[[#This Row],[H.EXTRAS]]*24 -> 2 | AC39: =IF(J39=1,(((R39*24)*(L39/9))),0)+IF(J39=2,(((R39*24)*(L39/8))),0)+IF(J39=8,(((R39*24)*(L39/8))),0) -> 66.48 | AD39: =Tabla1[[#This Row],[COS.BASE 2]]/8 -> 8.31 | AE39: =Tabla1[[#This Row],[CST_H_E]]+Tabla1[[#This Row],[COS.BASE 2]] -> 66.48 | AF39: =+_xlfn.IFNA(INDEX(RUBRO!$W$2:$AA$732,MATCH(Tabla1[[#This Row],[FECHA ]],RUBRO!$W$2:$W$732,0),5)," ") -> 0 | AG39: =+_xlfn.IFNA(INDEX(RUBRO!$W$2:$AA$732,MATCH(Tabla1[[#This Row],[FECHA ]],RUBRO!$W$2:$W$732,0),2)," ") -> 0 | AH39: =IFERROR(Tabla1[[#This Row],[F]]*Tabla1[[#This Row],[COS.B+E]]," ") -> 0 | AI39: =IFERROR(Tabla1[[#This Row],[COS.B+E]]*Tabla1[[#This Row],[D]]," ") -> 0 | AJ39: =IFERROR(Tabla1[[#This Row],[F]]*#REF!," ") | AK39: =IFERROR(#REF!*Tabla1[[#This Row],[D]]," ") | AO39: =+Tabla1[[#This Row],[COS.B+E]]+Tabla1[[#This Row],[COS.F1]]+Tabla1[[#This Row],[COS.D1]]+Tabla1[[#This Row],[ALIMENTACION]]+Tabla1[[#This Row],[PRESTAMO]]+AN39 -> 66.48 | AP39: =+#REF!+Tabla1[[#This Row],[COS F2]]+Tabla1[[#This Row],[COS D2]]+Tabla1[[#This Row],[ALIMENTACION]]+Tabla1[[#This Row],[PRESTAMO]]+Tabla1[[#This Row],[PASAJES]] -> #REF!
A40: =TEXT(Tabla1[[#This Row],[FECHA ]],"DDDDD") -> viernes | B40: =_xlfn.IFNA(VLOOKUP(Tabla1[[#This Row],[DESTINO]],RUBRO!$Q$1:$R$9996,2,FALSE)," ") -> OBRA | C40: =WEEKNUM(Tabla1[[#This Row],[FECHA ]],2) -> 19 | D40: =TEXT(Tabla1[[#This Row],[FECHA ]],"MMM-YY") -> may-YY | E40: =VLOOKUP(Tabla1[[#This Row],[DNI ]],RUBRO!$F$1:$O$9996,7,FALSE) -> 5ta | F40: =VLOOKUP(Tabla1[[#This Row],[DNI ]],RUBRO!$F$1:$O$88,3,FALSE) -> #N/A | G40: =VLOOKUP(Tabla1[[#This Row],[DNI ]],RUBRO!$F$1:$O$9996,5,FALSE) -> 0 | H40: =VLOOKUP(Tabla1[[#This Row],[DNI ]],RUBRO!$F$1:$O$9996,6,FALSE) -> PECHE CHAPOÑAN ALBERTO | I40: 44323 | J40: 2 | K40: 77226886 | L40: =VLOOKUP(Tabla1[[#This Row],[DNI ]],RUBRO!$F$2:$O$9996,8,FALSE) -> 80 | M40: 0.29166667 | N40: 0.54166667 | O40: 0.58333333 | P40: 0.75 | Q40: =(Tabla1[[#This Row],[SALIDA]]-Tabla1[[#This Row],[FIN ]])+(Tabla1[[#This Row],[INICIO]]-Tabla1[[#This Row],[INGRESO]]) -> 0.41666667 | R40: =IF(J40=1,IF(Q40>$AU$1,$AU$1,Q40),0)+IF(J40=2,IF(Q40>$AU$3,$AU$3,Q40),0)+IF(J40=8,IF(Q40>$AU$5,$AU$5,Q40),0) -> 0.33333333 | S40: =IF(J40=1,IF(Q40>$AU$1,(Q40-R40),0),0)+IF(J40=2,IF(Q40>$AU$3,(Q40-R40),0),0)+IF(J40=8,IF(Q40>$AU$5,(Q40-R40),0),0) -> 0.083333333 | V40: =(Tabla1[[#This Row],[COS.BASE 3]]*0.25+Tabla1[[#This Row],[COS.BASE 3]])*Tabla1[[#This Row],[HORAS 25 % ]] -> 0 | W40: =(Tabla1[[#This Row],[COS.BASE 3]]*0.35+Tabla1[[#This Row],[COS.BASE 3]])*Tabla1[[#This Row],[HORAS 35% ]] -> 0 | X40: =SUM(Tabla1[[#This Row],[C.HORA.35]],Tabla1[[#This Row],[C.HORA.25]]) -> 0 | Z40: =Tabla1[[#This Row],[T.HORAS]]*24 -> 10 | AA40: =Tabla1[[#This Row],[H.NORMALES]]*24 -> 8 | AB40: =Tabla1[[#This Row],[H.EXTRAS]]*24 -> 2 | AC40: =IF(J40=1,(((R40*24)*(L40/9))),0)+IF(J40=2,(((R40*24)*(L40/8))),0)+IF(J40=8,(((R40*24)*(L40/8))),0) -> 80 | AD40: =Tabla1[[#This Row],[COS.BASE 2]]/8 -> 10 | AE40: =Tabla1[[#This Row],[CST_H_E]]+Tabla1[[#This Row],[COS.BASE 2]] -> 80 | AF40: =+_xlfn.IFNA(INDEX(RUBRO!$W$2:$AA$732,MATCH(Tabla1[[#This Row],[FECHA ]],RUBRO!$W$2:$W$732,0),5)," ") -> 0 | AG40: =+_xlfn.IFNA(INDEX(RUBRO!$W$2:$AA$732,MATCH(Tabla1[[#This Row],[FECHA ]],RUBRO!$W$2:$W$732,0),2)," ") -> 0 | AH40: =IFERROR(Tabla1[[#This Row],[F]]*Tabla1[[#This Row],[COS.B+E]]," ") -> 0 | AI40: =IFERROR(Tabla1[[#This Row],[COS.B+E]]*Tabla1[[#This Row],[D]]," ") -> 0 | AJ40: =IFERROR(Tabla1[[#This Row],[F]]*#REF!," ") | AK40: =IFERROR(#REF!*Tabla1[[#This Row],[D]]," ") | AO40: =+Tabla1[[#This Row],[COS.B+E]]+Tabla1[[#This Row],[COS.F1]]+Tabla1[[#This Row],[COS.D1]]+Tabla1[[#This Row],[ALIMENTACION]]+Tabla1[[#This Row],[PRESTAMO]]+AN40 -> 80 | AP40: =+#REF!+Tabla1[[#This Row],[COS F2]]+Tabla1[[#This Row],[COS D2]]+Tabla1[[#This Row],[ALIMENTACION]]+Tabla1[[#This Row],[PRESTAMO]]+Tabla1[[#This Row],[PASAJES]] -> #REF!
A41: =TEXT(Tabla1[[#This Row],[FECHA ]],"DDDDD") -> viernes | B41: =_xlfn.IFNA(VLOOKUP(Tabla1[[#This Row],[DESTINO]],RUBRO!$Q$1:$R$9996,2,FALSE)," ") | C41: =WEEKNUM(Tabla1[[#This Row],[FECHA ]],2) -> 19 | D41: =TEXT(Tabla1[[#This Row],[FECHA ]],"MMM-YY") -> may-YY | E41: =VLOOKUP(Tabla1[[#This Row],[DNI ]],RUBRO!$F$1:$O$9996,7,FALSE) -> 5ta | F41: =VLOOKUP(Tabla1[[#This Row],[DNI ]],RUBRO!$F$1:$O$88,3,FALSE) -> MEC-02 | G41: =VLOOKUP(Tabla1[[#This Row],[DNI ]],RUBRO!$F$1:$O$9996,5,FALSE) -> MECANICO MONTAJISTA DE MAQUINARIA | H41: =VLOOKUP(Tabla1[[#This Row],[DNI ]],RUBRO!$F$1:$O$9996,6,FALSE) -> PEREZ VASQUEZ RONAL | I41: 44323 | K41: 47942907 | L41: =VLOOKUP(Tabla1[[#This Row],[DNI ]],RUBRO!$F$2:$O$9996,8,FALSE) -> 75 | Q41: =(Tabla1[[#This Row],[SALIDA]]-Tabla1[[#This Row],[FIN ]])+(Tabla1[[#This Row],[INICIO]]-Tabla1[[#This Row],[INGRESO]]) -> 0 | R41: =IF(J41=1,IF(Q41>$AU$1,$AU$1,Q41),0)+IF(J41=2,IF(Q41>$AU$3,$AU$3,Q41),0)+IF(J41=8,IF(Q41>$AU$5,$AU$5,Q41),0) -> 0 | S41: =IF(J41=1,IF(Q41>$AU$1,(Q41-R41),0),0)+IF(J41=2,IF(Q41>$AU$3,(Q41-R41),0),0)+IF(J41=8,IF(Q41>$AU$5,(Q41-R41),0),0) -> 0 | V41: =(Tabla1[[#This Row],[COS.BASE 3]]*0.25+Tabla1[[#This Row],[COS.BASE 3]])*Tabla1[[#This Row],[HORAS 25 % ]] -> 0 | W41: =(Tabla1[[#This Row],[COS.BASE 3]]*0.35+Tabla1[[#This Row],[COS.BASE 3]])*Tabla1[[#This Row],[HORAS 35% ]] -> 0 | X41: =SUM(Tabla1[[#This Row],[C.HORA.35]],Tabla1[[#This Row],[C.HORA.25]]) -> 0 | Z41: =Tabla1[[#This Row],[T.HORAS]]*24 -> 0 | AA41: =Tabla1[[#This Row],[H.NORMALES]]*24 -> 0 | AB41: =Tabla1[[#This Row],[H.EXTRAS]]*24 -> 0 | AC41: =IF(J41=1,(((R41*24)*(L41/9))),0)+IF(J41=2,(((R41*24)*(L41/8))),0)+IF(J41=8,(((R41*24)*(L41/8))),0) -> 0 | AD41: =Tabla1[[#This Row],[COS.BASE 2]]/8 -> 0 | AE41: =Tabla1[[#This Row],[CST_H_E]]+Tabla1[[#This Row],[COS.BASE 2]] -> 0 | AF41: =+_xlfn.IFNA(INDEX(RUBRO!$W$2:$AA$732,MATCH(Tabla1[[#This Row],[FECHA ]],RUBRO!$W$2:$W$732,0),5)," ") -> 0 | AG41: =+_xlfn.IFNA(INDEX(RUBRO!$W$2:$AA$732,MATCH(Tabla1[[#This Row],[FECHA ]],RUBRO!$W$2:$W$732,0),2)," ") -> 0 | AH41: =IFERROR(Tabla1[[#This Row],[F]]*Tabla1[[#This Row],[COS.B+E]]," ") -> 0 | AI41: =IFERROR(Tabla1[[#This Row],[COS.B+E]]*Tabla1[[#This Row],[D]]," ") -> 0 | AJ41: =IFERROR(Tabla1[[#This Row],[F]]*#REF!," ") | AK41: =IFERROR(#REF!*Tabla1[[#This Row],[D]]," ") | AO41: =+Tabla1[[#This Row],[COS.B+E]]+Tabla1[[#This Row],[COS.F1]]+Tabla1[[#This Row],[COS.D1]]+Tabla1[[#This Row],[ALIMENTACION]]+Tabla1[[#This Row],[PRESTAMO]]+AN41 -> 0 | AP41: =+#REF!+Tabla1[[#This Row],[COS F2]]+Tabla1[[#This Row],[COS D2]]+Tabla1[[#This Row],[ALIMENTACION]]+Tabla1[[#This Row],[PRESTAMO]]+Tabla1[[#This Row],[PASAJES]] -> #REF!
A42: =TEXT(Tabla1[[#This Row],[FECHA ]],"DDDDD") -> viernes | B42: =_xlfn.IFNA(VLOOKUP(Tabla1[[#This Row],[DESTINO]],RUBRO!$Q$1:$R$9996,2,FALSE)," ") -> PLANTA | C42: =WEEKNUM(Tabla1[[#This Row],[FECHA ]],2) -> 19 | D42: =TEXT(Tabla1[[#This Row],[FECHA ]],"MMM-YY") -> may-YY | E42: =VLOOKUP(Tabla1[[#This Row],[DNI ]],RUBRO!$F$1:$O$9996,7,FALSE) -> 5ta | F42: =VLOOKUP(Tabla1[[#This Row],[DNI ]],RUBRO!$F$1:$O$88,3,FALSE) -> TEC-02 | G42: =VLOOKUP(Tabla1[[#This Row],[DNI ]],RUBRO!$F$1:$O$9996,5,FALSE) -> TECNICO MECANICO MONTAJISTA DE MAQUINARIA | H42: =VLOOKUP(Tabla1[[#This Row],[DNI ]],RUBRO!$F$1:$O$9996,6,FALSE) -> PURIZACA CHUÑE JHON ANDERSON | I42: 44323 | J42: 1 | K42: 48372384 | L42: =VLOOKUP(Tabla1[[#This Row],[DNI ]],RUBRO!$F$2:$O$9996,8,FALSE) -> 57.62 | M42: 0.29166667 | N42: 0.54166667 | O42: 0.58333333 | P42: 0.70833333 | Q42: =(Tabla1[[#This Row],[SALIDA]]-Tabla1[[#This Row],[FIN ]])+(Tabla1[[#This Row],[INICIO]]-Tabla1[[#This Row],[INGRESO]]) -> 0.375 | R42: =IF(J42=1,IF(Q42>$AU$1,$AU$1,Q42),0)+IF(J42=2,IF(Q42>$AU$3,$AU$3,Q42),0)+IF(J42=8,IF(Q42>$AU$5,$AU$5,Q42),0) -> 0.375 | S42: =IF(J42=1,IF(Q42>$AU$1,(Q42-R42),0),0)+IF(J42=2,IF(Q42>$AU$3,(Q42-R42),0),0)+IF(J42=8,IF(Q42>$AU$5,(Q42-R42),0),0) -> 0 | V42: =(Tabla1[[#This Row],[COS.BASE 3]]*0.25+Tabla1[[#This Row],[COS.BASE 3]])*Tabla1[[#This Row],[HORAS 25 % ]] -> 0 | W42: =(Tabla1[[#This Row],[COS.BASE 3]]*0.35+Tabla1[[#This Row],[COS.BASE 3]])*Tabla1[[#This Row],[HORAS 35% ]] -> 0 | X42: =SUM(Tabla1[[#This Row],[C.HORA.35]],Tabla1[[#This Row],[C.HORA.25]]) -> 0 | Z42: =Tabla1[[#This Row],[T.HORAS]]*24 -> 9 | AA42: =Tabla1[[#This Row],[H.NORMALES]]*24 -> 9 | AB42: =Tabla1[[#This Row],[H.EXTRAS]]*24 -> 0 | AC42: =IF(J42=1,(((R42*24)*(L42/9))),0)+IF(J42=2,(((R42*24)*(L42/8))),0)+IF(J42=8,(((R42*24)*(L42/8))),0) -> 57.62 | AD42: =Tabla1[[#This Row],[COS.BASE 2]]/8 -> 7.2025 | AE42: =Tabla1[[#This Row],[CST_H_E]]+Tabla1[[#This Row],[COS.BASE 2]] -> 57.62 | AF42: =+_xlfn.IFNA(INDEX(RUBRO!$W$2:$AA$732,MATCH(Tabla1[[#This Row],[FECHA ]],RUBRO!$W$2:$W$732,0),5)," ") -> 0 | AG42: =+_xlfn.IFNA(INDEX(RUBRO!$W$2:$AA$732,MATCH(Tabla1[[#This Row],[FECHA ]],RUBRO!$W$2:$W$732,0),2)," ") -> 0 | AH42: =IFERROR(Tabla1[[#This Row],[F]]*Tabla1[[#This Row],[COS.B+E]]," ") -> 0 | AI42: =IFERROR(Tabla1[[#This Row],[COS.B+E]]*Tabla1[[#This Row],[D]]," ") -> 0 | AJ42: =IFERROR(Tabla1[[#This Row],[F]]*#REF!," ") | AK42: =IFERROR(#REF!*Tabla1[[#This Row],[D]]," ") | AO42: =+Tabla1[[#This Row],[COS.B+E]]+Tabla1[[#This Row],[COS.F1]]+Tabla1[[#This Row],[COS.D1]]+Tabla1[[#This Row],[ALIMENTACION]]+Tabla1[[#This Row],[PRESTAMO]]+AN42 -> 57.62 | AP42: =+#REF!+Tabla1[[#This Row],[COS F2]]+Tabla1[[#This Row],[COS D2]]+Tabla1[[#This Row],[ALIMENTACION]]+Tabla1[[#This Row],[PRESTAMO]]+Tabla1[[#This Row],[PASAJES]] -> #REF!
A43: =TEXT(Tabla1[[#This Row],[FECHA ]],"DDDDD") -> viernes | B43: =_xlfn.IFNA(VLOOKUP(Tabla1[[#This Row],[DESTINO]],RUBRO!$Q$1:$R$9996,2,FALSE)," ") -> PLANTA | C43: =WEEKNUM(Tabla1[[#This Row],[FECHA ]],2) -> 19 | D43: =TEXT(Tabla1[[#This Row],[FECHA ]],"MMM-YY") -> may-YY | E43: =VLOOKUP(Tabla1[[#This Row],[DNI ]],RUBRO!$F$1:$O$9996,7,FALSE) -> 5ta | F43: =VLOOKUP(Tabla1[[#This Row],[DNI ]],RUBRO!$F$1:$O$88,3,FALSE) -> MAE-02 | G43: =VLOOKUP(Tabla1[[#This Row],[DNI ]],RUBRO!$F$1:$O$9996,5,FALSE) -> MAESTRO MECANICO MONTAJISTA DE MAQUINARIA | H43: =VLOOKUP(Tabla1[[#This Row],[DNI ]],RUBRO!$F$1:$O$9996,6,FALSE) -> PURIZACA SEVERINO DANIEL FERNANDO | I43: 44323 | J43: 1 | K43: 42308744 | L43: =VLOOKUP(Tabla1[[#This Row],[DNI ]],RUBRO!$F$2:$O$9996,8,FALSE) -> 87.1 | M43: 0.29166667 | N43: 0.54166667 | O43: 0.58333333 | P43: 0.70833333 | Q43: =(Tabla1[[#This Row],[SALIDA]]-Tabla1[[#This Row],[FIN ]])+(Tabla1[[#This Row],[INICIO]]-Tabla1[[#This Row],[INGRESO]]) -> 0.375 | R43: =IF(J43=1,IF(Q43>$AU$1,$AU$1,Q43),0)+IF(J43=2,IF(Q43>$AU$3,$AU$3,Q43),0)+IF(J43=8,IF(Q43>$AU$5,$AU$5,Q43),0) -> 0.375 | S43: =IF(J43=1,IF(Q43>$AU$1,(Q43-R43),0),0)+IF(J43=2,IF(Q43>$AU$3,(Q43-R43),0),0)+IF(J43=8,IF(Q43>$AU$5,(Q43-R43),0),0) -> 0 | V43: =(Tabla1[[#This Row],[COS.BASE 3]]*0.25+Tabla1[[#This Row],[COS.BASE 3]])*Tabla1[[#This Row],[HORAS 25 % ]] -> 0 | W43: =(Tabla1[[#This Row],[COS.BASE 3]]*0.35+Tabla1[[#This Row],[COS.BASE 3]])*Tabla1[[#This Row],[HORAS 35% ]] -> 0 | X43: =SUM(Tabla1[[#This Row],[C.HORA.35]],Tabla1[[#This Row],[C.HORA.25]]) -> 0 | Z43: =Tabla1[[#This Row],[T.HORAS]]*24 -> 9 | AA43: =Tabla1[[#This Row],[H.NORMALES]]*24 -> 9 | AB43: =Tabla1[[#This Row],[H.EXTRAS]]*24 -> 0 | AC43: =IF(J43=1,(((R43*24)*(L43/9))),0)+IF(J43=2,(((R43*24)*(L43/8))),0)+IF(J43=8,(((R43*24)*(L43/8))),0) -> 87.1 | AD43: =Tabla1[[#This Row],[COS.BASE 2]]/8 -> 10.8875 | AE43: =Tabla1[[#This Row],[CST_H_E]]+Tabla1[[#This Row],[COS.BASE 2]] -> 87.1 | AF43: =+_xlfn.IFNA(INDEX(RUBRO!$W$2:$AA$732,MATCH(Tabla1[[#This Row],[FECHA ]],RUBRO!$W$2:$W$732,0),5)," ") -> 0 | AG43: =+_xlfn.IFNA(INDEX(RUBRO!$W$2:$AA$732,MATCH(Tabla1[[#This Row],[FECHA ]],RUBRO!$W$2:$W$732,0),2)," ") -> 0 | AH43: =IFERROR(Tabla1[[#This Row],[F]]*Tabla1[[#This Row],[COS.B+E]]," ") -> 0 | AI43: =IFERROR(Tabla1[[#This Row],[COS.B+E]]*Tabla1[[#This Row],[D]]," ") -> 0 | AJ43: =IFERROR(Tabla1[[#This Row],[F]]*#REF!," ") | AK43: =IFERROR(#REF!*Tabla1[[#This Row],[D]]," ") | AO43: =+Tabla1[[#This Row],[COS.B+E]]+Tabla1[[#This Row],[COS.F1]]+Tabla1[[#This Row],[COS.D1]]+Tabla1[[#This Row],[ALIMENTACION]]+Tabla1[[#This Row],[PRESTAMO]]+AN43 -> 87.1 | AP43: =+#REF!+Tabla1[[#This Row],[COS F2]]+Tabla1[[#This Row],[COS D2]]+Tabla1[[#This Row],[ALIMENTACION]]+Tabla1[[#This Row],[PRESTAMO]]+Tabla1[[#This Row],[PASAJES]] -> #REF!
A44: =TEXT(Tabla1[[#This Row],[FECHA ]],"DDDDD") -> viernes | B44: =_xlfn.IFNA(VLOOKUP(Tabla1[[#This Row],[DESTINO]],RUBRO!$Q$1:$R$9996,2,FALSE)," ") -> OBRA | C44: =WEEKNUM(Tabla1[[#This Row],[FECHA ]],2) -> 19 | D44: =TEXT(Tabla1[[#This Row],[FECHA ]],"MMM-YY") -> may-YY | E44: =VLOOKUP(Tabla1[[#This Row],[DNI ]],RUBRO!$F$1:$O$9996,7,FALSE) -> 4ta | F44: =VLOOKUP(Tabla1[[#This Row],[DNI ]],RUBRO!$F$1:$O$88,3,FALSE) -> MAE3G-01 | G44: =VLOOKUP(Tabla1[[#This Row],[DNI ]],RUBRO!$F$1:$O$9996,5,FALSE) -> MAESTRO SOLDADOR 3G | H44: =VLOOKUP(Tabla1[[#This Row],[DNI ]],RUBRO!$F$1:$O$9996,6,FALSE) -> QUIROZ CORTEJANA DANTE GABRIEL | I44: 44323 | J44: 2 | K44: 45486657 | L44: =VLOOKUP(Tabla1[[#This Row],[DNI ]],RUBRO!$F$2:$O$9996,8,FALSE) -> 90 | M44: 0.29166667 | N44: 0.54166667 | O44: 0.58333333 | P44: 0.75 | Q44: =(Tabla1[[#This Row],[SALIDA]]-Tabla1[[#This Row],[FIN ]])+(Tabla1[[#This Row],[INICIO]]-Tabla1[[#This Row],[INGRESO]]) -> 0.41666667 | R44: =IF(J44=1,IF(Q44>$AU$1,$AU$1,Q44),0)+IF(J44=2,IF(Q44>$AU$3,$AU$3,Q44),0)+IF(J44=8,IF(Q44>$AU$5,$AU$5,Q44),0) -> 0.33333333 | S44: =IF(J44=1,IF(Q44>$AU$1,(Q44-R44),0),0)+IF(J44=2,IF(Q44>$AU$3,(Q44-R44),0),0)+IF(J44=8,IF(Q44>$AU$5,(Q44-R44),0),0) -> 0.083333333 | V44: =(Tabla1[[#This Row],[COS.BASE 3]]*0.25+Tabla1[[#This Row],[COS.BASE 3]])*Tabla1[[#This Row],[HORAS 25 % ]] -> 0 | W44: =(Tabla1[[#This Row],[COS.BASE 3]]*0.35+Tabla1[[#This Row],[COS.BASE 3]])*Tabla1[[#This Row],[HORAS 35% ]] -> 0 | X44: =SUM(Tabla1[[#This Row],[C.HORA.35]],Tabla1[[#This Row],[C.HORA.25]]) -> 0 | Z44: =Tabla1[[#This Row],[T.HORAS]]*24 -> 10 | AA44: =Tabla1[[#This Row],[H.NORMALES]]*24 -> 8 | AB44: =Tabla1[[#This Row],[H.EXTRAS]]*24 -> 2 | AC44: =IF(J44=1,(((R44*24)*(L44/9))),0)+IF(J44=2,(((R44*24)*(L44/8))),0)+IF(J44=8,(((R44*24)*(L44/8))),0) -> 90 | AD44: =Tabla1[[#This Row],[COS.BASE 2]]/8 -> 11.25 | AE44: =Tabla1[[#This Row],[CST_H_E]]+Tabla1[[#This Row],[COS.BASE 2]] -> 90 | AF44: =+_xlfn.IFNA(INDEX(RUBRO!$W$2:$AA$732,MATCH(Tabla1[[#This Row],[FECHA ]],RUBRO!$W$2:$W$732,0),5)," ") -> 0 | AG44: =+_xlfn.IFNA(INDEX(RUBRO!$W$2:$AA$732,MATCH(Tabla1[[#This Row],[FECHA ]],RUBRO!$W$2:$W$732,0),2)," ") -> 0 | AH44: =IFERROR(Tabla1[[#This Row],[F]]*Tabla1[[#This Row],[COS.B+E]]," ") -> 0 | AI44: =IFERROR(Tabla1[[#This Row],[COS.B+E]]*Tabla1[[#This Row],[D]]," ") -> 0 | AJ44: =IFERROR(Tabla1[[#This Row],[F]]*#REF!," ") | AK44: =IFERROR(#REF!*Tabla1[[#This Row],[D]]," ") | AO44: =+Tabla1[[#This Row],[COS.B+E]]+Tabla1[[#This Row],[COS.F1]]+Tabla1[[#This Row],[COS.D1]]+Tabla1[[#This Row],[ALIMENTACION]]+Tabla1[[#This Row],[PRESTAMO]]+AN44 -> 90 | AP44: =+#REF!+Tabla1[[#This Row],[COS F2]]+Tabla1[[#This Row],[COS D2]]+Tabla1[[#This Row],[ALIMENTACION]]+Tabla1[[#This Row],[PRESTAMO]]+Tabla1[[#This Row],[PASAJES]] -> #REF!
A45: =TEXT(Tabla1[[#This Row],[FECHA ]],"DDDDD") -> viernes | B45: =_xlfn.IFNA(VLOOKUP(Tabla1[[#This Row],[DESTINO]],RUBRO!$Q$1:$R$9996,2,FALSE)," ") -> OBRA | C45: =WEEKNUM(Tabla1[[#This Row],[FECHA ]],2) -> 19 | D45: =TEXT(Tabla1[[#This Row],[FECHA ]],"MMM-YY") -> may-YY | E45: =VLOOKUP(Tabla1[[#This Row],[DNI ]],RUBRO!$F$1:$O$9996,7,FALSE) -> 5ta | F45: =VLOOKUP(Tabla1[[#This Row],[DNI ]],RUBRO!$F$1:$O$88,3,FALSE) -> MAEME-03 | G45: =VLOOKUP(Tabla1[[#This Row],[DNI ]],RUBRO!$F$1:$O$9996,5,FALSE) -> MAESTRO ELECTRICO MONTAJISTA DE MAQUINARIA EXTRANJERA | H45: =VLOOKUP(Tabla1[[#This Row],[DNI ]],RUBRO!$F$1:$O$9996,6,FALSE) -> RAMIREZ PELAEZ ELIAS | I45: 44323 | J45: 2 | K45: 45779525 | L45: =VLOOKUP(Tabla1[[#This Row],[DNI ]],RUBRO!$F$2:$O$9996,8,FALSE) -> 116.06 | M45: 0.27083333 | P45: 0.54166667 | Q45: =(Tabla1[[#This Row],[SALIDA]]-Tabla1[[#This Row],[FIN ]])+(Tabla1[[#This Row],[INICIO]]-Tabla1[[#This Row],[INGRESO]]) -> 0.27083333 | R45: =IF(J45=1,IF(Q45>$AU$1,$AU$1,Q45),0)+IF(J45=2,IF(Q45>$AU$3,$AU$3,Q45),0)+IF(J45=8,IF(Q45>$AU$5,$AU$5,Q45),0) -> 0.27083333 | S45: =IF(J45=1,IF(Q45>$AU$1,(Q45-R45),0),0)+IF(J45=2,IF(Q45>$AU$3,(Q45-R45),0),0)+IF(J45=8,IF(Q45>$AU$5,(Q45-R45),0),0) -> 0 | V45: =(Tabla1[[#This Row],[COS.BASE 3]]*0.25+Tabla1[[#This Row],[COS.BASE 3]])*Tabla1[[#This Row],[HORAS 25 % ]] -> 0 | W45: =(Tabla1[[#This Row],[COS.BASE 3]]*0.35+Tabla1[[#This Row],[COS.BASE 3]])*Tabla1[[#This Row],[HORAS 35% ]] -> 0 | X45: =SUM(Tabla1[[#This Row],[C.HORA.35]],Tabla1[[#This Row],[C.HORA.25]]) -> 0 | Z45: =Tabla1[[#This Row],[T.HORAS]]*24 -> 6.5 | AA45: =Tabla1[[#This Row],[H.NORMALES]]*24 -> 6.5 | AB45: =Tabla1[[#This Row],[H.EXTRAS]]*24 -> 0 | AC45: =IF(J45=1,(((R45*24)*(L45/9))),0)+IF(J45=2,(((R45*24)*(L45/8))),0)+IF(J45=8,(((R45*24)*(L45/8))),0) -> 94.29875 | AD45: =Tabla1[[#This Row],[COS.BASE 2]]/8 -> 11.787344 | AE45: =Tabla1[[#This Row],[CST_H_E]]+Tabla1[[#This Row],[COS.BASE 2]] -> 94.29875 | AF45: =+_xlfn.IFNA(INDEX(RUBRO!$W$2:$AA$732,MATCH(Tabla1[[#This Row],[FECHA ]],RUBRO!$W$2:$W$732,0),5)," ") -> 0 | AG45: =+_xlfn.IFNA(INDEX(RUBRO!$W$2:$AA$732,MATCH(Tabla1[[#This Row],[FECHA ]],RUBRO!$W$2:$W$732,0),2)," ") -> 0 | AH45: =IFERROR(Tabla1[[#This Row],[F]]*Tabla1[[#This Row],[COS.B+E]]," ") -> 0 | AI45: =IFERROR(Tabla1[[#This Row],[COS.B+E]]*Tabla1[[#This Row],[D]]," ") -> 0 | AJ45: =IFERROR(Tabla1[[#This Row],[F]]*#REF!," ") | AK45: =IFERROR(#REF!*Tabla1[[#This Row],[D]]," ") | AO45: =+Tabla1[[#This Row],[COS.B+E]]+Tabla1[[#This Row],[COS.F1]]+Tabla1[[#This Row],[COS.D1]]+Tabla1[[#This Row],[ALIMENTACION]]+Tabla1[[#This Row],[PRESTAMO]]+AN45 -> 94.29875 | AP45: =+#REF!+Tabla1[[#This Row],[COS F2]]+Tabla1[[#This Row],[COS D2]]+Tabla1[[#This Row],[ALIMENTACION]]+Tabla1[[#This Row],[PRESTAMO]]+Tabla1[[#This Row],[PASAJES]] -> #REF!
A46: =TEXT(Tabla1[[#This Row],[FECHA ]],"DDDDD") -> viernes | B46: =_xlfn.IFNA(VLOOKUP(Tabla1[[#This Row],[DESTINO]],RUBRO!$Q$1:$R$9996,2,FALSE)," ") -> FALTA | C46: =WEEKNUM(Tabla1[[#This Row],[FECHA ]],2) -> 19 | D46: =TEXT(Tabla1[[#This Row],[FECHA ]],"MMM-YY") -> may-YY | E46: =VLOOKUP(Tabla1[[#This Row],[DNI ]],RUBRO!$F$1:$O$9996,7,FALSE) -> 5ta | F46: =VLOOKUP(Tabla1[[#This Row],[DNI ]],RUBRO!$F$1:$O$88,3,FALSE) -> MAE3G-01 | G46: =VLOOKUP(Tabla1[[#This Row],[DNI ]],RUBRO!$F$1:$O$9996,5,FALSE) -> MAESTRO SOLDADOR 3G | H46: =VLOOKUP(Tabla1[[#This Row],[DNI ]],RUBRO!$F$1:$O$9996,6,FALSE) -> RIOJA RODRIGUEZ MARCO JEAIR | I46: 44323 | J46: 4 | K46: 77423720 | L46: =VLOOKUP(Tabla1[[#This Row],[DNI ]],RUBRO!$F$2:$O$9996,8,FALSE) -> 69.44 | Q46: =(Tabla1[[#This Row],[SALIDA]]-Tabla1[[#This Row],[FIN ]])+(Tabla1[[#This Row],[INICIO]]-Tabla1[[#This Row],[INGRESO]]) -> 0 | R46: =IF(J46=1,IF(Q46>$AU$1,$AU$1,Q46),0)+IF(J46=2,IF(Q46>$AU$3,$AU$3,Q46),0)+IF(J46=8,IF(Q46>$AU$5,$AU$5,Q46),0) -> 0 | S46: =IF(J46=1,IF(Q46>$AU$1,(Q46-R46),0),0)+IF(J46=2,IF(Q46>$AU$3,(Q46-R46),0),0)+IF(J46=8,IF(Q46>$AU$5,(Q46-R46),0),0) -> 0 | V46: =(Tabla1[[#This Row],[COS.BASE 3]]*0.25+Tabla1[[#This Row],[COS.BASE 3]])*Tabla1[[#This Row],[HORAS 25 % ]] -> 0 | W46: =(Tabla1[[#This Row],[COS.BASE 3]]*0.35+Tabla1[[#This Row],[COS.BASE 3]])*Tabla1[[#This Row],[HORAS 35% ]] -> 0 | X46: =SUM(Tabla1[[#This Row],[C.HORA.35]],Tabla1[[#This Row],[C.HORA.25]]) -> 0 | Z46: =Tabla1[[#This Row],[T.HORAS]]*24 -> 0 | AA46: =Tabla1[[#This Row],[H.NORMALES]]*24 -> 0 | AB46: =Tabla1[[#This Row],[H.EXTRAS]]*24 -> 0 | AC46: =IF(J46=1,(((R46*24)*(L46/9))),0)+IF(J46=2,(((R46*24)*(L46/8))),0)+IF(J46=8,(((R46*24)*(L46/8))),0) -> 0 | AD46: =Tabla1[[#This Row],[COS.BASE 2]]/8 -> 0 | AE46: =Tabla1[[#This Row],[CST_H_E]]+Tabla1[[#This Row],[COS.BASE 2]] -> 0 | AF46: =+_xlfn.IFNA(INDEX(RUBRO!$W$2:$AA$732,MATCH(Tabla1[[#This Row],[FECHA ]],RUBRO!$W$2:$W$732,0),5)," ") -> 0 | AG46: =+_xlfn.IFNA(INDEX(RUBRO!$W$2:$AA$732,MATCH(Tabla1[[#This Row],[FECHA ]],RUBRO!$W$2:$W$732,0),2)," ") -> 0 | AH46: =IFERROR(Tabla1[[#This Row],[F]]*Tabla1[[#This Row],[COS.B+E]]," ") -> 0 | AI46: =IFERROR(Tabla1[[#This Row],[COS.B+E]]*Tabla1[[#This Row],[D]]," ") -> 0 | AJ46: =IFERROR(Tabla1[[#This Row],[F]]*#REF!," ") | AK46: =IFERROR(#REF!*Tabla1[[#This Row],[D]]," ") | AO46: =+Tabla1[[#This Row],[COS.B+E]]+Tabla1[[#This Row],[COS.F1]]+Tabla1[[#This Row],[COS.D1]]+Tabla1[[#This Row],[ALIMENTACION]]+Tabla1[[#This Row],[PRESTAMO]]+AN46 -> 0 | AP46: =+#REF!+Tabla1[[#This Row],[COS F2]]+Tabla1[[#This Row],[COS D2]]+Tabla1[[#This Row],[ALIMENTACION]]+Tabla1[[#This Row],[PRESTAMO]]+Tabla1[[#This Row],[PASAJES]] -> #REF!
A47: =TEXT(Tabla1[[#This Row],[FECHA ]],"DDDDD") -> viernes | B47: =_xlfn.IFNA(VLOOKUP(Tabla1[[#This Row],[DESTINO]],RUBRO!$Q$1:$R$9996,2,FALSE)," ") -> PLANTA | C47: =WEEKNUM(Tabla1[[#This Row],[FECHA ]],2) -> 19 | D47: =TEXT(Tabla1[[#This Row],[FECHA ]],"MMM-YY") -> may-YY | E47: =VLOOKUP(Tabla1[[#This Row],[DNI ]],RUBRO!$F$1:$O$9996,7,FALSE) -> 5ta | F47: =VLOOKUP(Tabla1[[#This Row],[DNI ]],RUBRO!$F$1:$O$88,3,FALSE) -> MAE6G-01 | G47: =VLOOKUP(Tabla1[[#This Row],[DNI ]],RUBRO!$F$1:$O$9996,5,FALSE) -> MAESTRO SOLDADOR 6G MONTAJISTA DE MAQUINARIA | H47: =VLOOKUP(Tabla1[[#This Row],[DNI ]],RUBRO!$F$1:$O$9996,6,FALSE) -> RIVERA LEONARDO EVER JOSE | I47: 44323 | J47: 1 | K47: 45035778 | L47: =VLOOKUP(Tabla1[[#This Row],[DNI ]],RUBRO!$F$2:$O$9996,8,FALSE) -> 92.8 | M47: 0.29166667 | N47: 0.54166667 | O47: 0.58333333 | P47: 0.79166667 | Q47: =(Tabla1[[#This Row],[SALIDA]]-Tabla1[[#This Row],[FIN ]])+(Tabla1[[#This Row],[INICIO]]-Tabla1[[#This Row],[INGRESO]]) -> 0.45833333 | R47: =IF(J47=1,IF(Q47>$AU$1,$AU$1,Q47),0)+IF(J47=2,IF(Q47>$AU$3,$AU$3,Q47),0)+IF(J47=8,IF(Q47>$AU$5,$AU$5,Q47),0) -> 0.375 | S47: =IF(J47=1,IF(Q47>$AU$1,(Q47-R47),0),0)+IF(J47=2,IF(Q47>$AU$3,(Q47-R47),0),0)+IF(J47=8,IF(Q47>$AU$5,(Q47-R47),0),0) -> 0.083333333 | V47: =(Tabla1[[#This Row],[COS.BASE 3]]*0.25+Tabla1[[#This Row],[COS.BASE 3]])*Tabla1[[#This Row],[HORAS 25 % ]] -> 0 | W47: =(Tabla1[[#This Row],[COS.BASE 3]]*0.35+Tabla1[[#This Row],[COS.BASE 3]])*Tabla1[[#This Row],[HORAS 35% ]] -> 0 | X47: =SUM(Tabla1[[#This Row],[C.HORA.35]],Tabla1[[#This Row],[C.HORA.25]]) -> 0 | Z47: =Tabla1[[#This Row],[T.HORAS]]*24 -> 11 | AA47: =Tabla1[[#This Row],[H.NORMALES]]*24 -> 9 | AB47: =Tabla1[[#This Row],[H.EXTRAS]]*24 -> 2 | AC47: =IF(J47=1,(((R47*24)*(L47/9))),0)+IF(J47=2,(((R47*24)*(L47/8))),0)+IF(J47=8,(((R47*24)*(L47/8))),0) -> 92.8 | AD47: =Tabla1[[#This Row],[COS.BASE 2]]/8 -> 11.6 | AE47: =Tabla1[[#This Row],[CST_H_E]]+Tabla1[[#This Row],[COS.BASE 2]] -> 92.8 | AF47: =+_xlfn.IFNA(INDEX(RUBRO!$W$2:$AA$732,MATCH(Tabla1[[#This Row],[FECHA ]],RUBRO!$W$2:$W$732,0),5)," ") -> 0 | AG47: =+_xlfn.IFNA(INDEX(RUBRO!$W$2:$AA$732,MATCH(Tabla1[[#This Row],[FECHA ]],RUBRO!$W$2:$W$732,0),2)," ") -> 0 | AH47: =IFERROR(Tabla1[[#This Row],[F]]*Tabla1[[#This Row],[COS.B+E]]," ") -> 0 | AI47: =IFERROR(Tabla1[[#This Row],[COS.B+E]]*Tabla1[[#This Row],[D]]," ") -> 0 | AJ47: =IFERROR(Tabla1[[#This Row],[F]]*#REF!," ") | AK47: =IFERROR(#REF!*Tabla1[[#This Row],[D]]," ") | AO47: =+Tabla1[[#This Row],[COS.B+E]]+Tabla1[[#This Row],[COS.F1]]+Tabla1[[#This Row],[COS.D1]]+Tabla1[[#This Row],[ALIMENTACION]]+Tabla1[[#This Row],[PRESTAMO]]+AN47 -> 92.8 | AP47: =+#REF!+Tabla1[[#This Row],[COS F2]]+Tabla1[[#This Row],[COS D2]]+Tabla1[[#This Row],[ALIMENTACION]]+Tabla1[[#This Row],[PRESTAMO]]+Tabla1[[#This Row],[PASAJES]] -> #REF!
A48: =TEXT(Tabla1[[#This Row],[FECHA ]],"DDDDD") -> viernes | B48: =_xlfn.IFNA(VLOOKUP(Tabla1[[#This Row],[DESTINO]],RUBRO!$Q$1:$R$9996,2,FALSE)," ") -> OBRA | C48: =WEEKNUM(Tabla1[[#This Row],[FECHA ]],2) -> 19 | D48: =TEXT(Tabla1[[#This Row],[FECHA ]],"MMM-YY") -> may-YY | E48: =VLOOKUP(Tabla1[[#This Row],[DNI ]],RUBRO!$F$1:$O$9996,7,FALSE) -> 5ta | F48: =VLOOKUP(Tabla1[[#This Row],[DNI ]],RUBRO!$F$1:$O$88,3,FALSE) -> MAE-04 | G48: =VLOOKUP(Tabla1[[#This Row],[DNI ]],RUBRO!$F$1:$O$9996,5,FALSE) -> MAESTRO MECANICO MONTAJISTA DE MAQUINARIA EXTRANJERA | H48: =VLOOKUP(Tabla1[[#This Row],[DNI ]],RUBRO!$F$1:$O$9996,6,FALSE) -> ROMERO MARIN JAIRO JOEL | I48: 44323 | J48: 2 | K48: 72926564 | L48: =VLOOKUP(Tabla1[[#This Row],[DNI ]],RUBRO!$F$2:$O$9996,8,FALSE) -> 88.27 | M48: 0 | N48: 0.29166667 | O48: 0.91666667 | P48: 0.99930556 | Q48: =(Tabla1[[#This Row],[SALIDA]]-Tabla1[[#This Row],[FIN ]])+(Tabla1[[#This Row],[INICIO]]-Tabla1[[#This Row],[INGRESO]]) -> 0.37430556 | R48: =IF(J48=1,IF(Q48>$AU$1,$AU$1,Q48),0)+IF(J48=2,IF(Q48>$AU$3,$AU$3,Q48),0)+IF(J48=8,IF(Q48>$AU$5,$AU$5,Q48),0) -> 0.33333333 | S48: =IF(J48=1,IF(Q48>$AU$1,(Q48-R48),0),0)+IF(J48=2,IF(Q48>$AU$3,(Q48-R48),0),0)+IF(J48=8,IF(Q48>$AU$5,(Q48-R48),0),0) -> 0.040972222 | V48: =(Tabla1[[#This Row],[COS.BASE 3]]*0.25+Tabla1[[#This Row],[COS.BASE 3]])*Tabla1[[#This Row],[HORAS 25 % ]] -> 0 | W48: =(Tabla1[[#This Row],[COS.BASE 3]]*0.35+Tabla1[[#This Row],[COS.BASE 3]])*Tabla1[[#This Row],[HORAS 35% ]] -> 0 | X48: =SUM(Tabla1[[#This Row],[C.HORA.35]],Tabla1[[#This Row],[C.HORA.25]]) -> 0 | Z48: =Tabla1[[#This Row],[T.HORAS]]*24 -> 8.9833333 | AA48: =Tabla1[[#This Row],[H.NORMALES]]*24 -> 8 | AB48: =Tabla1[[#This Row],[H.EXTRAS]]*24 -> 0.98333333 | AC48: =IF(J48=1,(((R48*24)*(L48/9))),0)+IF(J48=2,(((R48*24)*(L48/8))),0)+IF(J48=8,(((R48*24)*(L48/8))),0) -> 88.27 | AD48: =Tabla1[[#This Row],[COS.BASE 2]]/8 -> 11.03375 | AE48: =Tabla1[[#This Row],[CST_H_E]]+Tabla1[[#This Row],[COS.BASE 2]] -> 88.27 | AF48: =+_xlfn.IFNA(INDEX(RUBRO!$W$2:$AA$732,MATCH(Tabla1[[#This Row],[FECHA ]],RUBRO!$W$2:$W$732,0),5)," ") -> 0 | AG48: =+_xlfn.IFNA(INDEX(RUBRO!$W$2:$AA$732,MATCH(Tabla1[[#This Row],[FECHA ]],RUBRO!$W$2:$W$732,0),2)," ") -> 0 | AH48: =IFERROR(Tabla1[[#This Row],[F]]*Tabla1[[#This Row],[COS.B+E]]," ") -> 0 | AI48: =IFERROR(Tabla1[[#This Row],[COS.B+E]]*Tabla1[[#This Row],[D]]," ") -> 0 | AJ48: =IFERROR(Tabla1[[#This Row],[F]]*#REF!," ") | AK48: =IFERROR(#REF!*Tabla1[[#This Row],[D]]," ") | AO48: =+Tabla1[[#This Row],[COS.B+E]]+Tabla1[[#This Row],[COS.F1]]+Tabla1[[#This Row],[COS.D1]]+Tabla1[[#This Row],[ALIMENTACION]]+Tabla1[[#This Row],[PRESTAMO]]+AN48 -> 88.27 | AP48: =+#REF!+Tabla1[[#This Row],[COS F2]]+Tabla1[[#This Row],[COS D2]]+Tabla1[[#This Row],[ALIMENTACION]]+Tabla1[[#This Row],[PRESTAMO]]+Tabla1[[#This Row],[PASAJES]] -> #REF!
A49: =TEXT(Tabla1[[#This Row],[FECHA ]],"DDDDD") -> viernes | B49: =_xlfn.IFNA(VLOOKUP(Tabla1[[#This Row],[DESTINO]],RUBRO!$Q$1:$R$9996,2,FALSE)," ") -> FALTA | C49: =WEEKNUM(Tabla1[[#This Row],[FECHA ]],2) -> 19 | D49: =TEXT(Tabla1[[#This Row],[FECHA ]],"MMM-YY") -> may-YY | E49: =VLOOKUP(Tabla1[[#This Row],[DNI ]],RUBRO!$F$1:$O$9996,7,FALSE) -> 5ta | F49: =VLOOKUP(Tabla1[[#This Row],[DNI ]],RUBRO!$F$1:$O$88,3,FALSE) -> #N/A | G49: =VLOOKUP(Tabla1[[#This Row],[DNI ]],RUBRO!$F$1:$O$9996,5,FALSE) -> TECNICO SOLDADOR | H49: =VLOOKUP(Tabla1[[#This Row],[DNI ]],RUBRO!$F$1:$O$9996,6,FALSE) -> SALAZAR FERNANDEZ WALTER | I49: 44323 | J49: 4 | K49: 72927801 | L49: =VLOOKUP(Tabla1[[#This Row],[DNI ]],RUBRO!$F$2:$O$9996,8,FALSE) -> 60 | Q49: =(Tabla1[[#This Row],[SALIDA]]-Tabla1[[#This Row],[FIN ]])+(Tabla1[[#This Row],[INICIO]]-Tabla1[[#This Row],[INGRESO]]) -> 0 | R49: =IF(J49=1,IF(Q49>$AU$1,$AU$1,Q49),0)+IF(J49=2,IF(Q49>$AU$3,$AU$3,Q49),0)+IF(J49=8,IF(Q49>$AU$5,$AU$5,Q49),0) -> 0 | S49: =IF(J49=1,IF(Q49>$AU$1,(Q49-R49),0),0)+IF(J49=2,IF(Q49>$AU$3,(Q49-R49),0),0)+IF(J49=8,IF(Q49>$AU$5,(Q49-R49),0),0) -> 0 | V49: =(Tabla1[[#This Row],[COS.BASE 3]]*0.25+Tabla1[[#This Row],[COS.BASE 3]])*Tabla1[[#This Row],[HORAS 25 % ]] -> 0 | W49: =(Tabla1[[#This Row],[COS.BASE 3]]*0.35+Tabla1[[#This Row],[COS.BASE 3]])*Tabla1[[#This Row],[HORAS 35% ]] -> 0 | X49: =SUM(Tabla1[[#This Row],[C.HORA.35]],Tabla1[[#This Row],[C.HORA.25]]) -> 0 | Z49: =Tabla1[[#This Row],[T.HORAS]]*24 -> 0 | AA49: =Tabla1[[#This Row],[H.NORMALES]]*24 -> 0 | AB49: =Tabla1[[#This Row],[H.EXTRAS]]*24 -> 0 | AC49: =IF(J49=1,(((R49*24)*(L49/9))),0)+IF(J49=2,(((R49*24)*(L49/8))),0)+IF(J49=8,(((R49*24)*(L49/8))),0) -> 0 | AD49: =Tabla1[[#This Row],[COS.BASE 2]]/8 -> 0 | AE49: =Tabla1[[#This Row],[CST_H_E]]+Tabla1[[#This Row],[COS.BASE 2]] -> 0 | AF49: =+_xlfn.IFNA(INDEX(RUBRO!$W$2:$AA$732,MATCH(Tabla1[[#This Row],[FECHA ]],RUBRO!$W$2:$W$732,0),5)," ") -> 0 | AG49: =+_xlfn.IFNA(INDEX(RUBRO!$W$2:$AA$732,MATCH(Tabla1[[#This Row],[FECHA ]],RUBRO!$W$2:$W$732,0),2)," ") -> 0 | AH49: =IFERROR(Tabla1[[#This Row],[F]]*Tabla1[[#This Row],[COS.B+E]]," ") -> 0 | AI49: =IFERROR(Tabla1[[#This Row],[COS.B+E]]*Tabla1[[#This Row],[D]]," ") -> 0 | AJ49: =IFERROR(Tabla1[[#This Row],[F]]*#REF!," ") | AK49: =IFERROR(#REF!*Tabla1[[#This Row],[D]]," ") | AO49: =+Tabla1[[#This Row],[COS.B+E]]+Tabla1[[#This Row],[COS.F1]]+Tabla1[[#This Row],[COS.D1]]+Tabla1[[#This Row],[ALIMENTACION]]+Tabla1[[#This Row],[PRESTAMO]]+AN49 -> 0 | AP49: =+#REF!+Tabla1[[#This Row],[COS F2]]+Tabla1[[#This Row],[COS D2]]+Tabla1[[#This Row],[ALIMENTACION]]+Tabla1[[#This Row],[PRESTAMO]]+Tabla1[[#This Row],[PASAJES]] -> #REF!
A50: =TEXT(Tabla1[[#This Row],[FECHA ]],"DDDDD") -> viernes | B50: =_xlfn.IFNA(VLOOKUP(Tabla1[[#This Row],[DESTINO]],RUBRO!$Q$1:$R$9996,2,FALSE)," ") -> OBRA | C50: =WEEKNUM(Tabla1[[#This Row],[FECHA ]],2) -> 19 | D50: =TEXT(Tabla1[[#This Row],[FECHA ]],"MMM-YY") -> may-YY | E50: =VLOOKUP(Tabla1[[#This Row],[DNI ]],RUBRO!$F$1:$O$9996,7,FALSE) -> 5ta | F50: =VLOOKUP(Tabla1[[#This Row],[DNI ]],RUBRO!$F$1:$O$88,3,FALSE) -> MEC-04 | G50: =VLOOKUP(Tabla1[[#This Row],[DNI ]],RUBRO!$F$1:$O$9996,5,FALSE) -> MECANICO MONTAJISTA DE MAQUINARIA EXTRANJERA | H50: =VLOOKUP(Tabla1[[#This Row],[DNI ]],RUBRO!$F$1:$O$9996,6,FALSE) -> SANDOVAL CHAPOÑAN ELVIS EDUARDO | I50: 44323 | J50: 2 | K50: 45360771 | L50: =VLOOKUP(Tabla1[[#This Row],[DNI ]],RUBRO!$F$2:$O$9996,8,FALSE) -> 94.35 | M50: 0 | N50: 0.29166667 | O50: 0.875 | P50: 0.95833333 | Q50: =(Tabla1[[#This Row],[SALIDA]]-Tabla1[[#This Row],[FIN ]])+(Tabla1[[#This Row],[INICIO]]-Tabla1[[#This Row],[INGRESO]]) -> 0.375 | R50: =IF(J50=1,IF(Q50>$AU$1,$AU$1,Q50),0)+IF(J50=2,IF(Q50>$AU$3,$AU$3,Q50),0)+IF(J50=8,IF(Q50>$AU$5,$AU$5,Q50),0) -> 0.33333333 | S50: =IF(J50=1,IF(Q50>$AU$1,(Q50-R50),0),0)+IF(J50=2,IF(Q50>$AU$3,(Q50-R50),0),0)+IF(J50=8,IF(Q50>$AU$5,(Q50-R50),0),0) -> 0.041666667 | V50: =(Tabla1[[#This Row],[COS.BASE 3]]*0.25+Tabla1[[#This Row],[COS.BASE 3]])*Tabla1[[#This Row],[HORAS 25 % ]] -> 0 | W50: =(Tabla1[[#This Row],[COS.BASE 3]]*0.35+Tabla1[[#This Row],[COS.BASE 3]])*Tabla1[[#This Row],[HORAS 35% ]] -> 0 | X50: =SUM(Tabla1[[#This Row],[C.HORA.35]],Tabla1[[#This Row],[C.HORA.25]]) -> 0 | Z50: =Tabla1[[#This Row],[T.HORAS]]*24 -> 9 | AA50: =Tabla1[[#This Row],[H.NORMALES]]*24 -> 8 | AB50: =Tabla1[[#This Row],[H.EXTRAS]]*24 -> 1 | AC50: =IF(J50=1,(((R50*24)*(L50/9))),0)+IF(J50=2,(((R50*24)*(L50/8))),0)+IF(J50=8,(((R50*24)*(L50/8))),0) -> 94.35 | AD50: =Tabla1[[#This Row],[COS.BASE 2]]/8 -> 11.79375 | AE50: =Tabla1[[#This Row],[CST_H_E]]+Tabla1[[#This Row],[COS.BASE 2]] -> 94.35 | AF50: =+_xlfn.IFNA(INDEX(RUBRO!$W$2:$AA$732,MATCH(Tabla1[[#This Row],[FECHA ]],RUBRO!$W$2:$W$732,0),5)," ") -> 0 | AG50: =+_xlfn.IFNA(INDEX(RUBRO!$W$2:$AA$732,MATCH(Tabla1[[#This Row],[FECHA ]],RUBRO!$W$2:$W$732,0),2)," ") -> 0 | AH50: =IFERROR(Tabla1[[#This Row],[F]]*Tabla1[[#This Row],[COS.B+E]]," ") -> 0 | AI50: =IFERROR(Tabla1[[#This Row],[COS.B+E]]*Tabla1[[#This Row],[D]]," ") -> 0 | AJ50: =IFERROR(Tabla1[[#This Row],[F]]*#REF!," ") | AK50: =IFERROR(#REF!*Tabla1[[#This Row],[D]]," ") | AO50: =+Tabla1[[#This Row],[COS.B+E]]+Tabla1[[#This Row],[COS.F1]]+Tabla1[[#This Row],[COS.D1]]+Tabla1[[#This Row],[ALIMENTACION]]+Tabla1[[#This Row],[PRESTAMO]]+AN50 -> 94.35 | AP50: =+#REF!+Tabla1[[#This Row],[COS F2]]+Tabla1[[#This Row],[COS D2]]+Tabla1[[#This Row],[ALIMENTACION]]+Tabla1[[#This Row],[PRESTAMO]]+Tabla1[[#This Row],[PASAJES]] -> #REF!
A51: =TEXT(Tabla1[[#This Row],[FECHA ]],"DDDDD") -> viernes | B51: =_xlfn.IFNA(VLOOKUP(Tabla1[[#This Row],[DESTINO]],RUBRO!$Q$1:$R$9996,2,FALSE)," ") -> OBRA | C51: =WEEKNUM(Tabla1[[#This Row],[FECHA ]],2) -> 19 | D51: =TEXT(Tabla1[[#This Row],[FECHA ]],"MMM-YY") -> may-YY | E51: =VLOOKUP(Tabla1[[#This Row],[DNI ]],RUBRO!$F$1:$O$9996,7,FALSE) -> 5ta | F51: =VLOOKUP(Tabla1[[#This Row],[DNI ]],RUBRO!$F$1:$O$88,3,FALSE) -> #N/A | G51: =VLOOKUP(Tabla1[[#This Row],[DNI ]],RUBRO!$F$1:$O$9996,5,FALSE) -> TECNICO MECANICO MONTAJISTA DE NAVE INDUSTRIAL | H51: =VLOOKUP(Tabla1[[#This Row],[DNI ]],RUBRO!$F$1:$O$9996,6,FALSE) -> SOLANO SUELDO CARLOS | I51: 44323 | J51: 2 | K51: 44676684 | L51: =VLOOKUP(Tabla1[[#This Row],[DNI ]],RUBRO!$F$2:$O$9996,8,FALSE) -> 70 | M51: 0.29166667 | N51: 0.54166667 | O51: 0.58333333 | P51: 0.75 | Q51: =(Tabla1[[#This Row],[SALIDA]]-Tabla1[[#This Row],[FIN ]])+(Tabla1[[#This Row],[INICIO]]-Tabla1[[#This Row],[INGRESO]]) -> 0.41666667 | R51: =IF(J51=1,IF(Q51>$AU$1,$AU$1,Q51),0)+IF(J51=2,IF(Q51>$AU$3,$AU$3,Q51),0)+IF(J51=8,IF(Q51>$AU$5,$AU$5,Q51),0) -> 0.33333333 | S51: =IF(J51=1,IF(Q51>$AU$1,(Q51-R51),0),0)+IF(J51=2,IF(Q51>$AU$3,(Q51-R51),0),0)+IF(J51=8,IF(Q51>$AU$5,(Q51-R51),0),0) -> 0.083333333 | V51: =(Tabla1[[#This Row],[COS.BASE 3]]*0.25+Tabla1[[#This Row],[COS.BASE 3]])*Tabla1[[#This Row],[HORAS 25 % ]] -> 0 | W51: =(Tabla1[[#This Row],[COS.BASE 3]]*0.35+Tabla1[[#This Row],[COS.BASE 3]])*Tabla1[[#This Row],[HORAS 35% ]] -> 0 | X51: =SUM(Tabla1[[#This Row],[C.HORA.35]],Tabla1[[#This Row],[C.HORA.25]]) -> 0 | Z51: =Tabla1[[#This Row],[T.HORAS]]*24 -> 10 | AA51: =Tabla1[[#This Row],[H.NORMALES]]*24 -> 8 | AB51: =Tabla1[[#This Row],[H.EXTRAS]]*24 -> 2 | AC51: =IF(J51=1,(((R51*24)*(L51/9))),0)+IF(J51=2,(((R51*24)*(L51/8))),0)+IF(J51=8,(((R51*24)*(L51/8))),0) -> 70 | AD51: =Tabla1[[#This Row],[COS.BASE 2]]/8 -> 8.75 | AE51: =Tabla1[[#This Row],[CST_H_E]]+Tabla1[[#This Row],[COS.BASE 2]] -> 70 | AF51: =+_xlfn.IFNA(INDEX(RUBRO!$W$2:$AA$732,MATCH(Tabla1[[#This Row],[FECHA ]],RUBRO!$W$2:$W$732,0),5)," ") -> 0 | AG51: =+_xlfn.IFNA(INDEX(RUBRO!$W$2:$AA$732,MATCH(Tabla1[[#This Row],[FECHA ]],RUBRO!$W$2:$W$732,0),2)," ") -> 0 | AH51: =IFERROR(Tabla1[[#This Row],[F]]*Tabla1[[#This Row],[COS.B+E]]," ") -> 0 | AI51: =IFERROR(Tabla1[[#This Row],[COS.B+E]]*Tabla1[[#This Row],[D]]," ") -> 0 | AJ51: =IFERROR(Tabla1[[#This Row],[F]]*#REF!," ") | AK51: =IFERROR(#REF!*Tabla1[[#This Row],[D]]," ") | AO51: =+Tabla1[[#This Row],[COS.B+E]]+Tabla1[[#This Row],[COS.F1]]+Tabla1[[#This Row],[COS.D1]]+Tabla1[[#This Row],[ALIMENTACION]]+Tabla1[[#This Row],[PRESTAMO]]+AN51 -> 70 | AP51: =+#REF!+Tabla1[[#This Row],[COS F2]]+Tabla1[[#This Row],[COS D2]]+Tabla1[[#This Row],[ALIMENTACION]]+Tabla1[[#This Row],[PRESTAMO]]+Tabla1[[#This Row],[PASAJES]] -> #REF!
A52: =TEXT(Tabla1[[#This Row],[FECHA ]],"DDDDD") -> viernes | B52: =_xlfn.IFNA(VLOOKUP(Tabla1[[#This Row],[DESTINO]],RUBRO!$Q$1:$R$9996,2,FALSE)," ") | C52: =WEEKNUM(Tabla1[[#This Row],[FECHA ]],2) -> 19 | D52: =TEXT(Tabla1[[#This Row],[FECHA ]],"MMM-YY") -> may-YY | E52: =VLOOKUP(Tabla1[[#This Row],[DNI ]],RUBRO!$F$1:$O$9996,7,FALSE) -> 4ta | F52: =VLOOKUP(Tabla1[[#This Row],[DNI ]],RUBRO!$F$1:$O$88,3,FALSE) -> #N/A | G52: =VLOOKUP(Tabla1[[#This Row],[DNI ]],RUBRO!$F$1:$O$9996,5,FALSE) -> 0 | H52: =VLOOKUP(Tabla1[[#This Row],[DNI ]],RUBRO!$F$1:$O$9996,6,FALSE) -> SOTO NIETO ALEXANDRO FABIO | I52: 44323 | K52: 71214531 | L52: =VLOOKUP(Tabla1[[#This Row],[DNI ]],RUBRO!$F$2:$O$9996,8,FALSE) -> 0 | Q52: =(Tabla1[[#This Row],[SALIDA]]-Tabla1[[#This Row],[FIN ]])+(Tabla1[[#This Row],[INICIO]]-Tabla1[[#This Row],[INGRESO]]) -> 0 | R52: =IF(J52=1,IF(Q52>$AU$1,$AU$1,Q52),0)+IF(J52=2,IF(Q52>$AU$3,$AU$3,Q52),0)+IF(J52=8,IF(Q52>$AU$5,$AU$5,Q52),0) -> 0 | S52: =IF(J52=1,IF(Q52>$AU$1,(Q52-R52),0),0)+IF(J52=2,IF(Q52>$AU$3,(Q52-R52),0),0)+IF(J52=8,IF(Q52>$AU$5,(Q52-R52),0),0) -> 0 | V52: =(Tabla1[[#This Row],[COS.BASE 3]]*0.25+Tabla1[[#This Row],[COS.BASE 3]])*Tabla1[[#This Row],[HORAS 25 % ]] -> 0 | W52: =(Tabla1[[#This Row],[COS.BASE 3]]*0.35+Tabla1[[#This Row],[COS.BASE 3]])*Tabla1[[#This Row],[HORAS 35% ]] -> 0 | X52: =SUM(Tabla1[[#This Row],[C.HORA.35]],Tabla1[[#This Row],[C.HORA.25]]) -> 0 | Z52: =Tabla1[[#This Row],[T.HORAS]]*24 -> 0 | AA52: =Tabla1[[#This Row],[H.NORMALES]]*24 -> 0 | AB52: =Tabla1[[#This Row],[H.EXTRAS]]*24 -> 0 | AC52: =IF(J52=1,(((R52*24)*(L52/9))),0)+IF(J52=2,(((R52*24)*(L52/8))),0)+IF(J52=8,(((R52*24)*(L52/8))),0) -> 0 | AD52: =Tabla1[[#This Row],[COS.BASE 2]]/8 -> 0 | AE52: =Tabla1[[#This Row],[CST_H_E]]+Tabla1[[#This Row],[COS.BASE 2]] -> 0 | AF52: =+_xlfn.IFNA(INDEX(RUBRO!$W$2:$AA$732,MATCH(Tabla1[[#This Row],[FECHA ]],RUBRO!$W$2:$W$732,0),5)," ") -> 0 | AG52: =+_xlfn.IFNA(INDEX(RUBRO!$W$2:$AA$732,MATCH(Tabla1[[#This Row],[FECHA ]],RUBRO!$W$2:$W$732,0),2)," ") -> 0 | AH52: =IFERROR(Tabla1[[#This Row],[F]]*Tabla1[[#This Row],[COS.B+E]]," ") -> 0 | AI52: =IFERROR(Tabla1[[#This Row],[COS.B+E]]*Tabla1[[#This Row],[D]]," ") -> 0 | AJ52: =IFERROR(Tabla1[[#This Row],[F]]*#REF!," ") | AK52: =IFERROR(#REF!*Tabla1[[#This Row],[D]]," ") | AO52: =+Tabla1[[#This Row],[COS.B+E]]+Tabla1[[#This Row],[COS.F1]]+Tabla1[[#This Row],[COS.D1]]+Tabla1[[#This Row],[ALIMENTACION]]+Tabla1[[#This Row],[PRESTAMO]]+AN52 -> 0 | AP52: =+#REF!+Tabla1[[#This Row],[COS F2]]+Tabla1[[#This Row],[COS D2]]+Tabla1[[#This Row],[ALIMENTACION]]+Tabla1[[#This Row],[PRESTAMO]]+Tabla1[[#This Row],[PASAJES]] -> #REF!
A53: =TEXT(Tabla1[[#This Row],[FECHA ]],"DDDDD") -> viernes | B53: =_xlfn.IFNA(VLOOKUP(Tabla1[[#This Row],[DESTINO]],RUBRO!$Q$1:$R$9996,2,FALSE)," ") -> PLANTA | C53: =WEEKNUM(Tabla1[[#This Row],[FECHA ]],2) -> 19 | D53: =TEXT(Tabla1[[#This Row],[FECHA ]],"MMM-YY") -> may-YY | E53: =VLOOKUP(Tabla1[[#This Row],[DNI ]],RUBRO!$F$1:$O$9996,7,FALSE) -> 5ta | F53: =VLOOKUP(Tabla1[[#This Row],[DNI ]],RUBRO!$F$1:$O$88,3,FALSE) -> TEC-02 | G53: =VLOOKUP(Tabla1[[#This Row],[DNI ]],RUBRO!$F$1:$O$9996,5,FALSE) -> TECNICO MECANICO MONTAJISTA DE MAQUINARIA | H53: =VLOOKUP(Tabla1[[#This Row],[DNI ]],RUBRO!$F$1:$O$9996,6,FALSE) -> TINOCO SANTISTEBAN JIMMY JOEL | I53: 44323 | J53: 1 | K53: 47158079 | L53: =VLOOKUP(Tabla1[[#This Row],[DNI ]],RUBRO!$F$2:$O$9996,8,FALSE) -> 56.55 | M53: 0.29166667 | N53: 0.54166667 | O53: 0.58333333 | P53: 0.70833333 | Q53: =(Tabla1[[#This Row],[SALIDA]]-Tabla1[[#This Row],[FIN ]])+(Tabla1[[#This Row],[INICIO]]-Tabla1[[#This Row],[INGRESO]]) -> 0.375 | R53: =IF(J53=1,IF(Q53>$AU$1,$AU$1,Q53),0)+IF(J53=2,IF(Q53>$AU$3,$AU$3,Q53),0)+IF(J53=8,IF(Q53>$AU$5,$AU$5,Q53),0) -> 0.375 | S53: =IF(J53=1,IF(Q53>$AU$1,(Q53-R53),0),0)+IF(J53=2,IF(Q53>$AU$3,(Q53-R53),0),0)+IF(J53=8,IF(Q53>$AU$5,(Q53-R53),0),0) -> 0 | V53: =(Tabla1[[#This Row],[COS.BASE 3]]*0.25+Tabla1[[#This Row],[COS.BASE 3]])*Tabla1[[#This Row],[HORAS 25 % ]] -> 0 | W53: =(Tabla1[[#This Row],[COS.BASE 3]]*0.35+Tabla1[[#This Row],[COS.BASE 3]])*Tabla1[[#This Row],[HORAS 35% ]] -> 0 | X53: =SUM(Tabla1[[#This Row],[C.HORA.35]],Tabla1[[#This Row],[C.HORA.25]]) -> 0 | Z53: =Tabla1[[#This Row],[T.HORAS]]*24 -> 9 | AA53: =Tabla1[[#This Row],[H.NORMALES]]*24 -> 9 | AB53: =Tabla1[[#This Row],[H.EXTRAS]]*24 -> 0 | AC53: =IF(J53=1,(((R53*24)*(L53/9))),0)+IF(J53=2,(((R53*24)*(L53/8))),0)+IF(J53=8,(((R53*24)*(L53/8))),0) -> 56.55 | AD53: =Tabla1[[#This Row],[COS.BASE 2]]/8 -> 7.06875 | AE53: =Tabla1[[#This Row],[CST_H_E]]+Tabla1[[#This Row],[COS.BASE 2]] -> 56.55 | AF53: =+_xlfn.IFNA(INDEX(RUBRO!$W$2:$AA$732,MATCH(Tabla1[[#This Row],[FECHA ]],RUBRO!$W$2:$W$732,0),5)," ") -> 0 | AG53: =+_xlfn.IFNA(INDEX(RUBRO!$W$2:$AA$732,MATCH(Tabla1[[#This Row],[FECHA ]],RUBRO!$W$2:$W$732,0),2)," ") -> 0 | AH53: =IFERROR(Tabla1[[#This Row],[F]]*Tabla1[[#This Row],[COS.B+E]]," ") -> 0 | AI53: =IFERROR(Tabla1[[#This Row],[COS.B+E]]*Tabla1[[#This Row],[D]]," ") -> 0 | AJ53: =IFERROR(Tabla1[[#This Row],[F]]*#REF!," ") | AK53: =IFERROR(#REF!*Tabla1[[#This Row],[D]]," ") | AO53: =+Tabla1[[#This Row],[COS.B+E]]+Tabla1[[#This Row],[COS.F1]]+Tabla1[[#This Row],[COS.D1]]+Tabla1[[#This Row],[ALIMENTACION]]+Tabla1[[#This Row],[PRESTAMO]]+AN53 -> 56.55 | AP53: =+#REF!+Tabla1[[#This Row],[COS F2]]+Tabla1[[#This Row],[COS D2]]+Tabla1[[#This Row],[ALIMENTACION]]+Tabla1[[#This Row],[PRESTAMO]]+Tabla1[[#This Row],[PASAJES]] -> #REF!
A54: =TEXT(Tabla1[[#This Row],[FECHA ]],"DDDDD") -> viernes | B54: =_xlfn.IFNA(VLOOKUP(Tabla1[[#This Row],[DESTINO]],RUBRO!$Q$1:$R$9996,2,FALSE)," ") -> FALTA | C54: =WEEKNUM(Tabla1[[#This Row],[FECHA ]],2) -> 19 | D54: =TEXT(Tabla1[[#This Row],[FECHA ]],"MMM-YY") -> may-YY | E54: =VLOOKUP(Tabla1[[#This Row],[DNI ]],RUBRO!$F$1:$O$9996,7,FALSE) -> 5ta | F54: =VLOOKUP(Tabla1[[#This Row],[DNI ]],RUBRO!$F$1:$O$88,3,FALSE) -> TECME-03 | G54: =VLOOKUP(Tabla1[[#This Row],[DNI ]],RUBRO!$F$1:$O$9996,5,FALSE) -> TECNICO ELECTRICO MONTAJISTA DE MAQUINARIA EXTRANJERA | H54: =VLOOKUP(Tabla1[[#This Row],[DNI ]],RUBRO!$F$1:$O$9996,6,FALSE) -> TORRES RAMOS ANGY ANDREINA | I54: 44323 | J54: 4 | K54: 76449683 | L54: =VLOOKUP(Tabla1[[#This Row],[DNI ]],RUBRO!$F$2:$O$9996,8,FALSE) -> 73.87 | Q54: =(Tabla1[[#This Row],[SALIDA]]-Tabla1[[#This Row],[FIN ]])+(Tabla1[[#This Row],[INICIO]]-Tabla1[[#This Row],[INGRESO]]) -> 0 | R54: =IF(J54=1,IF(Q54>$AU$1,$AU$1,Q54),0)+IF(J54=2,IF(Q54>$AU$3,$AU$3,Q54),0)+IF(J54=8,IF(Q54>$AU$5,$AU$5,Q54),0) -> 0 | S54: =IF(J54=1,IF(Q54>$AU$1,(Q54-R54),0),0)+IF(J54=2,IF(Q54>$AU$3,(Q54-R54),0),0)+IF(J54=8,IF(Q54>$AU$5,(Q54-R54),0),0) -> 0 | V54: =(Tabla1[[#This Row],[COS.BASE 3]]*0.25+Tabla1[[#This Row],[COS.BASE 3]])*Tabla1[[#This Row],[HORAS 25 % ]] -> 0 | W54: =(Tabla1[[#This Row],[COS.BASE 3]]*0.35+Tabla1[[#This Row],[COS.BASE 3]])*Tabla1[[#This Row],[HORAS 35% ]] -> 0 | X54: =SUM(Tabla1[[#This Row],[C.HORA.35]],Tabla1[[#This Row],[C.HORA.25]]) -> 0 | Z54: =Tabla1[[#This Row],[T.HORAS]]*24 -> 0 | AA54: =Tabla1[[#This Row],[H.NORMALES]]*24 -> 0 | AB54: =Tabla1[[#This Row],[H.EXTRAS]]*24 -> 0 | AC54: =IF(J54=1,(((R54*24)*(L54/9))),0)+IF(J54=2,(((R54*24)*(L54/8))),0)+IF(J54=8,(((R54*24)*(L54/8))),0) -> 0 | AD54: =Tabla1[[#This Row],[COS.BASE 2]]/8 -> 0 | AE54: =Tabla1[[#This Row],[CST_H_E]]+Tabla1[[#This Row],[COS.BASE 2]] -> 0 | AF54: =+_xlfn.IFNA(INDEX(RUBRO!$W$2:$AA$732,MATCH(Tabla1[[#This Row],[FECHA ]],RUBRO!$W$2:$W$732,0),5)," ") -> 0 | AG54: =+_xlfn.IFNA(INDEX(RUBRO!$W$2:$AA$732,MATCH(Tabla1[[#This Row],[FECHA ]],RUBRO!$W$2:$W$732,0),2)," ") -> 0 | AH54: =IFERROR(Tabla1[[#This Row],[F]]*Tabla1[[#This Row],[COS.B+E]]," ") -> 0 | AI54: =IFERROR(Tabla1[[#This Row],[COS.B+E]]*Tabla1[[#This Row],[D]]," ") -> 0 | AJ54: =IFERROR(Tabla1[[#This Row],[F]]*#REF!," ") | AK54: =IFERROR(#REF!*Tabla1[[#This Row],[D]]," ") | AO54: =+Tabla1[[#This Row],[COS.B+E]]+Tabla1[[#This Row],[COS.F1]]+Tabla1[[#This Row],[COS.D1]]+Tabla1[[#This Row],[ALIMENTACION]]+Tabla1[[#This Row],[PRESTAMO]]+AN54 -> 0 | AP54: =+#REF!+Tabla1[[#This Row],[COS F2]]+Tabla1[[#This Row],[COS D2]]+Tabla1[[#This Row],[ALIMENTACION]]+Tabla1[[#This Row],[PRESTAMO]]+Tabla1[[#This Row],[PASAJES]] -> #REF!
A55: =TEXT(Tabla1[[#This Row],[FECHA ]],"DDDDD") -> viernes | B55: =_xlfn.IFNA(VLOOKUP(Tabla1[[#This Row],[DESTINO]],RUBRO!$Q$1:$R$9996,2,FALSE)," ") -> FALTA | C55: =WEEKNUM(Tabla1[[#This Row],[FECHA ]],2) -> 19 | D55: =TEXT(Tabla1[[#This Row],[FECHA ]],"MMM-YY") -> may-YY | E55: =VLOOKUP(Tabla1[[#This Row],[DNI ]],RUBRO!$F$1:$O$9996,7,FALSE) -> 5ta | F55: =VLOOKUP(Tabla1[[#This Row],[DNI ]],RUBRO!$F$1:$O$88,3,FALSE) -> MEC-04 | G55: =VLOOKUP(Tabla1[[#This Row],[DNI ]],RUBRO!$F$1:$O$9996,5,FALSE) -> MECANICO MONTAJISTA DE MAQUINARIA EXTRANJERA | H55: =VLOOKUP(Tabla1[[#This Row],[DNI ]],RUBRO!$F$1:$O$9996,6,FALSE) -> VARGAS TARRILLO GLOBER | I55: 44323 | J55: 4 | K55: 43878459 | L55: =VLOOKUP(Tabla1[[#This Row],[DNI ]],RUBRO!$F$2:$O$9996,8,FALSE) -> 79.78 | Q55: =(Tabla1[[#This Row],[SALIDA]]-Tabla1[[#This Row],[FIN ]])+(Tabla1[[#This Row],[INICIO]]-Tabla1[[#This Row],[INGRESO]]) -> 0 | R55: =IF(J55=1,IF(Q55>$AU$1,$AU$1,Q55),0)+IF(J55=2,IF(Q55>$AU$3,$AU$3,Q55),0)+IF(J55=8,IF(Q55>$AU$5,$AU$5,Q55),0) -> 0 | S55: =IF(J55=1,IF(Q55>$AU$1,(Q55-R55),0),0)+IF(J55=2,IF(Q55>$AU$3,(Q55-R55),0),0)+IF(J55=8,IF(Q55>$AU$5,(Q55-R55),0),0) -> 0 | V55: =(Tabla1[[#This Row],[COS.BASE 3]]*0.25+Tabla1[[#This Row],[COS.BASE 3]])*Tabla1[[#This Row],[HORAS 25 % ]] -> 0 | W55: =(Tabla1[[#This Row],[COS.BASE 3]]*0.35+Tabla1[[#This Row],[COS.BASE 3]])*Tabla1[[#This Row],[HORAS 35% ]] -> 0 | X55: =SUM(Tabla1[[#This Row],[C.HORA.35]],Tabla1[[#This Row],[C.HORA.25]]) -> 0 | Z55: =Tabla1[[#This Row],[T.HORAS]]*24 -> 0 | AA55: =Tabla1[[#This Row],[H.NORMALES]]*24 -> 0 | AB55: =Tabla1[[#This Row],[H.EXTRAS]]*24 -> 0 | AC55: =IF(J55=1,(((R55*24)*(L55/9))),0)+IF(J55=2,(((R55*24)*(L55/8))),0)+IF(J55=8,(((R55*24)*(L55/8))),0) -> 0 | AD55: =Tabla1[[#This Row],[COS.BASE 2]]/8 -> 0 | AE55: =Tabla1[[#This Row],[CST_H_E]]+Tabla1[[#This Row],[COS.BASE 2]] -> 0 | AF55: =+_xlfn.IFNA(INDEX(RUBRO!$W$2:$AA$732,MATCH(Tabla1[[#This Row],[FECHA ]],RUBRO!$W$2:$W$732,0),5)," ") -> 0 | AG55: =+_xlfn.IFNA(INDEX(RUBRO!$W$2:$AA$732,MATCH(Tabla1[[#This Row],[FECHA ]],RUBRO!$W$2:$W$732,0),2)," ") -> 0 | AH55: =IFERROR(Tabla1[[#This Row],[F]]*Tabla1[[#This Row],[COS.B+E]]," ") -> 0 | AI55: =IFERROR(Tabla1[[#This Row],[COS.B+E]]*Tabla1[[#This Row],[D]]," ") -> 0 | AJ55: =IFERROR(Tabla1[[#This Row],[F]]*#REF!," ") | AK55: =IFERROR(#REF!*Tabla1[[#This Row],[D]]," ") | AO55: =+Tabla1[[#This Row],[COS.B+E]]+Tabla1[[#This Row],[COS.F1]]+Tabla1[[#This Row],[COS.D1]]+Tabla1[[#This Row],[ALIMENTACION]]+Tabla1[[#This Row],[PRESTAMO]]+AN55 -> 0 | AP55: =+#REF!+Tabla1[[#This Row],[COS F2]]+Tabla1[[#This Row],[COS D2]]+Tabla1[[#This Row],[ALIMENTACION]]+Tabla1[[#This Row],[PRESTAMO]]+Tabla1[[#This Row],[PASAJES]] -> #REF!
A56: =TEXT(Tabla1[[#This Row],[FECHA ]],"DDDDD") -> viernes | B56: =_xlfn.IFNA(VLOOKUP(Tabla1[[#This Row],[DESTINO]],RUBRO!$Q$1:$R$9996,2,FALSE)," ") -> FALTA | C56: =WEEKNUM(Tabla1[[#This Row],[FECHA ]],2) -> 19 | D56: =TEXT(Tabla1[[#This Row],[FECHA ]],"MMM-YY") -> may-YY | E56: =VLOOKUP(Tabla1[[#This Row],[DNI ]],RUBRO!$F$1:$O$9996,7,FALSE) -> 5ta | F56: =VLOOKUP(Tabla1[[#This Row],[DNI ]],RUBRO!$F$1:$O$88,3,FALSE) -> MEC-04 | G56: =VLOOKUP(Tabla1[[#This Row],[DNI ]],RUBRO!$F$1:$O$9996,5,FALSE) -> MECANICO MONTAJISTA DE MAQUINARIA EXTRANJERA | H56: =VLOOKUP(Tabla1[[#This Row],[DNI ]],RUBRO!$F$1:$O$9996,6,FALSE) -> VARGAS TARRILLO OMAR ALEXANDER | I56: 44323 | J56: 4 | K56: 46578402 | L56: =VLOOKUP(Tabla1[[#This Row],[DNI ]],RUBRO!$F$2:$O$9996,8,FALSE) -> 103.42 | Q56: =(Tabla1[[#This Row],[SALIDA]]-Tabla1[[#This Row],[FIN ]])+(Tabla1[[#This Row],[INICIO]]-Tabla1[[#This Row],[INGRESO]]) -> 0 | R56: =IF(J56=1,IF(Q56>$AU$1,$AU$1,Q56),0)+IF(J56=2,IF(Q56>$AU$3,$AU$3,Q56),0)+IF(J56=8,IF(Q56>$AU$5,$AU$5,Q56),0) -> 0 | S56: =IF(J56=1,IF(Q56>$AU$1,(Q56-R56),0),0)+IF(J56=2,IF(Q56>$AU$3,(Q56-R56),0),0)+IF(J56=8,IF(Q56>$AU$5,(Q56-R56),0),0) -> 0 | V56: =(Tabla1[[#This Row],[COS.BASE 3]]*0.25+Tabla1[[#This Row],[COS.BASE 3]])*Tabla1[[#This Row],[HORAS 25 % ]] -> 0 | W56: =(Tabla1[[#This Row],[COS.BASE 3]]*0.35+Tabla1[[#This Row],[COS.BASE 3]])*Tabla1[[#This Row],[HORAS 35% ]] -> 0 | X56: =SUM(Tabla1[[#This Row],[C.HORA.35]],Tabla1[[#This Row],[C.HORA.25]]) -> 0 | Z56: =Tabla1[[#This Row],[T.HORAS]]*24 -> 0 | AA56: =Tabla1[[#This Row],[H.NORMALES]]*24 -> 0 | AB56: =Tabla1[[#This Row],[H.EXTRAS]]*24 -> 0 | AC56: =IF(J56=1,(((R56*24)*(L56/9))),0)+IF(J56=2,(((R56*24)*(L56/8))),0)+IF(J56=8,(((R56*24)*(L56/8))),0) -> 0 | AD56: =Tabla1[[#This Row],[COS.BASE 2]]/8 -> 0 | AE56: =Tabla1[[#This Row],[CST_H_E]]+Tabla1[[#This Row],[COS.BASE 2]] -> 0 | AF56: =+_xlfn.IFNA(INDEX(RUBRO!$W$2:$AA$732,MATCH(Tabla1[[#This Row],[FECHA ]],RUBRO!$W$2:$W$732,0),5)," ") -> 0 | AG56: =+_xlfn.IFNA(INDEX(RUBRO!$W$2:$AA$732,MATCH(Tabla1[[#This Row],[FECHA ]],RUBRO!$W$2:$W$732,0),2)," ") -> 0 | AH56: =IFERROR(Tabla1[[#This Row],[F]]*Tabla1[[#This Row],[COS.B+E]]," ") -> 0 | AI56: =IFERROR(Tabla1[[#This Row],[COS.B+E]]*Tabla1[[#This Row],[D]]," ") -> 0 | AJ56: =IFERROR(Tabla1[[#This Row],[F]]*#REF!," ") | AK56: =IFERROR(#REF!*Tabla1[[#This Row],[D]]," ") | AO56: =+Tabla1[[#This Row],[COS.B+E]]+Tabla1[[#This Row],[COS.F1]]+Tabla1[[#This Row],[COS.D1]]+Tabla1[[#This Row],[ALIMENTACION]]+Tabla1[[#This Row],[PRESTAMO]]+AN56 -> 0 | AP56: =+#REF!+Tabla1[[#This Row],[COS F2]]+Tabla1[[#This Row],[COS D2]]+Tabla1[[#This Row],[ALIMENTACION]]+Tabla1[[#This Row],[PRESTAMO]]+Tabla1[[#This Row],[PASAJES]] -> #REF!
A57: =TEXT(Tabla1[[#This Row],[FECHA ]],"DDDDD") -> viernes | B57: =_xlfn.IFNA(VLOOKUP(Tabla1[[#This Row],[DESTINO]],RUBRO!$Q$1:$R$9996,2,FALSE)," ") -> OBRA | C57: =WEEKNUM(Tabla1[[#This Row],[FECHA ]],2) -> 19 | D57: =TEXT(Tabla1[[#This Row],[FECHA ]],"MMM-YY") -> may-YY | E57: =VLOOKUP(Tabla1[[#This Row],[DNI ]],RUBRO!$F$1:$O$9996,7,FALSE) -> 5ta | F57: =VLOOKUP(Tabla1[[#This Row],[DNI ]],RUBRO!$F$1:$O$88,3,FALSE) -> #N/A | G57: =VLOOKUP(Tabla1[[#This Row],[DNI ]],RUBRO!$F$1:$O$9996,5,FALSE) -> PRACTICANTE | H57: =VLOOKUP(Tabla1[[#This Row],[DNI ]],RUBRO!$F$1:$O$9996,6,FALSE) -> VASQUEZ CHUPILLON KEVIN | I57: 44323 | J57: 2 | K57: 72814417 | L57: =VLOOKUP(Tabla1[[#This Row],[DNI ]],RUBRO!$F$2:$O$9996,8,FALSE) -> 35.76 | M57: 0.29166667 | N57: 0.54166667 | O57: 0.58333333 | P57: 0.83333333 | Q57: =(Tabla1[[#This Row],[SALIDA]]-Tabla1[[#This Row],[FIN ]])+(Tabla1[[#This Row],[INICIO]]-Tabla1[[#This Row],[INGRESO]]) -> 0.5 | R57: =IF(J57=1,IF(Q57>$AU$1,$AU$1,Q57),0)+IF(J57=2,IF(Q57>$AU$3,$AU$3,Q57),0)+IF(J57=8,IF(Q57>$AU$5,$AU$5,Q57),0) -> 0.33333333 | S57: =IF(J57=1,IF(Q57>$AU$1,(Q57-R57),0),0)+IF(J57=2,IF(Q57>$AU$3,(Q57-R57),0),0)+IF(J57=8,IF(Q57>$AU$5,(Q57-R57),0),0) -> 0.16666667 | V57: =(Tabla1[[#This Row],[COS.BASE 3]]*0.25+Tabla1[[#This Row],[COS.BASE 3]])*Tabla1[[#This Row],[HORAS 25 % ]] -> 0 | W57: =(Tabla1[[#This Row],[COS.BASE 3]]*0.35+Tabla1[[#This Row],[COS.BASE 3]])*Tabla1[[#This Row],[HORAS 35% ]] -> 0 | X57: =SUM(Tabla1[[#This Row],[C.HORA.35]],Tabla1[[#This Row],[C.HORA.25]]) -> 0 | Z57: =Tabla1[[#This Row],[T.HORAS]]*24 -> 12 | AA57: =Tabla1[[#This Row],[H.NORMALES]]*24 -> 8 | AB57: =Tabla1[[#This Row],[H.EXTRAS]]*24 -> 4 | AC57: =IF(J57=1,(((R57*24)*(L57/9))),0)+IF(J57=2,(((R57*24)*(L57/8))),0)+IF(J57=8,(((R57*24)*(L57/8))),0) -> 35.76 | AD57: =Tabla1[[#This Row],[COS.BASE 2]]/8 -> 4.47 | AE57: =Tabla1[[#This Row],[CST_H_E]]+Tabla1[[#This Row],[COS.BASE 2]] -> 35.76 | AF57: =+_xlfn.IFNA(INDEX(RUBRO!$W$2:$AA$732,MATCH(Tabla1[[#This Row],[FECHA ]],RUBRO!$W$2:$W$732,0),5)," ") -> 0 | AG57: =+_xlfn.IFNA(INDEX(RUBRO!$W$2:$AA$732,MATCH(Tabla1[[#This Row],[FECHA ]],RUBRO!$W$2:$W$732,0),2)," ") -> 0 | AH57: =IFERROR(Tabla1[[#This Row],[F]]*Tabla1[[#This Row],[COS.B+E]]," ") -> 0 | AI57: =IFERROR(Tabla1[[#This Row],[COS.B+E]]*Tabla1[[#This Row],[D]]," ") -> 0 | AJ57: =IFERROR(Tabla1[[#This Row],[F]]*#REF!," ") | AK57: =IFERROR(#REF!*Tabla1[[#This Row],[D]]," ") | AO57: =+Tabla1[[#This Row],[COS.B+E]]+Tabla1[[#This Row],[COS.F1]]+Tabla1[[#This Row],[COS.D1]]+Tabla1[[#This Row],[ALIMENTACION]]+Tabla1[[#This Row],[PRESTAMO]]+AN57 -> 35.76 | AP57: =+#REF!+Tabla1[[#This Row],[COS F2]]+Tabla1[[#This Row],[COS D2]]+Tabla1[[#This Row],[ALIMENTACION]]+Tabla1[[#This Row],[PRESTAMO]]+Tabla1[[#This Row],[PASAJES]] -> #REF!
A58: =TEXT(Tabla1[[#This Row],[FECHA ]],"DDDDD") -> viernes | B58: =_xlfn.IFNA(VLOOKUP(Tabla1[[#This Row],[DESTINO]],RUBRO!$Q$1:$R$9996,2,FALSE)," ") -> OBRA | C58: =WEEKNUM(Tabla1[[#This Row],[FECHA ]],2) -> 19 | D58: =TEXT(Tabla1[[#This Row],[FECHA ]],"MMM-YY") -> may-YY | E58: =VLOOKUP(Tabla1[[#This Row],[DNI ]],RUBRO!$F$1:$O$9996,7,FALSE) -> 5ta | F58: =VLOOKUP(Tabla1[[#This Row],[DNI ]],RUBRO!$F$1:$O$88,3,FALSE) -> MEC-04 | G58: =VLOOKUP(Tabla1[[#This Row],[DNI ]],RUBRO!$F$1:$O$9996,5,FALSE) -> MECANICO MONTAJISTA DE MAQUINARIA EXTRANJERA | H58: =VLOOKUP(Tabla1[[#This Row],[DNI ]],RUBRO!$F$1:$O$9996,6,FALSE) -> VASQUEZ GAMBOA JUAN JOSE | I58: 44323 | J58: 2 | K58: 45416906 | L58: =VLOOKUP(Tabla1[[#This Row],[DNI ]],RUBRO!$F$2:$O$9996,8,FALSE) -> 87 | M58: 0.29166667 | N58: 0.54166667 | O58: 0.58333333 | P58: 0.75 | Q58: =(Tabla1[[#This Row],[SALIDA]]-Tabla1[[#This Row],[FIN ]])+(Tabla1[[#This Row],[INICIO]]-Tabla1[[#This Row],[INGRESO]]) -> 0.41666667 | R58: =IF(J58=1,IF(Q58>$AU$1,$AU$1,Q58),0)+IF(J58=2,IF(Q58>$AU$3,$AU$3,Q58),0)+IF(J58=8,IF(Q58>$AU$5,$AU$5,Q58),0) -> 0.33333333 | S58: =IF(J58=1,IF(Q58>$AU$1,(Q58-R58),0),0)+IF(J58=2,IF(Q58>$AU$3,(Q58-R58),0),0)+IF(J58=8,IF(Q58>$AU$5,(Q58-R58),0),0) -> 0.083333333 | V58: =(Tabla1[[#This Row],[COS.BASE 3]]*0.25+Tabla1[[#This Row],[COS.BASE 3]])*Tabla1[[#This Row],[HORAS 25 % ]] -> 0 | W58: =(Tabla1[[#This Row],[COS.BASE 3]]*0.35+Tabla1[[#This Row],[COS.BASE 3]])*Tabla1[[#This Row],[HORAS 35% ]] -> 0 | X58: =SUM(Tabla1[[#This Row],[C.HORA.35]],Tabla1[[#This Row],[C.HORA.25]]) -> 0 | Z58: =Tabla1[[#This Row],[T.HORAS]]*24 -> 10 | AA58: =Tabla1[[#This Row],[H.NORMALES]]*24 -> 8 | AB58: =Tabla1[[#This Row],[H.EXTRAS]]*24 -> 2 | AC58: =IF(J58=1,(((R58*24)*(L58/9))),0)+IF(J58=2,(((R58*24)*(L58/8))),0)+IF(J58=8,(((R58*24)*(L58/8))),0) -> 87 | AD58: =Tabla1[[#This Row],[COS.BASE 2]]/8 -> 10.875 | AE58: =Tabla1[[#This Row],[CST_H_E]]+Tabla1[[#This Row],[COS.BASE 2]] -> 87 | AF58: =+_xlfn.IFNA(INDEX(RUBRO!$W$2:$AA$732,MATCH(Tabla1[[#This Row],[FECHA ]],RUBRO!$W$2:$W$732,0),5)," ") -> 0 | AG58: =+_xlfn.IFNA(INDEX(RUBRO!$W$2:$AA$732,MATCH(Tabla1[[#This Row],[FECHA ]],RUBRO!$W$2:$W$732,0),2)," ") -> 0 | AH58: =IFERROR(Tabla1[[#This Row],[F]]*Tabla1[[#This Row],[COS.B+E]]," ") -> 0 | AI58: =IFERROR(Tabla1[[#This Row],[COS.B+E]]*Tabla1[[#This Row],[D]]," ") -> 0 | AJ58: =IFERROR(Tabla1[[#This Row],[F]]*#REF!," ") | AK58: =IFERROR(#REF!*Tabla1[[#This Row],[D]]," ") | AO58: =+Tabla1[[#This Row],[COS.B+E]]+Tabla1[[#This Row],[COS.F1]]+Tabla1[[#This Row],[COS.D1]]+Tabla1[[#This Row],[ALIMENTACION]]+Tabla1[[#This Row],[PRESTAMO]]+AN58 -> 87 | AP58: =+#REF!+Tabla1[[#This Row],[COS F2]]+Tabla1[[#This Row],[COS D2]]+Tabla1[[#This Row],[ALIMENTACION]]+Tabla1[[#This Row],[PRESTAMO]]+Tabla1[[#This Row],[PASAJES]] -> #REF!
A59: =TEXT(Tabla1[[#This Row],[FECHA ]],"DDDDD") -> viernes | B59: =_xlfn.IFNA(VLOOKUP(Tabla1[[#This Row],[DESTINO]],RUBRO!$Q$1:$R$9996,2,FALSE)," ") -> OBRA | C59: =WEEKNUM(Tabla1[[#This Row],[FECHA ]],2) -> 19 | D59: =TEXT(Tabla1[[#This Row],[FECHA ]],"MMM-YY") -> may-YY | E59: =VLOOKUP(Tabla1[[#This Row],[DNI ]],RUBRO!$F$1:$O$9996,7,FALSE) -> 5ta | F59: =VLOOKUP(Tabla1[[#This Row],[DNI ]],RUBRO!$F$1:$O$88,3,FALSE) -> TEC-04 | G59: =VLOOKUP(Tabla1[[#This Row],[DNI ]],RUBRO!$F$1:$O$9996,5,FALSE) -> TECNICO MECANICO MONTAJISTA DE MAQUINARIA EXTRANJERA | H59: =VLOOKUP(Tabla1[[#This Row],[DNI ]],RUBRO!$F$1:$O$9996,6,FALSE) -> VASQUEZ TARRILLO LUIS | I59: 44323 | J59: 2 | K59: 44044783 | L59: =VLOOKUP(Tabla1[[#This Row],[DNI ]],RUBRO!$F$2:$O$9996,8,FALSE) -> 70.92 | M59: 0.29166667 | N59: 0.54166667 | O59: 0.58333333 | P59: 0.83333333 | Q59: =(Tabla1[[#This Row],[SALIDA]]-Tabla1[[#This Row],[FIN ]])+(Tabla1[[#This Row],[INICIO]]-Tabla1[[#This Row],[INGRESO]]) -> 0.5 | R59: =IF(J59=1,IF(Q59>$AU$1,$AU$1,Q59),0)+IF(J59=2,IF(Q59>$AU$3,$AU$3,Q59),0)+IF(J59=8,IF(Q59>$AU$5,$AU$5,Q59),0) -> 0.33333333 | S59: =IF(J59=1,IF(Q59>$AU$1,(Q59-R59),0),0)+IF(J59=2,IF(Q59>$AU$3,(Q59-R59),0),0)+IF(J59=8,IF(Q59>$AU$5,(Q59-R59),0),0) -> 0.16666667 | V59: =(Tabla1[[#This Row],[COS.BASE 3]]*0.25+Tabla1[[#This Row],[COS.BASE 3]])*Tabla1[[#This Row],[HORAS 25 % ]] -> 0 | W59: =(Tabla1[[#This Row],[COS.BASE 3]]*0.35+Tabla1[[#This Row],[COS.BASE 3]])*Tabla1[[#This Row],[HORAS 35% ]] -> 0 | X59: =SUM(Tabla1[[#This Row],[C.HORA.35]],Tabla1[[#This Row],[C.HORA.25]]) -> 0 | Z59: =Tabla1[[#This Row],[T.HORAS]]*24 -> 12 | AA59: =Tabla1[[#This Row],[H.NORMALES]]*24 -> 8 | AB59: =Tabla1[[#This Row],[H.EXTRAS]]*24 -> 4 | AC59: =IF(J59=1,(((R59*24)*(L59/9))),0)+IF(J59=2,(((R59*24)*(L59/8))),0)+IF(J59=8,(((R59*24)*(L59/8))),0) -> 70.92 | AD59: =Tabla1[[#This Row],[COS.BASE 2]]/8 -> 8.865 | AE59: =Tabla1[[#This Row],[CST_H_E]]+Tabla1[[#This Row],[COS.BASE 2]] -> 70.92 | AF59: =+_xlfn.IFNA(INDEX(RUBRO!$W$2:$AA$732,MATCH(Tabla1[[#This Row],[FECHA ]],RUBRO!$W$2:$W$732,0),5)," ") -> 0 | AG59: =+_xlfn.IFNA(INDEX(RUBRO!$W$2:$AA$732,MATCH(Tabla1[[#This Row],[FECHA ]],RUBRO!$W$2:$W$732,0),2)," ") -> 0 | AH59: =IFERROR(Tabla1[[#This Row],[F]]*Tabla1[[#This Row],[COS.B+E]]," ") -> 0 | AI59: =IFERROR(Tabla1[[#This Row],[COS.B+E]]*Tabla1[[#This Row],[D]]," ") -> 0 | AJ59: =IFERROR(Tabla1[[#This Row],[F]]*#REF!," ") | AK59: =IFERROR(#REF!*Tabla1[[#This Row],[D]]," ") | AO59: =+Tabla1[[#This Row],[COS.B+E]]+Tabla1[[#This Row],[COS.F1]]+Tabla1[[#This Row],[COS.D1]]+Tabla1[[#This Row],[ALIMENTACION]]+Tabla1[[#This Row],[PRESTAMO]]+AN59 -> 70.92 | AP59: =+#REF!+Tabla1[[#This Row],[COS F2]]+Tabla1[[#This Row],[COS D2]]+Tabla1[[#This Row],[ALIMENTACION]]+Tabla1[[#This Row],[PRESTAMO]]+Tabla1[[#This Row],[PASAJES]] -> #REF!
A60: =TEXT(Tabla1[[#This Row],[FECHA ]],"DDDDD") -> viernes | B60: =_xlfn.IFNA(VLOOKUP(Tabla1[[#This Row],[DESTINO]],RUBRO!$Q$1:$R$9996,2,FALSE)," ") -> OBRA | C60: =WEEKNUM(Tabla1[[#This Row],[FECHA ]],2) -> 19 | D60: =TEXT(Tabla1[[#This Row],[FECHA ]],"MMM-YY") -> may-YY | E60: =VLOOKUP(Tabla1[[#This Row],[DNI ]],RUBRO!$F$1:$O$9996,7,FALSE) -> 5ta | F60: =VLOOKUP(Tabla1[[#This Row],[DNI ]],RUBRO!$F$1:$O$88,3,FALSE) -> MAEME-03 | G60: =VLOOKUP(Tabla1[[#This Row],[DNI ]],RUBRO!$F$1:$O$9996,5,FALSE) -> MAESTRO ELECTRICO MONTAJISTA DE MAQUINARIA EXTRANJERA | H60: =VLOOKUP(Tabla1[[#This Row],[DNI ]],RUBRO!$F$1:$O$9996,6,FALSE) -> VELASQUEZ LIZA JOSE ROGELIO | I60: 44323 | J60: 2 | K60: 44685832 | L60: =VLOOKUP(Tabla1[[#This Row],[DNI ]],RUBRO!$F$2:$O$9996,8,FALSE) -> 88.47 | M60: 0.29166667 | N60: 0.54166667 | O60: 0.58333333 | P60: 0.75 | Q60: =(Tabla1[[#This Row],[SALIDA]]-Tabla1[[#This Row],[FIN ]])+(Tabla1[[#This Row],[INICIO]]-Tabla1[[#This Row],[INGRESO]]) -> 0.41666667 | R60: =IF(J60=1,IF(Q60>$AU$1,$AU$1,Q60),0)+IF(J60=2,IF(Q60>$AU$3,$AU$3,Q60),0)+IF(J60=8,IF(Q60>$AU$5,$AU$5,Q60),0) -> 0.33333333 | S60: =IF(J60=1,IF(Q60>$AU$1,(Q60-R60),0),0)+IF(J60=2,IF(Q60>$AU$3,(Q60-R60),0),0)+IF(J60=8,IF(Q60>$AU$5,(Q60-R60),0),0) -> 0.083333333 | V60: =(Tabla1[[#This Row],[COS.BASE 3]]*0.25+Tabla1[[#This Row],[COS.BASE 3]])*Tabla1[[#This Row],[HORAS 25 % ]] -> 0 | W60: =(Tabla1[[#This Row],[COS.BASE 3]]*0.35+Tabla1[[#This Row],[COS.BASE 3]])*Tabla1[[#This Row],[HORAS 35% ]] -> 0 | X60: =SUM(Tabla1[[#This Row],[C.HORA.35]],Tabla1[[#This Row],[C.HORA.25]]) -> 0 | Z60: =Tabla1[[#This Row],[T.HORAS]]*24 -> 10 | AA60: =Tabla1[[#This Row],[H.NORMALES]]*24 -> 8 | AB60: =Tabla1[[#This Row],[H.EXTRAS]]*24 -> 2 | AC60: =IF(J60=1,(((R60*24)*(L60/9))),0)+IF(J60=2,(((R60*24)*(L60/8))),0)+IF(J60=8,(((R60*24)*(L60/8))),0) -> 88.47 | AD60: =Tabla1[[#This Row],[COS.BASE 2]]/8 -> 11.05875 | AE60: =Tabla1[[#This Row],[CST_H_E]]+Tabla1[[#This Row],[COS.BASE 2]] -> 88.47 | AF60: =+_xlfn.IFNA(INDEX(RUBRO!$W$2:$AA$732,MATCH(Tabla1[[#This Row],[FECHA ]],RUBRO!$W$2:$W$732,0),5)," ") -> 0 | AG60: =+_xlfn.IFNA(INDEX(RUBRO!$W$2:$AA$732,MATCH(Tabla1[[#This Row],[FECHA ]],RUBRO!$W$2:$W$732,0),2)," ") -> 0 | AH60: =IFERROR(Tabla1[[#This Row],[F]]*Tabla1[[#This Row],[COS.B+E]]," ") -> 0 | AI60: =IFERROR(Tabla1[[#This Row],[COS.B+E]]*Tabla1[[#This Row],[D]]," ") -> 0 | AJ60: =IFERROR(Tabla1[[#This Row],[F]]*#REF!," ") | AK60: =IFERROR(#REF!*Tabla1[[#This Row],[D]]," ") | AO60: =+Tabla1[[#This Row],[COS.B+E]]+Tabla1[[#This Row],[COS.F1]]+Tabla1[[#This Row],[COS.D1]]+Tabla1[[#This Row],[ALIMENTACION]]+Tabla1[[#This Row],[PRESTAMO]]+AN60 -> 88.47 | AP60: =+#REF!+Tabla1[[#This Row],[COS F2]]+Tabla1[[#This Row],[COS D2]]+Tabla1[[#This Row],[ALIMENTACION]]+Tabla1[[#This Row],[PRESTAMO]]+Tabla1[[#This Row],[PASAJES]] -> #REF!
A61: =TEXT(Tabla1[[#This Row],[FECHA ]],"DDDDD") -> viernes | B61: =_xlfn.IFNA(VLOOKUP(Tabla1[[#This Row],[DESTINO]],RUBRO!$Q$1:$R$9996,2,FALSE)," ") -> PLANTA | C61: =WEEKNUM(Tabla1[[#This Row],[FECHA ]],2) -> 19 | D61: =TEXT(Tabla1[[#This Row],[FECHA ]],"MMM-YY") -> may-YY | E61: =VLOOKUP(Tabla1[[#This Row],[DNI ]],RUBRO!$F$1:$O$9996,7,FALSE) -> 5ta | F61: =VLOOKUP(Tabla1[[#This Row],[DNI ]],RUBRO!$F$1:$O$88,3,FALSE) -> TEC-05 | G61: =VLOOKUP(Tabla1[[#This Row],[DNI ]],RUBRO!$F$1:$O$9996,5,FALSE) -> TECNICO MECANICO MONTAJISTA DE NAVE INDUSTRIAL | H61: =VLOOKUP(Tabla1[[#This Row],[DNI ]],RUBRO!$F$1:$O$9996,6,FALSE) -> VENTURA CUBAS ALEXANDER JOHAN | I61: 44323 | J61: 1 | K61: 47749907 | L61: =VLOOKUP(Tabla1[[#This Row],[DNI ]],RUBRO!$F$2:$O$9996,8,FALSE) -> 80 | M61: 0.29166667 | N61: 0.54166667 | O61: 0.58333333 | P61: 0.75 | Q61: =(Tabla1[[#This Row],[SALIDA]]-Tabla1[[#This Row],[FIN ]])+(Tabla1[[#This Row],[INICIO]]-Tabla1[[#This Row],[INGRESO]]) -> 0.41666667 | R61: =IF(J61=1,IF(Q61>$AU$1,$AU$1,Q61),0)+IF(J61=2,IF(Q61>$AU$3,$AU$3,Q61),0)+IF(J61=8,IF(Q61>$AU$5,$AU$5,Q61),0) -> 0.375 | S61: =IF(J61=1,IF(Q61>$AU$1,(Q61-R61),0),0)+IF(J61=2,IF(Q61>$AU$3,(Q61-R61),0),0)+IF(J61=8,IF(Q61>$AU$5,(Q61-R61),0),0) -> 0.041666667 | V61: =(Tabla1[[#This Row],[COS.BASE 3]]*0.25+Tabla1[[#This Row],[COS.BASE 3]])*Tabla1[[#This Row],[HORAS 25 % ]] -> 0 | W61: =(Tabla1[[#This Row],[COS.BASE 3]]*0.35+Tabla1[[#This Row],[COS.BASE 3]])*Tabla1[[#This Row],[HORAS 35% ]] -> 0 | X61: =SUM(Tabla1[[#This Row],[C.HORA.35]],Tabla1[[#This Row],[C.HORA.25]]) -> 0 | Z61: =Tabla1[[#This Row],[T.HORAS]]*24 -> 10 | AA61: =Tabla1[[#This Row],[H.NORMALES]]*24 -> 9 | AB61: =Tabla1[[#This Row],[H.EXTRAS]]*24 -> 1 | AC61: =IF(J61=1,(((R61*24)*(L61/9))),0)+IF(J61=2,(((R61*24)*(L61/8))),0)+IF(J61=8,(((R61*24)*(L61/8))),0) -> 80 | AD61: =Tabla1[[#This Row],[COS.BASE 2]]/8 -> 10 | AE61: =Tabla1[[#This Row],[CST_H_E]]+Tabla1[[#This Row],[COS.BASE 2]] -> 80 | AF61: =+_xlfn.IFNA(INDEX(RUBRO!$W$2:$AA$732,MATCH(Tabla1[[#This Row],[FECHA ]],RUBRO!$W$2:$W$732,0),5)," ") -> 0 | AG61: =+_xlfn.IFNA(INDEX(RUBRO!$W$2:$AA$732,MATCH(Tabla1[[#This Row],[FECHA ]],RUBRO!$W$2:$W$732,0),2)," ") -> 0 | AH61: =IFERROR(Tabla1[[#This Row],[F]]*Tabla1[[#This Row],[COS.B+E]]," ") -> 0 | AI61: =IFERROR(Tabla1[[#This Row],[COS.B+E]]*Tabla1[[#This Row],[D]]," ") -> 0 | AJ61: =IFERROR(Tabla1[[#This Row],[F]]*#REF!," ") | AK61: =IFERROR(#REF!*Tabla1[[#This Row],[D]]," ") | AO61: =+Tabla1[[#This Row],[COS.B+E]]+Tabla1[[#This Row],[COS.F1]]+Tabla1[[#This Row],[COS.D1]]+Tabla1[[#This Row],[ALIMENTACION]]+Tabla1[[#This Row],[PRESTAMO]]+AN61 -> 80 | AP61: =+#REF!+Tabla1[[#This Row],[COS F2]]+Tabla1[[#This Row],[COS D2]]+Tabla1[[#This Row],[ALIMENTACION]]+Tabla1[[#This Row],[PRESTAMO]]+Tabla1[[#This Row],[PASAJES]] -> #REF!
A62: =TEXT(Tabla1[[#This Row],[FECHA ]],"DDDDD") -> viernes | B62: =_xlfn.IFNA(VLOOKUP(Tabla1[[#This Row],[DESTINO]],RUBRO!$Q$1:$R$9996,2,FALSE)," ") -> OBRA | C62: =WEEKNUM(Tabla1[[#This Row],[FECHA ]],2) -> 19 | D62: =TEXT(Tabla1[[#This Row],[FECHA ]],"MMM-YY") -> may-YY | E62: =VLOOKUP(Tabla1[[#This Row],[DNI ]],RUBRO!$F$1:$O$9996,7,FALSE) -> 5ta | F62: =VLOOKUP(Tabla1[[#This Row],[DNI ]],RUBRO!$F$1:$O$88,3,FALSE) -> MAE-08 | G62: =VLOOKUP(Tabla1[[#This Row],[DNI ]],RUBRO!$F$1:$O$9996,5,FALSE) -> MAESTRO PINTOR | H62: =VLOOKUP(Tabla1[[#This Row],[DNI ]],RUBRO!$F$1:$O$9996,6,FALSE) -> ZETA DELGADO DERWIS YENNER | I62: 44323 | J62: 2 | K62: 46859101 | L62: =VLOOKUP(Tabla1[[#This Row],[DNI ]],RUBRO!$F$2:$O$9996,8,FALSE) -> 70 | M62: 0.29166667 | N62: 0.54166667 | O62: 0.58333333 | P62: 0.75 | Q62: =(Tabla1[[#This Row],[SALIDA]]-Tabla1[[#This Row],[FIN ]])+(Tabla1[[#This Row],[INICIO]]-Tabla1[[#This Row],[INGRESO]]) -> 0.41666667 | R62: =IF(J62=1,IF(Q62>$AU$1,$AU$1,Q62),0)+IF(J62=2,IF(Q62>$AU$3,$AU$3,Q62),0)+IF(J62=8,IF(Q62>$AU$5,$AU$5,Q62),0) -> 0.33333333 | S62: =IF(J62=1,IF(Q62>$AU$1,(Q62-R62),0),0)+IF(J62=2,IF(Q62>$AU$3,(Q62-R62),0),0)+IF(J62=8,IF(Q62>$AU$5,(Q62-R62),0),0) -> 0.083333333 | V62: =(Tabla1[[#This Row],[COS.BASE 3]]*0.25+Tabla1[[#This Row],[COS.BASE 3]])*Tabla1[[#This Row],[HORAS 25 % ]] -> 0 | W62: =(Tabla1[[#This Row],[COS.BASE 3]]*0.35+Tabla1[[#This Row],[COS.BASE 3]])*Tabla1[[#This Row],[HORAS 35% ]] -> 0 | X62: =SUM(Tabla1[[#This Row],[C.HORA.35]],Tabla1[[#This Row],[C.HORA.25]]) -> 0 | Z62: =Tabla1[[#This Row],[T.HORAS]]*24 -> 10 | AA62: =Tabla1[[#This Row],[H.NORMALES]]*24 -> 8 | AB62: =Tabla1[[#This Row],[H.EXTRAS]]*24 -> 2 | AC62: =IF(J62=1,(((R62*24)*(L62/9))),0)+IF(J62=2,(((R62*24)*(L62/8))),0)+IF(J62=8,(((R62*24)*(L62/8))),0) -> 70 | AD62: =Tabla1[[#This Row],[COS.BASE 2]]/8 -> 8.75 | AE62: =Tabla1[[#This Row],[CST_H_E]]+Tabla1[[#This Row],[COS.BASE 2]] -> 70 | AF62: =+_xlfn.IFNA(INDEX(RUBRO!$W$2:$AA$732,MATCH(Tabla1[[#This Row],[FECHA ]],RUBRO!$W$2:$W$732,0),5)," ") -> 0 | AG62: =+_xlfn.IFNA(INDEX(RUBRO!$W$2:$AA$732,MATCH(Tabla1[[#This Row],[FECHA ]],RUBRO!$W$2:$W$732,0),2)," ") -> 0 | AH62: =IFERROR(Tabla1[[#This Row],[F]]*Tabla1[[#This Row],[COS.B+E]]," ") -> 0 | AI62: =IFERROR(Tabla1[[#This Row],[COS.B+E]]*Tabla1[[#This Row],[D]]," ") -> 0 | AJ62: =IFERROR(Tabla1[[#This Row],[F]]*#REF!," ") | AK62: =IFERROR(#REF!*Tabla1[[#This Row],[D]]," ") | AO62: =+Tabla1[[#This Row],[COS.B+E]]+Tabla1[[#This Row],[COS.F1]]+Tabla1[[#This Row],[COS.D1]]+Tabla1[[#This Row],[ALIMENTACION]]+Tabla1[[#This Row],[PRESTAMO]]+AN62 -> 70 | AP62: =+#REF!+Tabla1[[#This Row],[COS F2]]+Tabla1[[#This Row],[COS D2]]+Tabla1[[#This Row],[ALIMENTACION]]+Tabla1[[#This Row],[PRESTAMO]]+Tabla1[[#This Row],[PASAJES]] -> #REF!
A63: =TEXT(Tabla1[[#This Row],[FECHA ]],"DDDDD") -> sábado | B63: =_xlfn.IFNA(VLOOKUP(Tabla1[[#This Row],[DESTINO]],RUBRO!$Q$1:$R$9996,2,FALSE)," ") -> PLANTA | C63: =WEEKNUM(Tabla1[[#This Row],[FECHA ]],2) -> 19 | D63: =TEXT(Tabla1[[#This Row],[FECHA ]],"MMM-YY") -> may-YY | E63: =VLOOKUP(Tabla1[[#This Row],[DNI ]],RUBRO!$F$1:$O$9996,7,FALSE) -> 5ta | F63: =VLOOKUP(Tabla1[[#This Row],[DNI ]],RUBRO!$F$1:$O$88,3,FALSE) -> TEC-02 | G63: =VLOOKUP(Tabla1[[#This Row],[DNI ]],RUBRO!$F$1:$O$9996,5,FALSE) -> TECNICO MECANICO MONTAJISTA DE MAQUINARIA | H63: =VLOOKUP(Tabla1[[#This Row],[DNI ]],RUBRO!$F$1:$O$9996,6,FALSE) -> ALVAREZ ALVINES JUAN MANUEL | I63: 44324 | J63: 1 | K63: 46108491 | L63: =VLOOKUP(Tabla1[[#This Row],[DNI ]],RUBRO!$F$2:$O$9996,8,FALSE) -> 50 | M63: 0.29166667 | P63: 0.58333333 | Q63: =(Tabla1[[#This Row],[SALIDA]]-Tabla1[[#This Row],[FIN ]])+(Tabla1[[#This Row],[INICIO]]-Tabla1[[#This Row],[INGRESO]]) -> 0.29166667 | R63: =IF(J63=1,IF(Q63>$AU$1,$AU$1,Q63),0)+IF(J63=2,IF(Q63>$AU$3,$AU$3,Q63),0)+IF(J63=8,IF(Q63>$AU$5,$AU$5,Q63),0) -> 0.29166667 | S63: =IF(J63=1,IF(Q63>$AU$1,(Q63-R63),0),0)+IF(J63=2,IF(Q63>$AU$3,(Q63-R63),0),0)+IF(J63=8,IF(Q63>$AU$5,(Q63-R63),0),0) -> 0 | V63: =(Tabla1[[#This Row],[COS.BASE 3]]*0.25+Tabla1[[#This Row],[COS.BASE 3]])*Tabla1[[#This Row],[HORAS 25 % ]] -> 0 | W63: =(Tabla1[[#This Row],[COS.BASE 3]]*0.35+Tabla1[[#This Row],[COS.BASE 3]])*Tabla1[[#This Row],[HORAS 35% ]] -> 0 | X63: =SUM(Tabla1[[#This Row],[C.HORA.35]],Tabla1[[#This Row],[C.HORA.25]]) -> 0 | Z63: =Tabla1[[#This Row],[T.HORAS]]*24 -> 7 | AA63: =Tabla1[[#This Row],[H.NORMALES]]*24 -> 7 | AB63: =Tabla1[[#This Row],[H.EXTRAS]]*24 -> 0 | AC63: =IF(J63=1,(((R63*24)*(L63/9))),0)+IF(J63=2,(((R63*24)*(L63/8))),0)+IF(J63=8,(((R63*24)*(L63/8))),0) -> 38.888889 | AD63: =Tabla1[[#This Row],[COS.BASE 2]]/8 -> 4.8611111 | AE63: =Tabla1[[#This Row],[CST_H_E]]+Tabla1[[#This Row],[COS.BASE 2]] -> 38.888889 | AF63: =+_xlfn.IFNA(INDEX(RUBRO!$W$2:$AA$732,MATCH(Tabla1[[#This Row],[FECHA ]],RUBRO!$W$2:$W$732,0),5)," ") -> 0 | AG63: =+_xlfn.IFNA(INDEX(RUBRO!$W$2:$AA$732,MATCH(Tabla1[[#This Row],[FECHA ]],RUBRO!$W$2:$W$732,0),2)," ") -> 0 | AH63: =IFERROR(Tabla1[[#This Row],[F]]*Tabla1[[#This Row],[COS.B+E]]," ") -> 0 | AI63: =IFERROR(Tabla1[[#This Row],[COS.B+E]]*Tabla1[[#This Row],[D]]," ") -> 0 | AJ63: =IFERROR(Tabla1[[#This Row],[F]]*#REF!," ") | AK63: =IFERROR(#REF!*Tabla1[[#This Row],[D]]," ") | AO63: =+Tabla1[[#This Row],[COS.B+E]]+Tabla1[[#This Row],[COS.F1]]+Tabla1[[#This Row],[COS.D1]]+Tabla1[[#This Row],[ALIMENTACION]]+Tabla1[[#This Row],[PRESTAMO]]+AN63 -> 38.888889 | AP63: =+#REF!+Tabla1[[#This Row],[COS F2]]+Tabla1[[#This Row],[COS D2]]+Tabla1[[#This Row],[ALIMENTACION]]+Tabla1[[#This Row],[PRESTAMO]]+Tabla1[[#This Row],[PASAJES]] -> #REF!
A64: =TEXT(Tabla1[[#This Row],[FECHA ]],"DDDDD") -> sábado | B64: =_xlfn.IFNA(VLOOKUP(Tabla1[[#This Row],[DESTINO]],RUBRO!$Q$1:$R$9996,2,FALSE)," ") -> FALTA | C64: =WEEKNUM(Tabla1[[#This Row],[FECHA ]],2) -> 19 | D64: =TEXT(Tabla1[[#This Row],[FECHA ]],"MMM-YY") -> may-YY | E64: =VLOOKUP(Tabla1[[#This Row],[DNI ]],RUBRO!$F$1:$O$9996,7,FALSE) -> 4ta | F64: =VLOOKUP(Tabla1[[#This Row],[DNI ]],RUBRO!$F$1:$O$88,3,FALSE) -> OPE-03 | G64: =VLOOKUP(Tabla1[[#This Row],[DNI ]],RUBRO!$F$1:$O$9996,5,FALSE) -> OPERARIO ELECTRICO | H64: =VLOOKUP(Tabla1[[#This Row],[DNI ]],RUBRO!$F$1:$O$9996,6,FALSE) -> AYALA RAMIREZ RUBEN ISAI | I64: 44324 | J64: 4 | K64: 75557820 | L64: =VLOOKUP(Tabla1[[#This Row],[DNI ]],RUBRO!$F$2:$O$9996,8,FALSE) -> 50 | Q64: =(Tabla1[[#This Row],[SALIDA]]-Tabla1[[#This Row],[FIN ]])+(Tabla1[[#This Row],[INICIO]]-Tabla1[[#This Row],[INGRESO]]) -> 0 | R64: =IF(J64=1,IF(Q64>$AU$1,$AU$1,Q64),0)+IF(J64=2,IF(Q64>$AU$3,$AU$3,Q64),0)+IF(J64=8,IF(Q64>$AU$5,$AU$5,Q64),0) -> 0 | S64: =IF(J64=1,IF(Q64>$AU$1,(Q64-R64),0),0)+IF(J64=2,IF(Q64>$AU$3,(Q64-R64),0),0)+IF(J64=8,IF(Q64>$AU$5,(Q64-R64),0),0) -> 0 | V64: =(Tabla1[[#This Row],[COS.BASE 3]]*0.25+Tabla1[[#This Row],[COS.BASE 3]])*Tabla1[[#This Row],[HORAS 25 % ]] -> 0 | W64: =(Tabla1[[#This Row],[COS.BASE 3]]*0.35+Tabla1[[#This Row],[COS.BASE 3]])*Tabla1[[#This Row],[HORAS 35% ]] -> 0 | X64: =SUM(Tabla1[[#This Row],[C.HORA.35]],Tabla1[[#This Row],[C.HORA.25]]) -> 0 | Z64: =Tabla1[[#This Row],[T.HORAS]]*24 -> 0 | AA64: =Tabla1[[#This Row],[H.NORMALES]]*24 -> 0 | AB64: =Tabla1[[#This Row],[H.EXTRAS]]*24 -> 0 | AC64: =IF(J64=1,(((R64*24)*(L64/9))),0)+IF(J64=2,(((R64*24)*(L64/8))),0)+IF(J64=8,(((R64*24)*(L64/8))),0) -> 0 | AD64: =Tabla1[[#This Row],[COS.BASE 2]]/8 -> 0 | AE64: =Tabla1[[#This Row],[CST_H_E]]+Tabla1[[#This Row],[COS.BASE 2]] -> 0 | AF64: =+_xlfn.IFNA(INDEX(RUBRO!$W$2:$AA$732,MATCH(Tabla1[[#This Row],[FECHA ]],RUBRO!$W$2:$W$732,0),5)," ") -> 0 | AG64: =+_xlfn.IFNA(INDEX(RUBRO!$W$2:$AA$732,MATCH(Tabla1[[#This Row],[FECHA ]],RUBRO!$W$2:$W$732,0),2)," ") -> 0 | AH64: =IFERROR(Tabla1[[#This Row],[F]]*Tabla1[[#This Row],[COS.B+E]]," ") -> 0 | AI64: =IFERROR(Tabla1[[#This Row],[COS.B+E]]*Tabla1[[#This Row],[D]]," ") -> 0 | AJ64: =IFERROR(Tabla1[[#This Row],[F]]*#REF!," ") | AK64: =IFERROR(#REF!*Tabla1[[#This Row],[D]]," ") | AO64: =+Tabla1[[#This Row],[COS.B+E]]+Tabla1[[#This Row],[COS.F1]]+Tabla1[[#This Row],[COS.D1]]+Tabla1[[#This Row],[ALIMENTACION]]+Tabla1[[#This Row],[PRESTAMO]]+AN64 -> 0 | AP64: =+#REF!+Tabla1[[#This Row],[COS F2]]+Tabla1[[#This Row],[COS D2]]+Tabla1[[#This Row],[ALIMENTACION]]+Tabla1[[#This Row],[PRESTAMO]]+Tabla1[[#This Row],[PASAJES]] -> #REF!
A65: =TEXT(Tabla1[[#This Row],[FECHA ]],"DDDDD") -> sábado | B65: =_xlfn.IFNA(VLOOKUP(Tabla1[[#This Row],[DESTINO]],RUBRO!$Q$1:$R$9996,2,FALSE)," ") -> OBRA | C65: =WEEKNUM(Tabla1[[#This Row],[FECHA ]],2) -> 19 | D65: =TEXT(Tabla1[[#This Row],[FECHA ]],"MMM-YY") -> may-YY | E65: =VLOOKUP(Tabla1[[#This Row],[DNI ]],RUBRO!$F$1:$O$9996,7,FALSE) -> 5ta | F65: =VLOOKUP(Tabla1[[#This Row],[DNI ]],RUBRO!$F$1:$O$88,3,FALSE) -> OPE-03 | G65: =VLOOKUP(Tabla1[[#This Row],[DNI ]],RUBRO!$F$1:$O$9996,5,FALSE) -> OPERARIO ELECTRICO | H65: =VLOOKUP(Tabla1[[#This Row],[DNI ]],RUBRO!$F$1:$O$9996,6,FALSE) -> BARRAGAN SALAZAR JHONATAN PEDRO | I65: 44324 | J65: 2 | K65: 46801821 | L65: =VLOOKUP(Tabla1[[#This Row],[DNI ]],RUBRO!$F$2:$O$9996,8,FALSE) -> 43.5 | M65: 0.29166667 | P65: 0.625 | Q65: =(Tabla1[[#This Row],[SALIDA]]-Tabla1[[#This Row],[FIN ]])+(Tabla1[[#This Row],[INICIO]]-Tabla1[[#This Row],[INGRESO]]) -> 0.33333333 | R65: =IF(J65=1,IF(Q65>$AU$1,$AU$1,Q65),0)+IF(J65=2,IF(Q65>$AU$3,$AU$3,Q65),0)+IF(J65=8,IF(Q65>$AU$5,$AU$5,Q65),0) -> 0.33333333 | S65: =IF(J65=1,IF(Q65>$AU$1,(Q65-R65),0),0)+IF(J65=2,IF(Q65>$AU$3,(Q65-R65),0),0)+IF(J65=8,IF(Q65>$AU$5,(Q65-R65),0),0) -> 0 | V65: =(Tabla1[[#This Row],[COS.BASE 3]]*0.25+Tabla1[[#This Row],[COS.BASE 3]])*Tabla1[[#This Row],[HORAS 25 % ]] -> 0 | W65: =(Tabla1[[#This Row],[COS.BASE 3]]*0.35+Tabla1[[#This Row],[COS.BASE 3]])*Tabla1[[#This Row],[HORAS 35% ]] -> 0 | X65: =SUM(Tabla1[[#This Row],[C.HORA.35]],Tabla1[[#This Row],[C.HORA.25]]) -> 0 | Z65: =Tabla1[[#This Row],[T.HORAS]]*24 -> 8 | AA65: =Tabla1[[#This Row],[H.NORMALES]]*24 -> 8 | AB65: =Tabla1[[#This Row],[H.EXTRAS]]*24 -> 0 | AC65: =IF(J65=1,(((R65*24)*(L65/9))),0)+IF(J65=2,(((R65*24)*(L65/8))),0)+IF(J65=8,(((R65*24)*(L65/8))),0) -> 43.5 | AD65: =Tabla1[[#This Row],[COS.BASE 2]]/8 -> 5.4375 | AE65: =Tabla1[[#This Row],[CST_H_E]]+Tabla1[[#This Row],[COS.BASE 2]] -> 43.5 | AF65: =+_xlfn.IFNA(INDEX(RUBRO!$W$2:$AA$732,MATCH(Tabla1[[#This Row],[FECHA ]],RUBRO!$W$2:$W$732,0),5)," ") -> 0 | AG65: =+_xlfn.IFNA(INDEX(RUBRO!$W$2:$AA$732,MATCH(Tabla1[[#This Row],[FECHA ]],RUBRO!$W$2:$W$732,0),2)," ") -> 0 | AH65: =IFERROR(Tabla1[[#This Row],[F]]*Tabla1[[#This Row],[COS.B+E]]," ") -> 0 | AI65: =IFERROR(Tabla1[[#This Row],[COS.B+E]]*Tabla1[[#This Row],[D]]," ") -> 0 | AJ65: =IFERROR(Tabla1[[#This Row],[F]]*#REF!," ") | AK65: =IFERROR(#REF!*Tabla1[[#This Row],[D]]," ") | AO65: =+Tabla1[[#This Row],[COS.B+E]]+Tabla1[[#This Row],[COS.F1]]+Tabla1[[#This Row],[COS.D1]]+Tabla1[[#This Row],[ALIMENTACION]]+Tabla1[[#This Row],[PRESTAMO]]+AN65 -> 43.5 | AP65: =+#REF!+Tabla1[[#This Row],[COS F2]]+Tabla1[[#This Row],[COS D2]]+Tabla1[[#This Row],[ALIMENTACION]]+Tabla1[[#This Row],[PRESTAMO]]+Tabla1[[#This Row],[PASAJES]] -> #REF!
